Workbook
Name Activitiesbalance: Graph!$G$29:INDEX(Graph!$G$29:$G$40,COUNT(Graph!$G$29:$G$40))
Name ActivitiesWith: Graph!$G$59:INDEX(Graph!$G$59:$G$70,COUNT(Graph!$G$59:$G$70))
Name ActivitiesWithout: Graph!$G$44:INDEX(Graph!$G$44:$G$55,COUNT(Graph!$G$44:$G$55))
Name AMWS_Breeding_Swine_HP_titles: IPCC!$A$2487:$P$2487
Name AMWS_Chicken_broiler_LP_titles: IPCC!$A$2640:$P$2640
Name AMWS_Growing_Swine_HP_titles: IPCC!$A$2521:$P$2521
Name AWMS_Breeding_Swine_LP_titles: IPCC!$A$2504:$P$2504
Name AWMS_Chicken_broiler_HP_titles: IPCC!$A$2623:$P$2623
Name AWMS_Chicken_Layer_Default_titles: IPCC!$A$2606:$P$2606
Name AWMS_Dairy_Buffalo_titles: IPCC!$A$2453:$P$2453
Name AWMS_Dairy_Cattle_titles: IPCC!$A$2419:$P$2419
Name AWMS_Deer_titles: IPCC!$A$2691:$P$2691
Name AWMS_Goat_titles: IPCC!$A$2589:$P$2589
Name AWMS_Growing_Swine_LP_titles: IPCC!$A$2538:$P$2538
Name AWMS_Ostrich_titles: IPCC!$A$2674:$P$2674
Name AWMS_Other_Buffalo_titles: IPCC!$A$2470:$P$2470
Name AWMS_Other_Cattle_titles: IPCC!$A$2436:$P$2436
Name AWMS_Other_Grazing_titles: IPCC!$A$2657:$P$2657
Name AWMS_Other_Sheep_titles: IPCC!$A$2555:$P$2555
Name AWMS_Sheep_dairy_titles: IPCC!$A$2572:$P$2572
Name Boreal: defo!$D$9:$D$14
Name Boreal2: affo!$D$8:$D$13
Name CH4_man_Camel_HP_titles: IPCC!$A$2912:$P$2912
Name CH4_man_Camel_LP_titles: IPCC!$A$2929:$P$2929
Name CH4_man_Dairy_Cattle_HP_titles: IPCC!$A$2708:$P$2708
Name CH4_man_Dairy_Cattle_LP_titles: IPCC!$A$2725:$P$2725
Name CH4_man_Goat_HP_titles: IPCC!$A$2878:$P$2878
Name CH4_man_Goat_LP_titles: IPCC!$A$2895:$P$2895
Name CH4_man_Horse_HP_titles: IPCC!$A$2946:$P$2946
Name CH4_man_Horse_LP_titles: IPCC!$A$2963:$P$2963
Name CH4_man_Mule_HP_titles: IPCC!$A$2980:$P$2980
Name CH4_man_Mule_LP_titles: IPCC!$A$2997:$P$2997
Name CH4_man_Other_Cattle_HP_titles: IPCC!$A$2742:$P$2742
Name CH4_man_Other_Cattle_LP_titles: IPCC!$A$2759:$P$2759
Name CH4_man_Poultry_HP_titles: IPCC!$A$2810:$P$2810
Name CH4_man_Poultry_LP_titles: IPCC!$A$2827:$P$2827
Name CH4_man_Sheep_HP_titles: IPCC!$A$2844:$P$2844
Name CH4_man_Sheep_LP_titles: IPCC!$A$2861:$P$2861
Name CH4_man_Swine_HP_titles: IPCC!$A$2776:$P$2776
Name CH4_man_Swine_LP_titles: IPCC!$A$2793:$P$2793
Name clim_moist: list!$I$8
Name clim_moist_cont: list!$I$9
Name clim3: list!$I$12
Name climate: '1.Description'!$Q$10
Name climate2: list!$I$11
Name continent: '1.Description'!$Q$8
Name continent_selected: '1.Description'!$Q$8
Name CoolTemperate: defo!$C$9:$C$18
Name CoolTemperate2: affo!$C$8:$C$17
Name country_selected: '1.Description'!$Q$9
Name EF_DIRECT_N2O_manure_mngt_cattle_poultry_pigs_titles: IPCC!$A$3065:$P$3065
Name EF_DIRECT_N2O_manure_mngt_Sheeps_others_titles: IPCC!$A$3082:$P$3082
Name eq_agrof_systems: OFFSET(list!$F$73, 1, MATCH(clim_moist, list!$F$73:$O$73,0)-1,COUNTA(OFFSET(list!$F$73, 1,MATCH(clim_moist, list!$F$73:$O$73,0)-1,10,1)),1)
Name equation: INDEX((TabBoreal[Boreal],Tabcooltemp[Cool Temperate],TabTrop[Tropical],TabTrMon[Tropical Montane],TabWarm[Warm Temperate]),,,MATCH(climate, list!$F$21:$J$21,0))
Name Error_Message: '3.Cropland'!$R$37
Name fluxesbalance: Graph!$H$29:INDEX(Graph!$H$29:$H$40,COUNT(Graph!$H$29:$H$40))
Name Frac_leach_all_categories_titles: IPCC!$A$3184:$P$3184
Name Frac_vol_dairy_cow_titles: IPCC!$A$3116:$P$3116
Name Frac_vol_Other_Animal_titles: IPCC!$A$3167:$P$3167
Name Frac_vol_Other_Cattle_titles: IPCC!$A$3150:$P$3150

Sheet 0.Start
B1: EX-ACT version 9 is based on the 2019 Refinement to the 2006 IPCC Guidelines for National Greenhouse Gas Inventories, their 2013 Supplement for Wetlands, as well as on FAOSTAT, UNFCCC, IHH, FEUD and other relevant scientific sources.
AD4: version 9.3.5
B45: EX-ACT is a designed to support decision makers within the governments, private sector and civil society organizations to calculate greenhouse gas emissions using IPCC methdoologies. EX-ACT can be used in the project (or programme) design phase as well as for on-going and ex-post evaluations of interventions in agriculture (the AFOLU sector, fisheries, aquaculture, inputs and infrastructure).
B46: EX-ACT v9 has been developped by FAO's Agrifood Economics Division with the support of the World Bank and Agence Française de Développement.
B47: Website: | C47: http://www.fao.org/tc/exact/ex-act-home/en/
B48: Contact: | C48: EX-ACT@fao.org
B51: DISCLAIMER FAO declines all responsibility for errors or deficiencies in the database or software or in the documentation accompanying it, for program maintenance and upgrading as well as for any damage that may arise from them. FAO also declines any responsibility for updating the data and assumes no responsibility for errors and omissions in the data provided. Users are, however, kindly asked to report any errors or deficiencies in this product to FAO.
B52: The choices of calculation made in this tool are those of the author(s) and do not necessarily reflect the views and choices of the Food and Agriculture Organization of the United Nations.
B54: © FAO (2021) FAO encourages the use, reproduction and dissemination of material in this product. Except where otherwise indicated, material may be copied, downloaded and printed for private study, research and teaching purposes, or for use in non-commercial products or services, provided that appropriate acknowledgement of FAO as the source and copyright holder is given and that FAO’s endorsement of users’ views, products or services is not implied in any way. All requests for translation and adaptation rights, and for resale and other commercial use rights should be made via www.fao.org/contact-us/licence-request or addressed to copyright@fao.org
B59: Terms of Use for the EX-ACT: Ex-Ante Carbon-balance Tool
B60: General Provisions
B61: To support efforts towards forest monitoring, the Food and Agriculture Organization of the United Nations (FAO) has developed the EX-ACT: Ex-Ante Carbon-balance Tool to help countries identify capacity gaps and weaknesses and address their real needs in a targeted manner.
B62: The EX-ACT: Ex-Ante Carbon-balance Tool is excel-based.
B63: The Ex-Ante Carbon-balance Tool (EX-ACT) is an appraisal system developed by FAO providing estimates of the impact of agriculture and forestry development projects, programmes and policies on the carbon-balance.
B64: The carbon-balance is defined as the net balance from all greenhouse gases (GHGs) expressed in CO2 equivalent that were emitted or sequestered due to project implementation as compared to a business-as-usual scenario.
B65: EX-ACT is a land-based accounting system, estimating C stock changes (i.e. emissions or sinks of CO2) as well as GHG emissions per unit of land, expressed in equivalent tonnes of CO2 per hectare and year. The tool helps project designers to estimate and prioritize project activities with high benefits in economic and climate change mitigation terms. The amount of GHG mitigation may also be used as part of economic analyses as well as for the application for additional project funds.
B66: EX-ACT can be applied on a wide range of development projects from all Agriculture, Forestry and Other Land Use (AFOLU) sub-sectors, including besides others projects on climate change mitigation, sustainable land management, watershed development, production intensification, food security, livestock, forest management or land use change. Furthermore, it is cost effective, requires a comparatively small amount of data, and has resources (tables, maps) which can help find the required information. While EX-ACT is mostly used at project level it may easily be up scaled to the programme/sector level and can also be used for policy analysis.
B67: 1. By using the EX-ACT: Ex-Ante Carbon-balance Tool (hereinafter referred to as the “Tool”), you acknowledge and accept to be bound by these Terms of Use, and the FAO’s Terms and Conditions for use of its website Tool. If the end users do not agree to these Terms of Use, they should not use the Tool. In the event of a conflict or inconsistency between these Terms of Use and FAO’s Terms and Conditions for use of its website, the present Terms of Use shall prevail.
... B105: 19. Nothing contained in or related to these Terms and Conditions shall be deemed a waiver, express or implied, of the privileges and immunities of FAO, or as its acceptance of the jurisdiction of the courts of any country over disputes arising out of these Terms of Use or documents or arrangements related thereto.

Sheet 1.Description
D4: =Languages!B31
D7: =Languages!B32 | N7: =Languages!B42 | Z7: =Languages!B56
D8: =Languages!B34 | N8: =Languages!B43 | Q8: Europe
D9: =Languages!B35 | N9: =Languages!B44 | Q9: Italy | AA9: English
D10: =Languages!B36 | N10: =Languages!B45 | Q10: Tropical
D11: =Languages!B37 | N11: =Languages!B46 | Q11: Dry
D12: =Languages!B38 | N12: =Languages!B47 | Q12: Sandy soils
D13: =Languages!B39 | N13: =Languages!B48 | S13: =Languages!B49 | T13: 10
D14: =Languages!B40 | S14: =Languages!B50 | T14: 15
D15: =Languages!B41 | G15: Please select | S15: =Languages!B51 | T15: =time+time_cap
D16: if other, please specify | N16: Please ensure the MAT is > 18C and the elevation> 1000m.
L17: Organic soil should be analyzed directly in the "Inland Wetlands" module. Please refrain from analysing activities on organic soils in other modules
C22: =Languages!B53 | O22: =Languages!B52
R23: tC/ha
D24: =Languages!B54 | E24: 100 yr AR5 w/out CC feedback | I24: Tier 2 | R24: =Languages!B55 | S24: Tier 2
D25: CO2 | G25: =IF($E$24="please select","",1) | P25: SOCref | R25: =IFERROR(INDEX(IPCC!$B$39:$I$49,MATCH(clim_moist,IPCC!$A$39:$A$49,0),MATCH(soil,IPCC!$B$38:$I$38,0)),"")
D26: CH4 | G26: =IF($E$24="please select","",IF($E$24="100 yr SAR", 21, IF($E$24="100 yr AR4", 25, IF($E$24="100 yr AR5 with CC feedback", 34, IF($E$24="100 yr AR5 w/out CC feedback", 28, IF($E$24="100 yr AR6", 27.2, IF($E$24="OTHER (TIER 2)", I26,"")))))))
D27: N2O | G27: =IF($E$24="please select","",IF($E$24="100 yr SAR", 310, IF($E$24="100 yr AR4", 298, IF($E$24="100 yr AR5 with CC feedback", 298, IF($E$24="100 yr AR5 w/out CC feedback", 265, IF($E$24="100 yr AR6", 273, IF($E$24="OTHER (TIER 2)", I27,""))))))) | N27: =IF(R25="NO", "ERROR: default value does not exist for selected combination of climate, moisture and soil type", "")
D28: CH4 | E28: fossil origin | G28: =IF($E$24="please select","",IF($E$24="100 yr SAR", 21, IF($E$24="100 yr AR4", 25, IF($E$24="100 yr AR5 with CC feedback", 34, IF($E$24="100 yr AR5 w/out CC feedback", 28, IF($E$24="100 yr AR6", 29.8, IF($E$24="OTHER (TIER 2)", I26,"")))))))
D29: =IF(OR(methane=0,Nitrous=0), "Please fill the GWP for methane and nitroux oxyde before proceeding","")

Sheet affo
A2: 2.2 Afforestation and reforestation
J4: AGB secondary | P4: BGB secondary | V4: Litter | X4: Dead wood | Z4: SOC 0 | AB4: MAX AGB+BGB | AC4: Bigger than actual growth? | AF4: All preriod | AJ4: Implementation phase alone (tCO2 eq)
J5: Default | L5: Tier 2 | M5: Default | O5: Tier 2 | P5: Default | R5: Tier 2 | S5: Default | U5: Tier 2 | V5: Default | W5: Tier 2 | X5: Default | Y5: Tier 2 | Z5: Default | AA5: Tier 2 | AJ5: time_tot= time and time_cap = 0 | AS5: Cumulated area burnt
A6: Forest types for Affo/Reforestation (without MANGROVES) | G6: No. | H6: Forest classes per IPCC climate region | I6: continent_selected | J6: t dm/ha/yr | K6: t C/ha/yr | L6: t C/ha/yr | M6: t dm/ha/yr | N6: tC/ha/yr | O6: t C/ha/yr | P6: t dm/ha/yr | Q6: t C/ha/yr | R6: t C/ha/yr | S6: t dm/ha/yr | T6: tC/ha/yr | U6: tC/ha/yr | V6: tC/ha | W6: tC/ha | X6: tC/ha | Y6: tC/ha | Z6: tC/ha | AA6: tC/ha | AB6: tCO2/ha | AF6: CH4 (tCO2 eq) | AH6: N2O (tCO2 eq) | AJ6: Biomass (AGB + BGB) gain | AL6: Biomass loss | AN6: DOM | AP6: Soil | AS6: (ha)
A7: Tropical2 | B7: WarmTemperate2 | C7: CoolTemperate2 | D7: Boreal2 | E7: TropicalMontane2 | H7: =clim3 | I7: =continent_selected | J7: ( ≤ 20 years ) | K7: ( ≤ 20 years ) | L7: ( ≤ 20 years ) | M7: ( > 20 years ) | N7: ( > 20 years ) | O7: ( > 20 years ) | P7: ( ≤ 20 years ) | Q7: ( ≤ 20 years ) | R7: ( ≤ 20 years ) | S7: ( > 20 years ) | T7: ( > 20 years ) | U7: ( > 20 years ) | AF7: w/out | AG7: with | AH7: w/out | AI7: with | AJ7: w/out | AK7: with | AL7: w/out | AM7: with | AN7: w/out | AO7: with | AP7: w/out | AQ7: with | AS7: without | AT7: With
A8: Tropical rainforest | B8: Subtropical humid forest | C8: Temperate oceanic forest | D8: Boreal coniferous forest | E8: Tropical mountain systems | G8: 1 | H8: =C24 | I8: =IF( $H8 <> "Please select", CONCATENATE(H8,continent_selected), "") | J8: =IF($I8<>"",VLOOKUP(affo!$I8, IPCC!$C$924:$E$1467, 3, FALSE),0) | K8: =$J8*0.47 | L8: =IF('2.LUC'!$BC36="",'2.LUC'!$BB36,'2.LUC'!$BC36) | M8: =IF(I8<>"",VLOOKUP(affo!$I8, IPCC!$C$924:$E$1467, 2, FALSE),0) | N8: =M8*0.47 | O8: =IF('2.LUC'!$BF36="",'2.LUC'!$BE36,'2.LUC'!$BF36) | P8: =IF($H8<>"Please select", IF(OR($J8<=125, $J8<= 75),INDEX(IPCC!$B$618:$AI$633,MATCH(continent_selected,IPCC!$A$618:$A$633,0),MATCH($H8,IPCC!$B$616:$AI$616,0)),(IF(OR($J8>125, $J8>75),INDEX(IPCC!$AJ$618:$BS$633,MATCH(continent_selected,IPCC!$A$618:$A$633,0),MATCH($H8,IPCC!$AJ$616:$BS$616,0)),"")))*$J8,0) | Q8: =P8*0.47 | R8: =IF('2.LUC'!$BI36="",'2.LUC'!$BH36,'2.LUC'!$BI36) | S8: =IF($H8 <>"Please select", IF(OR($M8 <=125, $M8 <= 75),INDEX(IPCC!$B$618:$AI$633,MATCH(continent_selected,IPCC!$A$618:$A$633,0),MATCH($H8,IPCC!$B$616:$AI$616,0)),(IF(OR($M8>125, $M8>75),INDEX(IPCC!$AJ$618:$BS$633,MATCH(continent_selected,IPCC!$A$618:$A$633,0),MATCH($H8,IPCC!$AJ$616:$BS$616,0)),"")))*$M8,0) | T8: =S8*0.47 | U8: =IF('2.LUC'!$BK36="",'2.LUC'!$BJ36,'2.LUC'!$BK36) | V8: =IF($H8<>"Please select", VLOOKUP($H8, IPCC!$A$643:$B$677, 2, FALSE), 0) | W8: =IF('2.LUC'!$BQ36="",'2.LUC'!$BP36,'2.LUC'!$BQ36) | X8: =IF($H8<>"Please select",VLOOKUP($H8,IPCC!$A$643:$C$677,3,FALSE),0) | Y8: =IF('2.LUC'!$BT36="",'2.LUC'!$BS36,'2.LUC'!$BT36) | Z8: =IF($I8<> "", SOCref, 0) | AA8: =IF('2.LUC'!$BW36="",'2.LUC'!$BV36,'2.LUC'!$BW36) | AB8: =IF('2.LUC'!BN36<> "", '2.LUC'!BN36*44/12, IF(H8="Please select",0,IF(INDEX(IPCC!$A$590:$AK$606,MATCH($I$7,IPCC!$A$590:$A$606,0),MATCH(H8,IPCC!$A$590:$AK$590,0))<= 125, INDEX(IPCC!$A$590:$AK$606,MATCH($I$7,IPCC!$A$590:$A$606,0),MATCH(H8,IPCC!$A$590:$AK$590,0))+(INDEX(IPCC!$A$590:$AK$606,MATCH($I$7,IPCC!$A$590:$A$606,0),MATCH(H8,IPCC!$A$590:$AK$590,0))*INDEX(IPCC!$A$617:$BS$633,MATCH($I$7,IPCC!$A$617:$A$633,0),MATCH(H8,IPCC!$A$616:$BS$616,0))),INDEX(IPCC!$A$590:$AK$606,MATCH($I$7,IPCC!$A$590:$A$606,0), MATCH(H8,IPCC!$A$590:$AK$590,0))+(INDEX(IPCC!$A$590:$AK$606,MATCH($I$7,IPCC!$A$590:$A$606,0),MATCH(H8,IPCC!$A$590:$AK$590,0))*INDEX(IPCC!$AJ$616:$BS$633,MATCH(continent_selected,IPCC!$A$616:$A$633,0),MATCH(H8,IPCC!$AJ$616:$BS$616,0)))))*0.47*44/12) | AC8: =IF(AB8>H37, "yes", "no") | AE8: Affo 1 | AF8: =IF($F24="YES", $D37*$P24*methane/1000,0) | AG8: =IF($F24="YES", $F37*$P24*methane/1000,0) | AH8: =IF($F24="YES", $D37*$Q24*Nitrous/1000,0) | AI8: =IF($F24="YES", $F37*$Q24*Nitrous/1000,0) | AJ8: =-(44/12)*($S24*(IF(E37="Immediate",D37*MIN(20,time),D37*IF(time>time+20,20,IF(time<20,(time*VLOOKUP(E37, list!$J$48:$K$50, 2,))+(time-time),((MIN(20,time)*VLOOKUP(affo!E37, list!$J$48:$K$50, 2,)) + (time-MIN(20,time))-IF(affo!E37="Exponential",time-20+0.217*time*(EXP(4.606*(20-time)/time)-1),((time-20)^2)*(0.5/time)))))))+($T24*(IF(affo!E37="Immediate", affo!D37*(time-MIN(20,time)), affo!D37*IF(time>time+20,(time*VLOOKUP(affo!E37, list!$J$48:$K$50,2,))+(time-time-20),IF(time<20,0,IF(affo!E37="Exponential",time-20+0.217*time*(EXP(4.606*(20-time)/time)-1),((time-20)^2)*(0.5/time)))))))) | AK8: =-(44/12)*($S24*(IF(G37="Immediate", F37*MIN(20,time), F37*IF(time>time+20,20,IF(time<20,(time*VLOOKUP(G37, list!$J$48:$K$50, 2,))+(time-time),((MIN(20,time)*VLOOKUP(affo!G37, list!$J$48:$K$50, 2,))+ (time-MIN(20,time))-IF(affo!G37="Exponential",time-20+0.217*time*(EXP(4.606*(20-time)/time)-1),((time-20)^2)*(0.5/time)))))))+($T24*(IF(affo!G37="Immediate", affo!F37*(time-MIN(20,time)), affo!F37*IF(time>time+20,(time*VLOOKUP(affo!G37, list!$J$48:$K$50,2,))+(time-time-20),IF(time<20,0,IF(affo!G37="Exponential",time-20+0.217*time*(EXP(4.606*(20-time)/time)-1),((time-20)^2)*(0.5/time)))))))) | AL8: =IF(time=0,0,$L37) | AM8: =IF(time=0,0, $M37) | AN8: =IF(time=0,0,$J37) | AO8: =IF(time=0,0,$K37) | AP8: =$M24*(IF(E37="Immediate", D37*MIN(20,time), D37*IF(time>=time+20,20,IF(time<=20,(time*VLOOKUP(E37, list!$J$48:$K$50, 2,))+(time-time),((MIN(20,time)*VLOOKUP(affo!E37, list!$J$48:$K$50,2,))+(time-MIN(20,time))-IF(affo!E37="Exponential",time-20+0.217*time*(EXP(4.606*(20-time)/time)-1),((time-20)^2)*(0.5/time))))))) | AQ8: =$M24*(IF(G37="Immediate", F37*MIN(20,time), F37*IF(time>time+20,20,IF(time<20,(time*VLOOKUP( G37, list!$J$48:$K$50, 2,))+(time-time),((MIN(20,time)*VLOOKUP(affo!G37, list!$J$48:$K$50,2,))+(time-MIN(20,time))-IF(affo!G37="Exponential",time-20+0.217*time*(EXP(4.606*(20-time)/time)-1),((time-20)^2)*(0.5/time))))))) | AS8: =IF($P24>0, $D37, 0) | AT8: =IF($P24>0, $F37, 0)
A9: Tropical moist deciduous forest | B9: Subtropical dry forest | C9: Temperate continental forest | D9: Boreal tundra woodland | E9: Planted Tropical mountain systems | G9: 2 | H9: =C25 | I9: =IF( $H9 <> "Please select", CONCATENATE(H9,continent_selected), "") | J9: =IF($I9<>"",VLOOKUP(affo!$I9, IPCC!$C$924:$E$1467, 3, FALSE),0) | K9: =$J9*0.47 | L9: =IF('2.LUC'!$BC37="",'2.LUC'!$BB37,'2.LUC'!$BC37) | M9: =IF(I9<>"",VLOOKUP(affo!$I9, IPCC!$C$924:$E$1467, 2, FALSE),0) | N9: =M9*0.47 | O9: =IF('2.LUC'!$BF37="",'2.LUC'!$BE37,'2.LUC'!$BF37) | P9: =IF($H9<>"Please select", IF(OR($J9<=125, $J9<= 75),INDEX(IPCC!$B$618:$AI$633,MATCH(continent_selected,IPCC!$A$618:$A$633,0),MATCH($H9,IPCC!$B$616:$AI$616,0)),(IF(OR($J9>125, $J9>75),INDEX(IPCC!$AJ$618:$BS$633,MATCH(continent_selected,IPCC!$A$618:$A$633,0),MATCH($H9,IPCC!$AJ$616:$BS$616,0)),"")))*$J9,0) | Q9: =P9*0.47 | R9: =IF('2.LUC'!$BI37="",'2.LUC'!$BH37,'2.LUC'!$BI37) | S9: =IF($H9 <>"Please select", IF(OR($M9 <=125, $M9 <= 75),INDEX(IPCC!$B$618:$AI$633,MATCH(continent_selected,IPCC!$A$618:$A$633,0),MATCH($H9,IPCC!$B$616:$AI$616,0)),(IF(OR($M9>125, $M9>75),INDEX(IPCC!$AJ$618:$BS$633,MATCH(continent_selected,IPCC!$A$618:$A$633,0),MATCH($H9,IPCC!$AJ$616:$BS$616,0)),"")))*$M9,0) | T9: =S9*0.47 | U9: =IF('2.LUC'!$BK37="",'2.LUC'!$BJ37,'2.LUC'!$BK37) | V9: =IF($H9<>"Please select", VLOOKUP($H9, IPCC!$A$643:$B$677, 2, FALSE), 0) | W9: =IF('2.LUC'!$BQ37="",'2.LUC'!$BP37,'2.LUC'!$BQ37) | X9: =IF($H9<>"Please select",VLOOKUP($H9,IPCC!$A$643:$C$677,3,FALSE),0) | Y9: =IF('2.LUC'!$BT37="",'2.LUC'!$BS37,'2.LUC'!$BT37) | Z9: =IF($I9<> "", SOCref, 0) | AA9: =IF('2.LUC'!$BW37="",'2.LUC'!$BV37,'2.LUC'!$BW37) | AB9: =IF('2.LUC'!BN37<> "", '2.LUC'!BN37*44/12, IF(H9="Please select",0,IF(INDEX(IPCC!$A$590:$AK$606,MATCH($I$7,IPCC!$A$590:$A$606,0),MATCH(H9,IPCC!$A$590:$AK$590,0))<= 125, INDEX(IPCC!$A$590:$AK$606,MATCH($I$7,IPCC!$A$590:$A$606,0),MATCH(H9,IPCC!$A$590:$AK$590,0))+(INDEX(IPCC!$A$590:$AK$606,MATCH($I$7,IPCC!$A$590:$A$606,0),MATCH(H9,IPCC!$A$590:$AK$590,0))*INDEX(IPCC!$A$617:$BS$633,MATCH($I$7,IPCC!$A$617:$A$633,0),MATCH(H9,IPCC!$A$616:$BS$616,0))),INDEX(IPCC!$A$590:$AK$606,MATCH($I$7,IPCC!$A$590:$A$606,0), MATCH(H9,IPCC!$A$590:$AK$590,0))+(INDEX(IPCC!$A$590:$AK$606,MATCH($I$7,IPCC!$A$590:$A$606,0),MATCH(H9,IPCC!$A$590:$AK$590,0))*INDEX(IPCC!$AJ$616:$BS$633,MATCH(continent_selected,IPCC!$A$616:$A$633,0),MATCH(H9,IPCC!$AJ$616:$BS$616,0)))))*0.47*44/12) | AC9: =IF(AB9>H38, "yes", "no") | AE9: Affo 2 | AF9: =IF($F25="YES", $D38*$P25*methane/1000,0) | AG9: =IF($F25="YES", $F38*$P25*methane/1000,0) | AH9: =IF($F25="YES", $D38*$Q25*Nitrous/1000,0) | AI9: =IF($F25="YES", $F38*$Q25*Nitrous/1000,0) | AJ9: =-(44/12)*($S25*(IF(E38="Immediate",D38*MIN(20,time),D38*IF(time>time+20,20,IF(time<20,(time*VLOOKUP(E38, list!$J$48:$K$50, 2,))+(time-time),((MIN(20,time)*VLOOKUP(affo!E38, list!$J$48:$K$50, 2,)) + (time-MIN(20,time))-IF(affo!E38="Exponential",time-20+0.217*time*(EXP(4.606*(20-time)/time)-1),((time-20)^2)*(0.5/time)))))))+($T25*(IF(affo!E38="Immediate", affo!D38*(time-MIN(20,time)), affo!D38*IF(time>time+20,(time*VLOOKUP(affo!E38, list!$J$48:$K$50,2,))+(time-time-20),IF(time<20,0,IF(affo!E38="Exponential",time-20+0.217*time*(EXP(4.606*(20-time)/time)-1),((time-20)^2)*(0.5/time)))))))) | AK9: =-(44/12)*($S25*(IF(G38="Immediate", F38*MIN(20,time), F38*IF(time>time+20,20,IF(time<20,(time*VLOOKUP(G38, list!$J$48:$K$50, 2,))+(time-time),((MIN(20,time)*VLOOKUP(affo!G38, list!$J$48:$K$50, 2,))+ (time-MIN(20,time))-IF(affo!G38="Exponential",time-20+0.217*time*(EXP(4.606*(20-time)/time)-1),((time-20)^2)*(0.5/time)))))))+($T25*(IF(affo!G38="Immediate", affo!F38*(time-MIN(20,time)), affo!F38*IF(time>time+20,(time*VLOOKUP(affo!G38, list!$J$48:$K$50,2,))+(time-time-20),IF(time<20,0,IF(affo!G38="Exponential",time-20+0.217*time*(EXP(4.606*(20-time)/time)-1),((time-20)^2)*(0.5/time)))))))) | AL9: =IF(time=0,0,$L38) | AM9: =IF(time=0,0, $M38) | AN9: =IF(time=0,0,$J38) | AO9: =IF(time=0,0,$K38) | AP9: =$M25*(IF(E38="Immediate", D38*MIN(20,time), D38*IF(time>=time+20,20,IF(time<=20,(time*VLOOKUP(E38, list!$J$48:$K$50, 2,))+(time-time),((MIN(20,time)*VLOOKUP(affo!E38, list!$J$48:$K$50,2,))+(time-MIN(20,time))-IF(affo!E38="Exponential",time-20+0.217*time*(EXP(4.606*(20-time)/time)-1),((time-20)^2)*(0.5/time))))))) | AQ9: =$M25*(IF(G38="Immediate", F38*MIN(20,time), F38*IF(time>time+20,20,IF(time<20,(time*VLOOKUP( G38, list!$J$48:$K$50, 2,))+(time-time),((MIN(20,time)*VLOOKUP(affo!G38, list!$J$48:$K$50,2,))+(time-MIN(20,time))-IF(affo!G38="Exponential",time-20+0.217*time*(EXP(4.606*(20-time)/time)-1),((time-20)^2)*(0.5/time))))))) | AS9: =IF($P25>0, $D38, 0) | AT9: =IF($P25>0, $F38, 0)
A10: Tropical dry forest | B10: Subtropical steppe | C10: Temperate mountain systems | D10: Boreal mountain systems | G10: 3 | H10: =C26 | I10: =IF( $H10 <> "Please select", CONCATENATE(H10,continent_selected), "") | J10: =IF($I10<>"",VLOOKUP(affo!$I10, IPCC!$C$924:$E$1467, 3, FALSE),0) | K10: =$J10*0.47 | L10: =IF('2.LUC'!$BC38="",'2.LUC'!$BB38,'2.LUC'!$BC38) | M10: =IF(I10<>"",VLOOKUP(affo!$I10, IPCC!$C$924:$E$1467, 2, FALSE),0) | N10: =M10*0.47 | O10: =IF('2.LUC'!$BF38="",'2.LUC'!$BE38,'2.LUC'!$BF38) | P10: =IF($H10<>"Please select", IF(OR($J10<=125, $J10<= 75),INDEX(IPCC!$B$618:$AI$633,MATCH(continent_selected,IPCC!$A$618:$A$633,0),MATCH($H10,IPCC!$B$616:$AI$616,0)),(IF(OR($J10>125, $J10>75),INDEX(IPCC!$AJ$618:$BS$633,MATCH(continent_selected,IPCC!$A$618:$A$633,0),MATCH($H10,IPCC!$AJ$616:$BS$616,0)),"")))*$J10,0) | Q10: =P10*0.47 | R10: =IF('2.LUC'!$BI38="",'2.LUC'!$BH38,'2.LUC'!$BI38) | S10: =IF($H10 <>"Please select", IF(OR($M10 <=125, $M10 <= 75),INDEX(IPCC!$B$618:$AI$633,MATCH(continent_selected,IPCC!$A$618:$A$633,0),MATCH($H10,IPCC!$B$616:$AI$616,0)),(IF(OR($M10>125, $M10>75),INDEX(IPCC!$AJ$618:$BS$633,MATCH(continent_selected,IPCC!$A$618:$A$633,0),MATCH($H10,IPCC!$AJ$616:$BS$616,0)),"")))*$M10,0) | T10: =S10*0.47 | U10: =IF('2.LUC'!$BK38="",'2.LUC'!$BJ38,'2.LUC'!$BK38) | V10: =IF($H10<>"Please select", VLOOKUP($H10, IPCC!$A$643:$B$677, 2, FALSE), 0) | W10: =IF('2.LUC'!$BQ38="",'2.LUC'!$BP38,'2.LUC'!$BQ38) | X10: =IF($H10<>"Please select",VLOOKUP($H10,IPCC!$A$643:$C$677,3,FALSE),0) | Y10: =IF('2.LUC'!$BT38="",'2.LUC'!$BS38,'2.LUC'!$BT38) | Z10: =IF($I10<> "", SOCref, 0) | AA10: =IF('2.LUC'!$BW38="",'2.LUC'!$BV38,'2.LUC'!$BW38) | AB10: =IF('2.LUC'!BN38<> "", '2.LUC'!BN38*44/12, IF(H10="Please select",0,IF(INDEX(IPCC!$A$590:$AK$606,MATCH($I$7,IPCC!$A$590:$A$606,0),MATCH(H10,IPCC!$A$590:$AK$590,0))<= 125, INDEX(IPCC!$A$590:$AK$606,MATCH($I$7,IPCC!$A$590:$A$606,0),MATCH(H10,IPCC!$A$590:$AK$590,0))+(INDEX(IPCC!$A$590:$AK$606,MATCH($I$7,IPCC!$A$590:$A$606,0),MATCH(H10,IPCC!$A$590:$AK$590,0))*INDEX(IPCC!$A$617:$BS$633,MATCH($I$7,IPCC!$A$617:$A$633,0),MATCH(H10,IPCC!$A$616:$BS$616,0))),INDEX(IPCC!$A$590:$AK$606,MATCH($I$7,IPCC!$A$590:$A$606,0), MATCH(H10,IPCC!$A$590:$AK$590,0))+(INDEX(IPCC!$A$590:$AK$606,MATCH($I$7,IPCC!$A$590:$A$606,0),MATCH(H10,IPCC!$A$590:$AK$590,0))*INDEX(IPCC!$AJ$616:$BS$633,MATCH(continent_selected,IPCC!$A$616:$A$633,0),MATCH(H10,IPCC!$AJ$616:$BS$616,0)))))*0.47*44/12) | AC10: =IF(AB10>H39, "yes", "no") | AE10: Affo 3 | AF10: =IF($F26="YES", $D39*$P26*methane/1000,0) | AG10: =IF($F26="YES", $F39*$P26*methane/1000,0) | AH10: =IF($F26="YES", $D39*$Q26*Nitrous/1000,0) | AI10: =IF($F26="YES", $F39*$Q26*Nitrous/1000,0) | AJ10: =-(44/12)*($S26*(IF(E39="Immediate",D39*MIN(20,time),D39*IF(time>time+20,20,IF(time<20,(time*VLOOKUP(E39, list!$J$48:$K$50, 2,))+(time-time),((MIN(20,time)*VLOOKUP(affo!E39, list!$J$48:$K$50, 2,)) + (time-MIN(20,time))-IF(affo!E39="Exponential",time-20+0.217*time*(EXP(4.606*(20-time)/time)-1),((time-20)^2)*(0.5/time)))))))+($T26*(IF(affo!E39="Immediate", affo!D39*(time-MIN(20,time)), affo!D39*IF(time>time+20,(time*VLOOKUP(affo!E39, list!$J$48:$K$50,2,))+(time-time-20),IF(time<20,0,IF(affo!E39="Exponential",time-20+0.217*time*(EXP(4.606*(20-time)/time)-1),((time-20)^2)*(0.5/time)))))))) | AK10: =-(44/12)*($S26*(IF(G39="Immediate", F39*MIN(20,time), F39*IF(time>time+20,20,IF(time<20,(time*VLOOKUP(G39, list!$J$48:$K$50, 2,))+(time-time),((MIN(20,time)*VLOOKUP(affo!G39, list!$J$48:$K$50, 2,))+ (time-MIN(20,time))-IF(affo!G39="Exponential",time-20+0.217*time*(EXP(4.606*(20-time)/time)-1),((time-20)^2)*(0.5/time)))))))+($T26*(IF(affo!G39="Immediate", affo!F39*(time-MIN(20,time)), affo!F39*IF(time>time+20,(time*VLOOKUP(affo!G39, list!$J$48:$K$50,2,))+(time-time-20),IF(time<20,0,IF(affo!G39="Exponential",time-20+0.217*time*(EXP(4.606*(20-time)/time)-1),((time-20)^2)*(0.5/time)))))))) | AL10: =IF(time=0,0,$L39) | AM10: =IF(time=0,0, $M39) | AN10: =IF(time=0,0,$J39) | AO10: =IF(time=0,0,$K39) | AP10: =$M26*(IF(E39="Immediate", D39*MIN(20,time), D39*IF(time>=time+20,20,IF(time<=20,(time*VLOOKUP(E39, list!$J$48:$K$50, 2,))+(time-time),((MIN(20,time)*VLOOKUP(affo!E39, list!$J$48:$K$50,2,))+(time-MIN(20,time))-IF(affo!E39="Exponential",time-20+0.217*time*(EXP(4.606*(20-time)/time)-1),((time-20)^2)*(0.5/time))))))) | AQ10: =$M26*(IF(G39="Immediate", F39*MIN(20,time), F39*IF(time>time+20,20,IF(time<20,(time*VLOOKUP( G39, list!$J$48:$K$50, 2,))+(time-time),((MIN(20,time)*VLOOKUP(affo!G39, list!$J$48:$K$50,2,))+(time-MIN(20,time))-IF(affo!G39="Exponential",time-20+0.217*time*(EXP(4.606*(20-time)/time)-1),((time-20)^2)*(0.5/time))))))) | AS10: =IF($P26>0, $D39, 0) | AT10: =IF($P26>0, $F39, 0)
A11: Tropical shrubland | B11: Subtropical mountain systems | C11: Temperate desert | D11: Planted Boreal coniferous forest | G11: 4 | H11: =C27 | I11: =IF( $H11 <> "Please select", CONCATENATE(H11,continent_selected), "") | J11: =IF($I11<>"",VLOOKUP(affo!$I11, IPCC!$C$924:$E$1467, 3, FALSE),0) | K11: =$J11*0.47 | L11: =IF('2.LUC'!$BC39="",'2.LUC'!$BB39,'2.LUC'!$BC39) | M11: =IF(I11<>"",VLOOKUP(affo!$I11, IPCC!$C$924:$E$1467, 2, FALSE),0) | N11: =M11*0.47 | O11: =IF('2.LUC'!$BF39="",'2.LUC'!$BE39,'2.LUC'!$BF39) | P11: =IF($H11<>"Please select", IF(OR($J11<=125, $J11<= 75),INDEX(IPCC!$B$618:$AI$633,MATCH(continent_selected,IPCC!$A$618:$A$633,0),MATCH($H11,IPCC!$B$616:$AI$616,0)),(IF(OR($J11>125, $J11>75),INDEX(IPCC!$AJ$618:$BS$633,MATCH(continent_selected,IPCC!$A$618:$A$633,0),MATCH($H11,IPCC!$AJ$616:$BS$616,0)),"")))*$J11,0) | Q11: =P11*0.47 | R11: =IF('2.LUC'!$BI39="",'2.LUC'!$BH39,'2.LUC'!$BI39) | S11: =IF($H11 <>"Please select", IF(OR($M11 <=125, $M11 <= 75),INDEX(IPCC!$B$618:$AI$633,MATCH(continent_selected,IPCC!$A$618:$A$633,0),MATCH($H11,IPCC!$B$616:$AI$616,0)),(IF(OR($M11>125, $M11>75),INDEX(IPCC!$AJ$618:$BS$633,MATCH(continent_selected,IPCC!$A$618:$A$633,0),MATCH($H11,IPCC!$AJ$616:$BS$616,0)),"")))*$M11,0) | T11: =S11*0.47 | U11: =IF('2.LUC'!$BK39="",'2.LUC'!$BJ39,'2.LUC'!$BK39) | V11: =IF($H11<>"Please select", VLOOKUP($H11, IPCC!$A$643:$B$677, 2, FALSE), 0) | W11: =IF('2.LUC'!$BQ39="",'2.LUC'!$BP39,'2.LUC'!$BQ39) | X11: =IF($H11<>"Please select",VLOOKUP($H11,IPCC!$A$643:$C$677,3,FALSE),0) | Y11: =IF('2.LUC'!$BT39="",'2.LUC'!$BS39,'2.LUC'!$BT39) | Z11: =IF($I11<> "", SOCref, 0) | AA11: =IF('2.LUC'!$BW39="",'2.LUC'!$BV39,'2.LUC'!$BW39) | AB11: =IF('2.LUC'!BN39<> "", '2.LUC'!BN39*44/12, IF(H11="Please select",0,IF(INDEX(IPCC!$A$590:$AK$606,MATCH($I$7,IPCC!$A$590:$A$606,0),MATCH(H11,IPCC!$A$590:$AK$590,0))<= 125, INDEX(IPCC!$A$590:$AK$606,MATCH($I$7,IPCC!$A$590:$A$606,0),MATCH(H11,IPCC!$A$590:$AK$590,0))+(INDEX(IPCC!$A$590:$AK$606,MATCH($I$7,IPCC!$A$590:$A$606,0),MATCH(H11,IPCC!$A$590:$AK$590,0))*INDEX(IPCC!$A$617:$BS$633,MATCH($I$7,IPCC!$A$617:$A$633,0),MATCH(H11,IPCC!$A$616:$BS$616,0))),INDEX(IPCC!$A$590:$AK$606,MATCH($I$7,IPCC!$A$590:$A$606,0), MATCH(H11,IPCC!$A$590:$AK$590,0))+(INDEX(IPCC!$A$590:$AK$606,MATCH($I$7,IPCC!$A$590:$A$606,0),MATCH(H11,IPCC!$A$590:$AK$590,0))*INDEX(IPCC!$AJ$616:$BS$633,MATCH(continent_selected,IPCC!$A$616:$A$633,0),MATCH(H11,IPCC!$AJ$616:$BS$616,0)))))*0.47*44/12) | AC11: =IF(AB11>H40, "yes", "no") | AE11: Affo 4 | AF11: =IF($F27="YES", $D40*$P27*methane/1000,0) | AG11: =IF($F27="YES", $F40*$P27*methane/1000,0) | AH11: =IF($F27="YES", $D40*$Q27*Nitrous/1000,0) | AI11: =IF($F27="YES", $F40*$Q27*Nitrous/1000,0) | AJ11: =-(44/12)*($S27*(IF(E40="Immediate",D40*MIN(20,time),D40*IF(time>time+20,20,IF(time<20,(time*VLOOKUP(E40, list!$J$48:$K$50, 2,))+(time-time),((MIN(20,time)*VLOOKUP(affo!E40, list!$J$48:$K$50, 2,)) + (time-MIN(20,time))-IF(affo!E40="Exponential",time-20+0.217*time*(EXP(4.606*(20-time)/time)-1),((time-20)^2)*(0.5/time)))))))+($T27*(IF(affo!E40="Immediate", affo!D40*(time-MIN(20,time)), affo!D40*IF(time>time+20,(time*VLOOKUP(affo!E40, list!$J$48:$K$50,2,))+(time-time-20),IF(time<20,0,IF(affo!E40="Exponential",time-20+0.217*time*(EXP(4.606*(20-time)/time)-1),((time-20)^2)*(0.5/time)))))))) | AK11: =-(44/12)*($S27*(IF(G40="Immediate", F40*MIN(20,time), F40*IF(time>time+20,20,IF(time<20,(time*VLOOKUP(G40, list!$J$48:$K$50, 2,))+(time-time),((MIN(20,time)*VLOOKUP(affo!G40, list!$J$48:$K$50, 2,))+ (time-MIN(20,time))-IF(affo!G40="Exponential",time-20+0.217*time*(EXP(4.606*(20-time)/time)-1),((time-20)^2)*(0.5/time)))))))+($T27*(IF(affo!G40="Immediate", affo!F40*(time-MIN(20,time)), affo!F40*IF(time>time+20,(time*VLOOKUP(affo!G40, list!$J$48:$K$50,2,))+(time-time-20),IF(time<20,0,IF(affo!G40="Exponential",time-20+0.217*time*(EXP(4.606*(20-time)/time)-1),((time-20)^2)*(0.5/time)))))))) | AL11: =IF(time=0,0,$L40) | AM11: =IF(time=0,0, $M40) | AN11: =IF(time=0,0,$J40) | AO11: =IF(time=0,0,$K40) | AP11: =$M27*(IF(E40="Immediate", D40*MIN(20,time), D40*IF(time>=time+20,20,IF(time<=20,(time*VLOOKUP(E40, list!$J$48:$K$50, 2,))+(time-time),((MIN(20,time)*VLOOKUP(affo!E40, list!$J$48:$K$50,2,))+(time-MIN(20,time))-IF(affo!E40="Exponential",time-20+0.217*time*(EXP(4.606*(20-time)/time)-1),((time-20)^2)*(0.5/time))))))) | AQ11: =$M27*(IF(G40="Immediate", F40*MIN(20,time), F40*IF(time>time+20,20,IF(time<20,(time*VLOOKUP( G40, list!$J$48:$K$50, 2,))+(time-time),((MIN(20,time)*VLOOKUP(affo!G40, list!$J$48:$K$50,2,))+(time-MIN(20,time))-IF(affo!G40="Exponential",time-20+0.217*time*(EXP(4.606*(20-time)/time)-1),((time-20)^2)*(0.5/time))))))) | AS11: =IF($P27>0, $D40, 0) | AT11: =IF($P27>0, $F40, 0)
A12: Planted Tropical rainforest | B12: Planted Subtropical humid forest | C12: Temperate steppe | D12: Planted Boreal tundra woodland | G12: 5 | H12: =C28 | I12: =IF( $H12 <> "Please select", CONCATENATE(H12,continent_selected), "") | J12: =IF($I12<>"",VLOOKUP(affo!$I12, IPCC!$C$924:$E$1467, 3, FALSE),0) | K12: =$J12*0.47 | L12: =IF('2.LUC'!$BC40="",'2.LUC'!$BB40,'2.LUC'!$BC40) | M12: =IF(I12<>"",VLOOKUP(affo!$I12, IPCC!$C$924:$E$1467, 2, FALSE),0) | N12: =M12*0.47 | O12: =IF('2.LUC'!$BF40="",'2.LUC'!$BE40,'2.LUC'!$BF40) | P12: =IF($H12<>"Please select", IF(OR($J12<=125, $J12<= 75),INDEX(IPCC!$B$618:$AI$633,MATCH(continent_selected,IPCC!$A$618:$A$633,0),MATCH($H12,IPCC!$B$616:$AI$616,0)),(IF(OR($J12>125, $J12>75),INDEX(IPCC!$AJ$618:$BS$633,MATCH(continent_selected,IPCC!$A$618:$A$633,0),MATCH($H12,IPCC!$AJ$616:$BS$616,0)),"")))*$J12,0) | Q12: =P12*0.47 | R12: =IF('2.LUC'!$BI40="",'2.LUC'!$BH40,'2.LUC'!$BI40) | S12: =IF($H12 <>"Please select", IF(OR($M12 <=125, $M12 <= 75),INDEX(IPCC!$B$618:$AI$633,MATCH(continent_selected,IPCC!$A$618:$A$633,0),MATCH($H12,IPCC!$B$616:$AI$616,0)),(IF(OR($M12>125, $M12>75),INDEX(IPCC!$AJ$618:$BS$633,MATCH(continent_selected,IPCC!$A$618:$A$633,0),MATCH($H12,IPCC!$AJ$616:$BS$616,0)),"")))*$M12,0) | T12: =S12*0.47 | U12: =IF('2.LUC'!$BK40="",'2.LUC'!$BJ40,'2.LUC'!$BK40) | V12: =IF($H12<>"Please select", VLOOKUP($H12, IPCC!$A$643:$B$677, 2, FALSE), 0) | W12: =IF('2.LUC'!$BQ40="",'2.LUC'!$BP40,'2.LUC'!$BQ40) | X12: =IF($H12<>"Please select",VLOOKUP($H12,IPCC!$A$643:$C$677,3,FALSE),0) | Y12: =IF('2.LUC'!$BT40="",'2.LUC'!$BS40,'2.LUC'!$BT40) | Z12: =IF($I12<> "", SOCref, 0) | AA12: =IF('2.LUC'!$BW40="",'2.LUC'!$BV40,'2.LUC'!$BW40) | AB12: =IF('2.LUC'!BN40<> "", '2.LUC'!BN40*44/12, IF(H12="Please select",0,IF(INDEX(IPCC!$A$590:$AK$606,MATCH($I$7,IPCC!$A$590:$A$606,0),MATCH(H12,IPCC!$A$590:$AK$590,0))<= 125, INDEX(IPCC!$A$590:$AK$606,MATCH($I$7,IPCC!$A$590:$A$606,0),MATCH(H12,IPCC!$A$590:$AK$590,0))+(INDEX(IPCC!$A$590:$AK$606,MATCH($I$7,IPCC!$A$590:$A$606,0),MATCH(H12,IPCC!$A$590:$AK$590,0))*INDEX(IPCC!$A$617:$BS$633,MATCH($I$7,IPCC!$A$617:$A$633,0),MATCH(H12,IPCC!$A$616:$BS$616,0))),INDEX(IPCC!$A$590:$AK$606,MATCH($I$7,IPCC!$A$590:$A$606,0), MATCH(H12,IPCC!$A$590:$AK$590,0))+(INDEX(IPCC!$A$590:$AK$606,MATCH($I$7,IPCC!$A$590:$A$606,0),MATCH(H12,IPCC!$A$590:$AK$590,0))*INDEX(IPCC!$AJ$616:$BS$633,MATCH(continent_selected,IPCC!$A$616:$A$633,0),MATCH(H12,IPCC!$AJ$616:$BS$616,0)))))*0.47*44/12) | AC12: =IF(AB12>H41, "yes", "no") | AE12: Affo 5 | AF12: =IF($F28="YES", $D41*$P28*methane/1000,0) | AG12: =IF($F28="YES", $F41*$P28*methane/1000,0) | AH12: =IF($F28="YES", $D41*$Q28*Nitrous/1000,0) | AI12: =IF($F28="YES", $F41*$Q28*Nitrous/1000,0) | AJ12: =-(44/12)*($S28*(IF(E41="Immediate",D41*MIN(20,time),D41*IF(time>time+20,20,IF(time<20,(time*VLOOKUP(E41, list!$J$48:$K$50, 2,))+(time-time),((MIN(20,time)*VLOOKUP(affo!E41, list!$J$48:$K$50, 2,)) + (time-MIN(20,time))-IF(affo!E41="Exponential",time-20+0.217*time*(EXP(4.606*(20-time)/time)-1),((time-20)^2)*(0.5/time)))))))+($T28*(IF(affo!E41="Immediate", affo!D41*(time-MIN(20,time)), affo!D41*IF(time>time+20,(time*VLOOKUP(affo!E41, list!$J$48:$K$50,2,))+(time-time-20),IF(time<20,0,IF(affo!E41="Exponential",time-20+0.217*time*(EXP(4.606*(20-time)/time)-1),((time-20)^2)*(0.5/time)))))))) | AK12: =-(44/12)*($S28*(IF(G41="Immediate", F41*MIN(20,time), F41*IF(time>time+20,20,IF(time<20,(time*VLOOKUP(G41, list!$J$48:$K$50, 2,))+(time-time),((MIN(20,time)*VLOOKUP(affo!G41, list!$J$48:$K$50, 2,))+ (time-MIN(20,time))-IF(affo!G41="Exponential",time-20+0.217*time*(EXP(4.606*(20-time)/time)-1),((time-20)^2)*(0.5/time)))))))+($T28*(IF(affo!G41="Immediate", affo!F41*(time-MIN(20,time)), affo!F41*IF(time>time+20,(time*VLOOKUP(affo!G41, list!$J$48:$K$50,2,))+(time-time-20),IF(time<20,0,IF(affo!G41="Exponential",time-20+0.217*time*(EXP(4.606*(20-time)/time)-1),((time-20)^2)*(0.5/time)))))))) | AL12: =IF(time=0,0,$L41) | AM12: =IF(time=0,0, $M41) | AN12: =IF(time=0,0,$J41) | AO12: =IF(time=0,0,$K41) | AP12: =$M28*(IF(E41="Immediate", D41*MIN(20,time), D41*IF(time>=time+20,20,IF(time<=20,(time*VLOOKUP(E41, list!$J$48:$K$50, 2,))+(time-time),((MIN(20,time)*VLOOKUP(affo!E41, list!$J$48:$K$50,2,))+(time-MIN(20,time))-IF(affo!E41="Exponential",time-20+0.217*time*(EXP(4.606*(20-time)/time)-1),((time-20)^2)*(0.5/time))))))) | AQ12: =$M28*(IF(G41="Immediate", F41*MIN(20,time), F41*IF(time>time+20,20,IF(time<20,(time*VLOOKUP( G41, list!$J$48:$K$50, 2,))+(time-time),((MIN(20,time)*VLOOKUP(affo!G41, list!$J$48:$K$50,2,))+(time-MIN(20,time))-IF(affo!G41="Exponential",time-20+0.217*time*(EXP(4.606*(20-time)/time)-1),((time-20)^2)*(0.5/time))))))) | AS12: =IF($P28>0, $D41, 0) | AT12: =IF($P28>0, $F41, 0)
A13: Planted Tropical moist deciduous forest | B13: Planted Subtropical dry forest | C13: Planted Temperate oceanic forest | D13: Planted Boreal mountain systems | G13: 6 | H13: =C29 | I13: =IF( $H13 <> "Please select", CONCATENATE(H13,continent_selected), "") | J13: =IF($I13<>"",VLOOKUP(affo!$I13, IPCC!$C$924:$E$1467, 3, FALSE),0) | K13: =$J13*0.47 | L13: =IF('2.LUC'!$BC41="",'2.LUC'!$BB41,'2.LUC'!$BC41) | M13: =IF(I13<>"",VLOOKUP(affo!$I13, IPCC!$C$924:$E$1467, 2, FALSE),0) | N13: =M13*0.47 | O13: =IF('2.LUC'!$BF41="",'2.LUC'!$BE41,'2.LUC'!$BF41) | P13: =IF($H13<>"Please select", IF(OR($J13<=125, $J13<= 75),INDEX(IPCC!$B$618:$AI$633,MATCH(continent_selected,IPCC!$A$618:$A$633,0),MATCH($H13,IPCC!$B$616:$AI$616,0)),(IF(OR($J13>125, $J13>75),INDEX(IPCC!$AJ$618:$BS$633,MATCH(continent_selected,IPCC!$A$618:$A$633,0),MATCH($H13,IPCC!$AJ$616:$BS$616,0)),"")))*$J13,0) | Q13: =P13*0.47 | R13: =IF('2.LUC'!$BI41="",'2.LUC'!$BH41,'2.LUC'!$BI41) | S13: =IF($H13 <>"Please select", IF(OR($M13 <=125, $M13 <= 75),INDEX(IPCC!$B$618:$AI$633,MATCH(continent_selected,IPCC!$A$618:$A$633,0),MATCH($H13,IPCC!$B$616:$AI$616,0)),(IF(OR($M13>125, $M13>75),INDEX(IPCC!$AJ$618:$BS$633,MATCH(continent_selected,IPCC!$A$618:$A$633,0),MATCH($H13,IPCC!$AJ$616:$BS$616,0)),"")))*$M13,0) | T13: =S13*0.47 | U13: =IF('2.LUC'!$BK41="",'2.LUC'!$BJ41,'2.LUC'!$BK41) | V13: =IF($H13<>"Please select", VLOOKUP($H13, IPCC!$A$643:$B$677, 2, FALSE), 0) | W13: =IF('2.LUC'!$BQ41="",'2.LUC'!$BP41,'2.LUC'!$BQ41) | X13: =IF($H13<>"Please select",VLOOKUP($H13,IPCC!$A$643:$C$677,3,FALSE),0) | Y13: =IF('2.LUC'!$BT41="",'2.LUC'!$BS41,'2.LUC'!$BT41) | Z13: =IF($I13<> "", SOCref, 0) | AA13: =IF('2.LUC'!$BW41="",'2.LUC'!$BV41,'2.LUC'!$BW41) | AB13: =IF('2.LUC'!BN41<> "", '2.LUC'!BN41*44/12, IF(H13="Please select",0,IF(INDEX(IPCC!$A$590:$AK$606,MATCH($I$7,IPCC!$A$590:$A$606,0),MATCH(H13,IPCC!$A$590:$AK$590,0))<= 125, INDEX(IPCC!$A$590:$AK$606,MATCH($I$7,IPCC!$A$590:$A$606,0),MATCH(H13,IPCC!$A$590:$AK$590,0))+(INDEX(IPCC!$A$590:$AK$606,MATCH($I$7,IPCC!$A$590:$A$606,0),MATCH(H13,IPCC!$A$590:$AK$590,0))*INDEX(IPCC!$A$617:$BS$633,MATCH($I$7,IPCC!$A$617:$A$633,0),MATCH(H13,IPCC!$A$616:$BS$616,0))),INDEX(IPCC!$A$590:$AK$606,MATCH($I$7,IPCC!$A$590:$A$606,0), MATCH(H13,IPCC!$A$590:$AK$590,0))+(INDEX(IPCC!$A$590:$AK$606,MATCH($I$7,IPCC!$A$590:$A$606,0),MATCH(H13,IPCC!$A$590:$AK$590,0))*INDEX(IPCC!$AJ$616:$BS$633,MATCH(continent_selected,IPCC!$A$616:$A$633,0),MATCH(H13,IPCC!$AJ$616:$BS$616,0)))))*0.47*44/12) | AC13: =IF(AB13>H42, "yes", "no") | AE13: Affo 6 | AF13: =IF($F29="YES", $D42*$P29*methane/1000,0) | AG13: =IF($F29="YES", $F42*$P29*methane/1000,0) | AH13: =IF($F29="YES", $D42*$Q29*Nitrous/1000,0) | AI13: =IF($F29="YES", $F42*$Q29*Nitrous/1000,0) | AJ13: =-(44/12)*($S29*(IF(E42="Immediate",D42*MIN(20,time),D42*IF(time>time+20,20,IF(time<20,(time*VLOOKUP(E42, list!$J$48:$K$50, 2,))+(time-time),((MIN(20,time)*VLOOKUP(affo!E42, list!$J$48:$K$50, 2,)) + (time-MIN(20,time))-IF(affo!E42="Exponential",time-20+0.217*time*(EXP(4.606*(20-time)/time)-1),((time-20)^2)*(0.5/time)))))))+($T29*(IF(affo!E42="Immediate", affo!D42*(time-MIN(20,time)), affo!D42*IF(time>time+20,(time*VLOOKUP(affo!E42, list!$J$48:$K$50,2,))+(time-time-20),IF(time<20,0,IF(affo!E42="Exponential",time-20+0.217*time*(EXP(4.606*(20-time)/time)-1),((time-20)^2)*(0.5/time)))))))) | AK13: =-(44/12)*($S29*(IF(G42="Immediate", F42*MIN(20,time), F42*IF(time>time+20,20,IF(time<20,(time*VLOOKUP(G42, list!$J$48:$K$50, 2,))+(time-time),((MIN(20,time)*VLOOKUP(affo!G42, list!$J$48:$K$50, 2,))+ (time-MIN(20,time))-IF(affo!G42="Exponential",time-20+0.217*time*(EXP(4.606*(20-time)/time)-1),((time-20)^2)*(0.5/time)))))))+($T29*(IF(affo!G42="Immediate", affo!F42*(time-MIN(20,time)), affo!F42*IF(time>time+20,(time*VLOOKUP(affo!G42, list!$J$48:$K$50,2,))+(time-time-20),IF(time<20,0,IF(affo!G42="Exponential",time-20+0.217*time*(EXP(4.606*(20-time)/time)-1),((time-20)^2)*(0.5/time)))))))) | AL13: =IF(time=0,0,$L42) | AM13: =IF(time=0,0, $M42) | AN13: =IF(time=0,0,$J42) | AO13: =IF(time=0,0,$K42) | AP13: =$M29*(IF(E42="Immediate", D42*MIN(20,time), D42*IF(time>=time+20,20,IF(time<=20,(time*VLOOKUP(E42, list!$J$48:$K$50, 2,))+(time-time),((MIN(20,time)*VLOOKUP(affo!E42, list!$J$48:$K$50,2,))+(time-MIN(20,time))-IF(affo!E42="Exponential",time-20+0.217*time*(EXP(4.606*(20-time)/time)-1),((time-20)^2)*(0.5/time))))))) | AQ13: =$M29*(IF(G42="Immediate", F42*MIN(20,time), F42*IF(time>time+20,20,IF(time<20,(time*VLOOKUP( G42, list!$J$48:$K$50, 2,))+(time-time),((MIN(20,time)*VLOOKUP(affo!G42, list!$J$48:$K$50,2,))+(time-MIN(20,time))-IF(affo!G42="Exponential",time-20+0.217*time*(EXP(4.606*(20-time)/time)-1),((time-20)^2)*(0.5/time))))))) | AS13: =IF($P29>0, $D42, 0) | AT13: =IF($P29>0, $F42, 0)
A14: Planted Tropical dry forest | B14: Planted Subtropical steppe | C14: Planted Temperate continental forest | G14: 7 | H14: =C30 | I14: =IF( $H14 <> "Please select", CONCATENATE(H14,continent_selected), "") | J14: =IF($I14<>"",VLOOKUP(affo!$I14, IPCC!$C$924:$E$1467, 3, FALSE),0) | K14: =$J14*0.47 | L14: =IF('2.LUC'!$BC42="",'2.LUC'!$BB42,'2.LUC'!$BC42) | M14: =IF(I14<>"",VLOOKUP(affo!$I14, IPCC!$C$924:$E$1467, 2, FALSE),0) | N14: =M14*0.47 | O14: =IF('2.LUC'!$BF42="",'2.LUC'!$BE42,'2.LUC'!$BF42) | P14: =IF($H14<>"Please select", IF(OR($J14<=125, $J14<= 75),INDEX(IPCC!$B$618:$AI$633,MATCH(continent_selected,IPCC!$A$618:$A$633,0),MATCH($H14,IPCC!$B$616:$AI$616,0)),(IF(OR($J14>125, $J14>75),INDEX(IPCC!$AJ$618:$BS$633,MATCH(continent_selected,IPCC!$A$618:$A$633,0),MATCH($H14,IPCC!$AJ$616:$BS$616,0)),"")))*$J14,0) | Q14: =P14*0.47 | R14: =IF('2.LUC'!$BI42="",'2.LUC'!$BH42,'2.LUC'!$BI42) | S14: =IF($H14 <>"Please select", IF(OR($M14 <=125, $M14 <= 75),INDEX(IPCC!$B$618:$AI$633,MATCH(continent_selected,IPCC!$A$618:$A$633,0),MATCH($H14,IPCC!$B$616:$AI$616,0)),(IF(OR($M14>125, $M14>75),INDEX(IPCC!$AJ$618:$BS$633,MATCH(continent_selected,IPCC!$A$618:$A$633,0),MATCH($H14,IPCC!$AJ$616:$BS$616,0)),"")))*$M14,0) | T14: =S14*0.47 | U14: =IF('2.LUC'!$BK42="",'2.LUC'!$BJ42,'2.LUC'!$BK42) | V14: =IF($H14<>"Please select", VLOOKUP($H14, IPCC!$A$643:$B$677, 2, FALSE), 0) | W14: =IF('2.LUC'!$BQ42="",'2.LUC'!$BP42,'2.LUC'!$BQ42) | X14: =IF($H14<>"Please select",VLOOKUP($H14,IPCC!$A$643:$C$677,3,FALSE),0) | Y14: =IF('2.LUC'!$BT42="",'2.LUC'!$BS42,'2.LUC'!$BT42) | Z14: =IF($I14<> "", SOCref, 0) | AA14: =IF('2.LUC'!$BW42="",'2.LUC'!$BV42,'2.LUC'!$BW42) | AB14: =IF('2.LUC'!BN42<> "", '2.LUC'!BN42*44/12, IF(H14="Please select",0,IF(INDEX(IPCC!$A$590:$AK$606,MATCH($I$7,IPCC!$A$590:$A$606,0),MATCH(H14,IPCC!$A$590:$AK$590,0))<= 125, INDEX(IPCC!$A$590:$AK$606,MATCH($I$7,IPCC!$A$590:$A$606,0),MATCH(H14,IPCC!$A$590:$AK$590,0))+(INDEX(IPCC!$A$590:$AK$606,MATCH($I$7,IPCC!$A$590:$A$606,0),MATCH(H14,IPCC!$A$590:$AK$590,0))*INDEX(IPCC!$A$617:$BS$633,MATCH($I$7,IPCC!$A$617:$A$633,0),MATCH(H14,IPCC!$A$616:$BS$616,0))),INDEX(IPCC!$A$590:$AK$606,MATCH($I$7,IPCC!$A$590:$A$606,0), MATCH(H14,IPCC!$A$590:$AK$590,0))+(INDEX(IPCC!$A$590:$AK$606,MATCH($I$7,IPCC!$A$590:$A$606,0),MATCH(H14,IPCC!$A$590:$AK$590,0))*INDEX(IPCC!$AJ$616:$BS$633,MATCH(continent_selected,IPCC!$A$616:$A$633,0),MATCH(H14,IPCC!$AJ$616:$BS$616,0)))))*0.47*44/12) | AC14: =IF(AB14>H43, "yes", "no") | AE14: Affo 7 | AF14: =IF($F30="YES", $D43*$P30*methane/1000,0) | AG14: =IF($F30="YES", $F43*$P30*methane/1000,0) | AH14: =IF($F30="YES", $D43*$Q30*Nitrous/1000,0) | AI14: =IF($F30="YES", $F43*$Q30*Nitrous/1000,0) | AJ14: =-(44/12)*($S30*(IF(E43="Immediate",D43*MIN(20,time),D43*IF(time>time+20,20,IF(time<20,(time*VLOOKUP(E43, list!$J$48:$K$50, 2,))+(time-time),((MIN(20,time)*VLOOKUP(affo!E43, list!$J$48:$K$50, 2,)) + (time-MIN(20,time))-IF(affo!E43="Exponential",time-20+0.217*time*(EXP(4.606*(20-time)/time)-1),((time-20)^2)*(0.5/time)))))))+($T30*(IF(affo!E43="Immediate", affo!D43*(time-MIN(20,time)), affo!D43*IF(time>time+20,(time*VLOOKUP(affo!E43, list!$J$48:$K$50,2,))+(time-time-20),IF(time<20,0,IF(affo!E43="Exponential",time-20+0.217*time*(EXP(4.606*(20-time)/time)-1),((time-20)^2)*(0.5/time)))))))) | AK14: =-(44/12)*($S30*(IF(G43="Immediate", F43*MIN(20,time), F43*IF(time>time+20,20,IF(time<20,(time*VLOOKUP(G43, list!$J$48:$K$50, 2,))+(time-time),((MIN(20,time)*VLOOKUP(affo!G43, list!$J$48:$K$50, 2,))+ (time-MIN(20,time))-IF(affo!G43="Exponential",time-20+0.217*time*(EXP(4.606*(20-time)/time)-1),((time-20)^2)*(0.5/time)))))))+($T30*(IF(affo!G43="Immediate", affo!F43*(time-MIN(20,time)), affo!F43*IF(time>time+20,(time*VLOOKUP(affo!G43, list!$J$48:$K$50,2,))+(time-time-20),IF(time<20,0,IF(affo!G43="Exponential",time-20+0.217*time*(EXP(4.606*(20-time)/time)-1),((time-20)^2)*(0.5/time)))))))) | AL14: =IF(time=0,0,$L43) | AM14: =IF(time=0,0, $M43) | AN14: =IF(time=0,0,$J43) | AO14: =IF(time=0,0,$K43) | AP14: =$M30*(IF(E43="Immediate", D43*MIN(20,time), D43*IF(time>=time+20,20,IF(time<=20,(time*VLOOKUP(E43, list!$J$48:$K$50, 2,))+(time-time),((MIN(20,time)*VLOOKUP(affo!E43, list!$J$48:$K$50,2,))+(time-MIN(20,time))-IF(affo!E43="Exponential",time-20+0.217*time*(EXP(4.606*(20-time)/time)-1),((time-20)^2)*(0.5/time))))))) | AQ14: =$M30*(IF(G43="Immediate", F43*MIN(20,time), F43*IF(time>time+20,20,IF(time<20,(time*VLOOKUP( G43, list!$J$48:$K$50, 2,))+(time-time),((MIN(20,time)*VLOOKUP(affo!G43, list!$J$48:$K$50,2,))+(time-MIN(20,time))-IF(affo!G43="Exponential",time-20+0.217*time*(EXP(4.606*(20-time)/time)-1),((time-20)^2)*(0.5/time))))))) | AS14: =IF($P30>0, $D43, 0) | AT14: =IF($P30>0, $F43, 0)
A15: Planted Tropical shrubland | B15: Planted Subtropical mountain systems | C15: Planted Temperate mountain systems | G15: 8 | H15: =C31 | I15: =IF( $H15 <> "Please select", CONCATENATE(H15,continent_selected), "") | J15: =IF($I15<>"",VLOOKUP(affo!$I15, IPCC!$C$924:$E$1467, 3, FALSE),0) | K15: =$J15*0.47 | L15: =IF('2.LUC'!$BC43="",'2.LUC'!$BB43,'2.LUC'!$BC43) | M15: =IF(I15<>"",VLOOKUP(affo!$I15, IPCC!$C$924:$E$1467, 2, FALSE),0) | N15: =M15*0.47 | O15: =IF('2.LUC'!$BF43="",'2.LUC'!$BE43,'2.LUC'!$BF43) | P15: =IF($H15<>"Please select", IF(OR($J15<=125, $J15<= 75),INDEX(IPCC!$B$618:$AI$633,MATCH(continent_selected,IPCC!$A$618:$A$633,0),MATCH($H15,IPCC!$B$616:$AI$616,0)),(IF(OR($J15>125, $J15>75),INDEX(IPCC!$AJ$618:$BS$633,MATCH(continent_selected,IPCC!$A$618:$A$633,0),MATCH($H15,IPCC!$AJ$616:$BS$616,0)),"")))*$J15,0) | Q15: =P15*0.47 | R15: =IF('2.LUC'!$BI43="",'2.LUC'!$BH43,'2.LUC'!$BI43) | S15: =IF($H15 <>"Please select", IF(OR($M15 <=125, $M15 <= 75),INDEX(IPCC!$B$618:$AI$633,MATCH(continent_selected,IPCC!$A$618:$A$633,0),MATCH($H15,IPCC!$B$616:$AI$616,0)),(IF(OR($M15>125, $M15>75),INDEX(IPCC!$AJ$618:$BS$633,MATCH(continent_selected,IPCC!$A$618:$A$633,0),MATCH($H15,IPCC!$AJ$616:$BS$616,0)),"")))*$M15,0) | T15: =S15*0.47 | U15: =IF('2.LUC'!$BK43="",'2.LUC'!$BJ43,'2.LUC'!$BK43) | V15: =IF($H15<>"Please select", VLOOKUP($H15, IPCC!$A$643:$B$677, 2, FALSE), 0) | W15: =IF('2.LUC'!$BQ43="",'2.LUC'!$BP43,'2.LUC'!$BQ43) | X15: =IF($H15<>"Please select",VLOOKUP($H15,IPCC!$A$643:$C$677,3,FALSE),0) | Y15: =IF('2.LUC'!$BT43="",'2.LUC'!$BS43,'2.LUC'!$BT43) | Z15: =IF($I15<> "", SOCref, 0) | AA15: =IF('2.LUC'!$BW43="",'2.LUC'!$BV43,'2.LUC'!$BW43) | AB15: =IF('2.LUC'!BN43<> "", '2.LUC'!BN43*44/12, IF(H15="Please select",0,IF(INDEX(IPCC!$A$590:$AK$606,MATCH($I$7,IPCC!$A$590:$A$606,0),MATCH(H15,IPCC!$A$590:$AK$590,0))<= 125, INDEX(IPCC!$A$590:$AK$606,MATCH($I$7,IPCC!$A$590:$A$606,0),MATCH(H15,IPCC!$A$590:$AK$590,0))+(INDEX(IPCC!$A$590:$AK$606,MATCH($I$7,IPCC!$A$590:$A$606,0),MATCH(H15,IPCC!$A$590:$AK$590,0))*INDEX(IPCC!$A$617:$BS$633,MATCH($I$7,IPCC!$A$617:$A$633,0),MATCH(H15,IPCC!$A$616:$BS$616,0))),INDEX(IPCC!$A$590:$AK$606,MATCH($I$7,IPCC!$A$590:$A$606,0), MATCH(H15,IPCC!$A$590:$AK$590,0))+(INDEX(IPCC!$A$590:$AK$606,MATCH($I$7,IPCC!$A$590:$A$606,0),MATCH(H15,IPCC!$A$590:$AK$590,0))*INDEX(IPCC!$AJ$616:$BS$633,MATCH(continent_selected,IPCC!$A$616:$A$633,0),MATCH(H15,IPCC!$AJ$616:$BS$616,0)))))*0.47*44/12) | AC15: =IF(AB15>H44, "yes", "no") | AE15: Affo 8 | AF15: =IF($F31="YES", $D44*$P31*methane/1000,0) | AG15: =IF($F31="YES", $F44*$P31*methane/1000,0) | AH15: =IF($F31="YES", $D44*$Q31*Nitrous/1000,0) | AI15: =IF($F31="YES", $F44*$Q31*Nitrous/1000,0) | AJ15: =-(44/12)*($S31*(IF(E44="Immediate",D44*MIN(20,time),D44*IF(time>time+20,20,IF(time<20,(time*VLOOKUP(E44, list!$J$48:$K$50, 2,))+(time-time),((MIN(20,time)*VLOOKUP(affo!E44, list!$J$48:$K$50, 2,)) + (time-MIN(20,time))-IF(affo!E44="Exponential",time-20+0.217*time*(EXP(4.606*(20-time)/time)-1),((time-20)^2)*(0.5/time)))))))+($T31*(IF(affo!E44="Immediate", affo!D44*(time-MIN(20,time)), affo!D44*IF(time>time+20,(time*VLOOKUP(affo!E44, list!$J$48:$K$50,2,))+(time-time-20),IF(time<20,0,IF(affo!E44="Exponential",time-20+0.217*time*(EXP(4.606*(20-time)/time)-1),((time-20)^2)*(0.5/time)))))))) | AK15: =-(44/12)*($S31*(IF(G44="Immediate", F44*MIN(20,time), F44*IF(time>time+20,20,IF(time<20,(time*VLOOKUP(G44, list!$J$48:$K$50, 2,))+(time-time),((MIN(20,time)*VLOOKUP(affo!G44, list!$J$48:$K$50, 2,))+ (time-MIN(20,time))-IF(affo!G44="Exponential",time-20+0.217*time*(EXP(4.606*(20-time)/time)-1),((time-20)^2)*(0.5/time)))))))+($T31*(IF(affo!G44="Immediate", affo!F44*(time-MIN(20,time)), affo!F44*IF(time>time+20,(time*VLOOKUP(affo!G44, list!$J$48:$K$50,2,))+(time-time-20),IF(time<20,0,IF(affo!G44="Exponential",time-20+0.217*time*(EXP(4.606*(20-time)/time)-1),((time-20)^2)*(0.5/time)))))))) | AL15: =IF(time=0,0,$L44) | AM15: =IF(time=0,0, $M44) | AN15: =IF(time=0,0,$J44) | AO15: =IF(time=0,0,$K44) | AP15: =$M31*(IF(E44="Immediate", D44*MIN(20,time), D44*IF(time>=time+20,20,IF(time<=20,(time*VLOOKUP(E44, list!$J$48:$K$50, 2,))+(time-time),((MIN(20,time)*VLOOKUP(affo!E44, list!$J$48:$K$50,2,))+(time-MIN(20,time))-IF(affo!E44="Exponential",time-20+0.217*time*(EXP(4.606*(20-time)/time)-1),((time-20)^2)*(0.5/time))))))) | AQ15: =$M31*(IF(G44="Immediate", F44*MIN(20,time), F44*IF(time>time+20,20,IF(time<20,(time*VLOOKUP( G44, list!$J$48:$K$50, 2,))+(time-time),((MIN(20,time)*VLOOKUP(affo!G44, list!$J$48:$K$50,2,))+(time-MIN(20,time))-IF(affo!G44="Exponential",time-20+0.217*time*(EXP(4.606*(20-time)/time)-1),((time-20)^2)*(0.5/time))))))) | AS15: =IF($P31>0, $D44, 0) | AT15: =IF($P31>0, $F44, 0)
C16: Planted Temperate desert | AS16: =SUM(AS8:AS15) | AT16: =SUM(AT8:AT15)
C17: Planted Temperate steppe
K20: SOC (0-T) | L20: ΔC Mineral | M20: ΔC Mineral | N20: MB | O20: Cf | S20: Tot_biomass growth | T20: Tot_biomass growth | U20: DOM | V20: DOM | W20: Total biomass growth with annual rate | AA20: Additional biomass availability
N21: mass of fuel | O21: the fraction | P21: Non-CO2 emissions from biomass burning | S21: AGB + BGB | T21: AGB + BGB | U21: Litter + Dead wood | V21: Litter + Dead wood | W21: WOP | X21: WP | Y21: WOP | Z21: WP | AA21: WOP | AB21: WP
C22: FINAL LU | D22: LU converted to FL | E22: Agroforestry systems | F22: Biomass burnt | H22: LU converted to FL | I22: Biomass of LUs converted to FL | J22: FLU | L22: SOC0 - SOC (0-T) | M22: limited to 20 yrs | N22: for combustion | O22: combusted | P22: CH4 | Q22: N2O | R22: Total_non-CO2 | S22: ( ≤ 20 years ) | T22: ( > 20 years ) | W22: AGB+BGB | X22: AGB+BGB | Y22: Total BGB | Z22: Total BGB | AA22: AGB+BGB | AB22: AGB+BGB
B23: Afforestation | C23: After Affo/Reforestation | E23: converted to FL | F23: before LUC | H23: incl. agroforestry systems | I23: tC/ha | J23: dimensionless | K23: tC/ha | L23: tC/ha | M23: tCO2/ha/yr | N23: tonnes dry matter/ha | O23: % | P23: kg CH4 | Q23: kg N2O | R23: tCO2 eq | S23: t C/ha/yr | T23: t C/ha/yr | U23: tC/ha | V23: tCO2/ha | W23: tCO2 | X23: tCO2 | Y23: tCO2/ha | Z23: tCO2/ha | AA23: tCO2/ha | AB23: tCO2/ha
B24: Affo 1 | C24: ='2.LUC'!$C36 | D24: ='2.LUC'!$I36 | E24: ='2.LUC'!$K36 | F24: ='2.LUC'!$G36 | H24: =IF('2.LUC'!$K36 = "Please select", IF('2.LUC'!$I36<>"Agroforestry", '2.LUC'!$I36, "Agroforestry - default"), '2.LUC'!$K36) | I24: =IF( '2.LUC'!$I36 <> "Please select", IF('2.LUC'!AT36=0, INDEX(IPCC!$D$1521:$Y$1680,MATCH(clim_moist_cont,IPCC!$C$1521:$C$1680,0),MATCH($H24,IPCC!$D$1520:$Y$1520,0)), '2.LUC'!AT36), 0) | J24: =IF( '2.LUC'!$I36 <> "Please select", INDEX(IPCC!$B$1689:$W$1698,MATCH(clim_moist, IPCC!$A$1689:$A$1698,0),MATCH(affo!$H24, IPCC!$B$1687:$W$1687,0)),0) | K24: =IF('2.LUC'!AW36=0, $J24*$Z8,'2.LUC'!AW36) | L24: =IF( '2.LUC'!$C36<> "Please select", VLOOKUP('2.LUC'!$C36, $H$8:$AA$15, 20, FALSE) - $K24, 0) | M24: =$L24*(-44/12)/20 | N24: =$I24*(1/0.4) | O24: =IF($H24 <> "Please select", VLOOKUP(H24, IPCC!$A$1473:$B$1495,2, FALSE), 0) | P24: =IF($H24<> "Please select", $N24*$O24*VLOOKUP($H24, IPCC!$A$1473:$E$1496, 4, FALSE), 0) | Q24: =IF($H24<> "Please select", $N24*$O24*VLOOKUP($H24, IPCC!$A$1473:$E$1496, 5, FALSE), 0) | R24: =($P24*methane + $Q24*Nitrous)/1000 | S24: =IF($C24<> "Please select", VLOOKUP($C24, $H$8:$U$15, 5, FALSE) + VLOOKUP($C24, $H$8:$U$15, 11, FALSE), 0) | T24: =IF($C24<> "Please select", VLOOKUP($C24, $H$8:$U$15, 8, FALSE) + VLOOKUP($C24, $H$8:$U$15, 14, FALSE), 0) | U24: =IF($C24<> "Please select", VLOOKUP($C24, $H$8:$Y$15, 16, FALSE) + VLOOKUP($C24, $H$8:$Y$15, 18, FALSE),0) | V24: =$U24*(-44/12) | W24: =-(44/12)*($S24*(IF(E37="Immediate",D37*MIN(20,time_tot),D37*IF(time_tot>time+20,20,IF(time_tot<20,(time*VLOOKUP(E37, list!$J$48:$K$50, 2,))+(time_tot-time),((MIN(20,time)*VLOOKUP(affo!E37, list!$J$48:$K$50, 2,)) + (time_tot-MIN(20,time))-IF(affo!E37="Exponential",time_tot-20+0.217*time*(EXP(4.606*(20-time_tot)/time)-1),((time_tot-20)^2)*(0.5/time)))))))+($T24*(IF(affo!E37="Immediate", affo!D37*(time_tot-MIN(20,time_tot)), affo!D37*IF(time_tot>time+20,(time*VLOOKUP(affo!E37, list!$J$48:$K$50,2,))+(time_tot-time-20),IF(time_tot<20,0,IF(affo!E37="Exponential",time_tot-20+0.217*time*(EXP(4.606*(20-time_tot)/time)-1),((time_tot-20)^2)*(0.5/time)))))))) | X24: =-(44/12)*($S24*(IF(G37="Immediate", F37*MIN(20,time_tot), F37*IF(time_tot>time+20,20,IF(time_tot<20,(time*VLOOKUP(G37, list!$J$48:$K$50, 2,))+(time_tot-time),((MIN(20,time)*VLOOKUP(affo!G37, list!$J$48:$K$50, 2,))+ (time_tot-MIN(20,time))-IF(affo!G37="Exponential",time_tot-20+0.217*time*(EXP(4.606*(20-time_tot)/time)-1),((time_tot-20)^2)*(0.5/time)))))))+($T24*(IF(affo!G37="Immediate", affo!F37*(time_tot-MIN(20,time_tot)), affo!F37*IF(time_tot>time+20,(time*VLOOKUP(affo!G37, list!$J$48:$K$50,2,))+(time_tot-time-20),IF(time_tot<20,0,IF(affo!G37="Exponential",time_tot-20+0.217*time*(EXP(4.606*(20-time_tot)/time)-1),((time_tot-20)^2)*(0.5/time)))))))) | Y24: =-(44/12)*(IF($C24<> "Please select", VLOOKUP($C24, $H$8:$U$15, 11, FALSE), 0)*(IF(E37="Immediate",D37*MIN(20,time_tot),D37*IF(time_tot>time+20,20,IF(time_tot<20,(time*VLOOKUP(E37, list!$J$48:$K$50, 2,))+(time_tot-time),((MIN(20,time)*VLOOKUP(affo!E37, list!$J$48:$K$50, 2,)) + (time_tot-MIN(20,time))-IF(affo!E37="Exponential",time_tot-20+0.217*time*(EXP(4.606*(20-time_tot)/time)-1),((time_tot-20)^2)*(0.5/time)))))))+(IF($C24<> "Please select", VLOOKUP($C24, $H$8:$U$15, 14, FALSE), 0)*(IF(affo!E37="Immediate", affo!D37*(time_tot-MIN(20,time_tot)), affo!D37*IF(time_tot>time+20,(time*VLOOKUP(affo!E37, list!$J$48:$K$50,2,))+(time_tot-time-20),IF(time_tot<20,0,IF(affo!E37="Exponential",time_tot-20+0.217*time*(EXP(4.606*(20-time_tot)/time)-1),((time_tot-20)^2)*(0.5/time)))))))) | Z24: =-(44/12)*(IF($C24<> "Please select", VLOOKUP($C24, $H$8:$U$15, 11, FALSE), 0)*(IF(G37="Immediate", F37*MIN(20,time_tot), F37*IF(time_tot>time+20,20,IF(time_tot<20,(time*VLOOKUP(G37, list!$J$48:$K$50, 2,))+(time_tot-time),((MIN(20,time)*VLOOKUP(affo!G37, list!$J$48:$K$50, 2,))+ (time_tot-MIN(20,time))-IF(affo!G37="Exponential",time_tot-20+0.217*time*(EXP(4.606*(20-time_tot)/time)-1),((time_tot-20)^2)*(0.5/time)))))))+(IF($C24<> "Please select", VLOOKUP($C24, $H$8:$U$15, 14, FALSE), 0)*(IF(affo!G37="Immediate", affo!F37*(time_tot-MIN(20,time_tot)), affo!F37*IF(time_tot>time+20,(time*VLOOKUP(affo!G37, list!$J$48:$K$50,2,))+(time_tot-time-20),IF(time_tot<20,0,IF(affo!G37="Exponential",time_tot-20+0.217*time*(EXP(4.606*(20-time_tot)/time)-1),((time_tot-20)^2)*(0.5/time)))))))) | AA24: =IF(W24<-AB8*D37,(-W24-AB8*D37)-(-Y24-((INDEX(IPCC!$A$590:$AK$606,MATCH($I$7,IPCC!$A$590:$A$606,0),MATCH(H8,IPCC!$A$590:$AK$590,0))*INDEX(IPCC!$A$617:$BS$633,MATCH($I$7,IPCC!$A$617:$A$633,0),MATCH(H8,IPCC!$A$616:$BS$616,0))))*0.47*44/12*D37),0) | AB24: =IF(X24<-AB8*F37,(-X24-AB8*F37)-(-Z24-((INDEX(IPCC!$A$590:$AK$606,MATCH($I$7,IPCC!$A$590:$A$606,0),MATCH(H8,IPCC!$A$590:$AK$590,0))*INDEX(IPCC!$A$617:$BS$633,MATCH($I$7,IPCC!$A$617:$A$633,0),MATCH(H8,IPCC!$A$616:$BS$616,0))))*0.47*44/12*F37),0) | AK24: All period in tCO2-e
B25: Affo 2 | C25: ='2.LUC'!$C37 | D25: ='2.LUC'!$I37 | E25: ='2.LUC'!$K37 | F25: ='2.LUC'!$G37 | H25: =IF('2.LUC'!$K37 = "Please select", IF('2.LUC'!$I37<>"Agroforestry", '2.LUC'!$I37, "Agroforestry - default"), '2.LUC'!$K37) | I25: =IF( '2.LUC'!$I37 <> "Please select", IF('2.LUC'!AT37=0, INDEX(IPCC!$D$1521:$Y$1680,MATCH(clim_moist_cont,IPCC!$C$1521:$C$1680,0),MATCH($H25,IPCC!$D$1520:$Y$1520,0)), '2.LUC'!AT37), 0) | J25: =IF( '2.LUC'!$I37 <> "Please select", INDEX(IPCC!$B$1689:$W$1698,MATCH(clim_moist, IPCC!$A$1689:$A$1698,0),MATCH(affo!$H25, IPCC!$B$1687:$W$1687,0)),0) | K25: =IF('2.LUC'!AW37=0, $J25*$Z9,'2.LUC'!AW37) | L25: =IF( '2.LUC'!$C37<> "Please select", VLOOKUP('2.LUC'!$C37, $H$8:$AA$15, 20, FALSE) - $K25, 0) | M25: =$L25*(-44/12)/20 | N25: =$I25*(1/0.4) | O25: =IF($H25 <> "Please select", VLOOKUP(H25, IPCC!$A$1473:$B$1495,2, FALSE), 0) | P25: =IF($H25<> "Please select", $N25*$O25*VLOOKUP($H25, IPCC!$A$1473:$E$1496, 4, FALSE), 0) | Q25: =IF($H25<> "Please select", $N25*$O25*VLOOKUP($H25, IPCC!$A$1473:$E$1496, 5, FALSE), 0) | R25: =($P25*methane + $Q25*Nitrous)/1000 | S25: =IF($C25<> "Please select", VLOOKUP($C25, $H$9:$U$15, 5, FALSE) + VLOOKUP($C25, $H$9:$U$15, 11, FALSE), 0) | T25: =IF($C25<> "Please select", VLOOKUP($C25, $H$9:$U$15, 8, FALSE) + VLOOKUP($C25, $H$9:$U$15, 14, FALSE), 0) | U25: =IF($C25<> "Please select", VLOOKUP($C25, $H$9:$Y$15, 16, FALSE) + VLOOKUP($C25, $H$9:$Y$15, 18, FALSE),0) | V25: =$U25*(-44/12) | W25: =-(44/12)*($S25*(IF(E38="Immediate",D38*MIN(20,time_tot),D38*IF(time_tot>time+20,20,IF(time_tot<20,(time*VLOOKUP(E38, list!$J$48:$K$50, 2,))+(time_tot-time),((MIN(20,time)*VLOOKUP(affo!E38, list!$J$48:$K$50, 2,)) + (time_tot-MIN(20,time))-IF(affo!E38="Exponential",time_tot-20+0.217*time*(EXP(4.606*(20-time_tot)/time)-1),((time_tot-20)^2)*(0.5/time)))))))+($T25*(IF(affo!E38="Immediate", affo!D38*(time_tot-MIN(20,time_tot)), affo!D38*IF(time_tot>time+20,(time*VLOOKUP(affo!E38, list!$J$48:$K$50,2,))+(time_tot-time-20),IF(time_tot<20,0,IF(affo!E38="Exponential",time_tot-20+0.217*time*(EXP(4.606*(20-time_tot)/time)-1),((time_tot-20)^2)*(0.5/time)))))))) | X25: =-(44/12)*($S25*(IF(G38="Immediate", F38*MIN(20,time_tot), F38*IF(time_tot>time+20,20,IF(time_tot<20,(time*VLOOKUP(G38, list!$J$48:$K$50, 2,))+(time_tot-time),((MIN(20,time)*VLOOKUP(affo!G38, list!$J$48:$K$50, 2,))+ (time_tot-MIN(20,time))-IF(affo!G38="Exponential",time_tot-20+0.217*time*(EXP(4.606*(20-time_tot)/time)-1),((time_tot-20)^2)*(0.5/time)))))))+($T25*(IF(affo!G38="Immediate", affo!F38*(time_tot-MIN(20,time_tot)), affo!F38*IF(time_tot>time+20,(time*VLOOKUP(affo!G38, list!$J$48:$K$50,2,))+(time_tot-time-20),IF(time_tot<20,0,IF(affo!G38="Exponential",time_tot-20+0.217*time*(EXP(4.606*(20-time_tot)/time)-1),((time_tot-20)^2)*(0.5/time)))))))) | Y25: =-(44/12)*(IF($C25<> "Please select", VLOOKUP($C25, $H$8:$U$15, 11, FALSE), 0)*(IF(E38="Immediate",D38*MIN(20,time_tot),D38*IF(time_tot>time+20,20,IF(time_tot<20,(time*VLOOKUP(E38, list!$J$48:$K$50, 2,))+(time_tot-time),((MIN(20,time)*VLOOKUP(affo!E38, list!$J$48:$K$50, 2,)) + (time_tot-MIN(20,time))-IF(affo!E38="Exponential",time_tot-20+0.217*time*(EXP(4.606*(20-time_tot)/time)-1),((time_tot-20)^2)*(0.5/time)))))))+(IF($C25<> "Please select", VLOOKUP($C25, $H$8:$U$15, 14, FALSE), 0)*(IF(affo!E38="Immediate", affo!D38*(time_tot-MIN(20,time_tot)), affo!D38*IF(time_tot>time+20,(time*VLOOKUP(affo!E38, list!$J$48:$K$50,2,))+(time_tot-time-20),IF(time_tot<20,0,IF(affo!E38="Exponential",time_tot-20+0.217*time*(EXP(4.606*(20-time_tot)/time)-1),((time_tot-20)^2)*(0.5/time)))))))) | Z25: =-(44/12)*(IF($C25<> "Please select", VLOOKUP($C25, $H$8:$U$15, 11, FALSE), 0)*(IF(G38="Immediate", F38*MIN(20,time_tot), F38*IF(time_tot>time+20,20,IF(time_tot<20,(time*VLOOKUP(G38, list!$J$48:$K$50, 2,))+(time_tot-time),((MIN(20,time)*VLOOKUP(affo!G38, list!$J$48:$K$50, 2,))+ (time_tot-MIN(20,time))-IF(affo!G38="Exponential",time_tot-20+0.217*time*(EXP(4.606*(20-time_tot)/time)-1),((time_tot-20)^2)*(0.5/time)))))))+(IF($C25<> "Please select", VLOOKUP($C25, $H$8:$U$15, 14, FALSE), 0)*(IF(affo!G38="Immediate", affo!F38*(time_tot-MIN(20,time_tot)), affo!F38*IF(time_tot>time+20,(time*VLOOKUP(affo!G38, list!$J$48:$K$50,2,))+(time_tot-time-20),IF(time_tot<20,0,IF(affo!G38="Exponential",time_tot-20+0.217*time*(EXP(4.606*(20-time_tot)/time)-1),((time_tot-20)^2)*(0.5/time)))))))) | AA25: =IF(W25<-AB9*D38,(-W25-AB9*D38)-(-Y25-((INDEX(IPCC!$A$590:$AK$606,MATCH($I$7,IPCC!$A$590:$A$606,0),MATCH(H9,IPCC!$A$590:$AK$590,0))*INDEX(IPCC!$A$617:$BS$633,MATCH($I$7,IPCC!$A$617:$A$633,0),MATCH(H9,IPCC!$A$616:$BS$616,0))))*0.47*44/12*D38),0) | AB25: =IF(X25<-AB9*F38,(-X25-AB9*F38)-(-Z25-((INDEX(IPCC!$A$590:$AK$606,MATCH($I$7,IPCC!$A$590:$A$606,0),MATCH(H9,IPCC!$A$590:$AK$590,0))*INDEX(IPCC!$A$617:$BS$633,MATCH($I$7,IPCC!$A$617:$A$633,0),MATCH(H9,IPCC!$A$616:$BS$616,0))))*0.47*44/12*F38),0) | AK25: Categories | AL25: Without | AM25: With
B26: Affo 3 | C26: ='2.LUC'!$C38 | D26: ='2.LUC'!$I38 | E26: ='2.LUC'!$K38 | F26: ='2.LUC'!$G38 | H26: =IF('2.LUC'!$K38 = "Please select", IF('2.LUC'!$I38<>"Agroforestry", '2.LUC'!$I38, "Agroforestry - default"), '2.LUC'!$K38) | I26: =IF( '2.LUC'!$I38 <> "Please select", IF('2.LUC'!AT38=0, INDEX(IPCC!$D$1521:$Y$1680,MATCH(clim_moist_cont,IPCC!$C$1521:$C$1680,0),MATCH($H26,IPCC!$D$1520:$Y$1520,0)), '2.LUC'!AT38), 0) | J26: =IF( '2.LUC'!$I38 <> "Please select", INDEX(IPCC!$B$1689:$W$1698,MATCH(clim_moist, IPCC!$A$1689:$A$1698,0),MATCH(affo!$H26, IPCC!$B$1687:$W$1687,0)),0) | K26: =IF('2.LUC'!AW38=0, $J26*$Z10,'2.LUC'!AW38) | L26: =IF( '2.LUC'!$C38<> "Please select", VLOOKUP('2.LUC'!$C38, $H$8:$AA$15, 20, FALSE) - $K26, 0) | M26: =$L26*(-44/12)/20 | N26: =$I26*(1/0.4) | O26: =IF($H26 <> "Please select", VLOOKUP(H26, IPCC!$A$1473:$B$1495,2, FALSE), 0) | P26: =IF($H26<> "Please select", $N26*$O26*VLOOKUP($H26, IPCC!$A$1473:$E$1496, 4, FALSE), 0) | Q26: =IF($H26<> "Please select", $N26*$O26*VLOOKUP($H26, IPCC!$A$1473:$E$1496, 5, FALSE), 0) | R26: =($P26*methane + $Q26*Nitrous)/1000 | S26: =IF($C26<> "Please select", VLOOKUP($C26, $H$10:$U$15, 5, FALSE) + VLOOKUP($C26, $H$10:$U$15, 11, FALSE), 0) | T26: =IF($C26<> "Please select", VLOOKUP($C26, $H$10:$U$15, 8, FALSE) + VLOOKUP($C26, $H$10:$U$15, 14, FALSE), 0) | U26: =IF($C26<> "Please select", VLOOKUP($C26, $H$10:$Y$15, 16, FALSE) + VLOOKUP($C26, $H$10:$Y$15, 18, FALSE),0) | V26: =$U26*(-44/12) | W26: =-(44/12)*($S26*(IF(E39="Immediate",D39*MIN(20,time_tot),D39*IF(time_tot>time+20,20,IF(time_tot<20,(time*VLOOKUP(E39, list!$J$48:$K$50, 2,))+(time_tot-time),((MIN(20,time)*VLOOKUP(affo!E39, list!$J$48:$K$50, 2,)) + (time_tot-MIN(20,time))-IF(affo!E39="Exponential",time_tot-20+0.217*time*(EXP(4.606*(20-time_tot)/time)-1),((time_tot-20)^2)*(0.5/time)))))))+($T26*(IF(affo!E39="Immediate", affo!D39*(time_tot-MIN(20,time_tot)), affo!D39*IF(time_tot>time+20,(time*VLOOKUP(affo!E39, list!$J$48:$K$50,2,))+(time_tot-time-20),IF(time_tot<20,0,IF(affo!E39="Exponential",time_tot-20+0.217*time*(EXP(4.606*(20-time_tot)/time)-1),((time_tot-20)^2)*(0.5/time)))))))) | X26: =-(44/12)*($S26*(IF(G39="Immediate", F39*MIN(20,time_tot), F39*IF(time_tot>time+20,20,IF(time_tot<20,(time*VLOOKUP(G39, list!$J$48:$K$50, 2,))+(time_tot-time),((MIN(20,time)*VLOOKUP(affo!G39, list!$J$48:$K$50, 2,))+ (time_tot-MIN(20,time))-IF(affo!G39="Exponential",time_tot-20+0.217*time*(EXP(4.606*(20-time_tot)/time)-1),((time_tot-20)^2)*(0.5/time)))))))+($T26*(IF(affo!G39="Immediate", affo!F39*(time_tot-MIN(20,time_tot)), affo!F39*IF(time_tot>time+20,(time*VLOOKUP(affo!G39, list!$J$48:$K$50,2,))+(time_tot-time-20),IF(time_tot<20,0,IF(affo!G39="Exponential",time_tot-20+0.217*time*(EXP(4.606*(20-time_tot)/time)-1),((time_tot-20)^2)*(0.5/time)))))))) | Y26: =-(44/12)*(IF($C26<> "Please select", VLOOKUP($C26, $H$8:$U$15, 11, FALSE), 0)*(IF(E39="Immediate",D39*MIN(20,time_tot),D39*IF(time_tot>time+20,20,IF(time_tot<20,(time*VLOOKUP(E39, list!$J$48:$K$50, 2,))+(time_tot-time),((MIN(20,time)*VLOOKUP(affo!E39, list!$J$48:$K$50, 2,)) + (time_tot-MIN(20,time))-IF(affo!E39="Exponential",time_tot-20+0.217*time*(EXP(4.606*(20-time_tot)/time)-1),((time_tot-20)^2)*(0.5/time)))))))+(IF($C26<> "Please select", VLOOKUP($C26, $H$8:$U$15, 14, FALSE), 0)*(IF(affo!E39="Immediate", affo!D39*(time_tot-MIN(20,time_tot)), affo!D39*IF(time_tot>time+20,(time*VLOOKUP(affo!E39, list!$J$48:$K$50,2,))+(time_tot-time-20),IF(time_tot<20,0,IF(affo!E39="Exponential",time_tot-20+0.217*time*(EXP(4.606*(20-time_tot)/time)-1),((time_tot-20)^2)*(0.5/time)))))))) | Z26: =-(44/12)*(IF($C26<> "Please select", VLOOKUP($C26, $H$8:$U$15, 11, FALSE), 0)*(IF(G39="Immediate", F39*MIN(20,time_tot), F39*IF(time_tot>time+20,20,IF(time_tot<20,(time*VLOOKUP(G39, list!$J$48:$K$50, 2,))+(time_tot-time),((MIN(20,time)*VLOOKUP(affo!G39, list!$J$48:$K$50, 2,))+ (time_tot-MIN(20,time))-IF(affo!G39="Exponential",time_tot-20+0.217*time*(EXP(4.606*(20-time_tot)/time)-1),((time_tot-20)^2)*(0.5/time)))))))+(IF($C26<> "Please select", VLOOKUP($C26, $H$8:$U$15, 14, FALSE), 0)*(IF(affo!G39="Immediate", affo!F39*(time_tot-MIN(20,time_tot)), affo!F39*IF(time_tot>time+20,(time*VLOOKUP(affo!G39, list!$J$48:$K$50,2,))+(time_tot-time-20),IF(time_tot<20,0,IF(affo!G39="Exponential",time_tot-20+0.217*time*(EXP(4.606*(20-time_tot)/time)-1),((time_tot-20)^2)*(0.5/time)))))))) | AA26: =IF(W26<-AB10*D39,(-W26-AB10*D39)-(-Y26-((INDEX(IPCC!$A$590:$AK$606,MATCH($I$7,IPCC!$A$590:$A$606,0),MATCH(H10,IPCC!$A$590:$AK$590,0))*INDEX(IPCC!$A$617:$BS$633,MATCH($I$7,IPCC!$A$617:$A$633,0),MATCH(H10,IPCC!$A$616:$BS$616,0))))*0.47*44/12*D39),0) | AB26: =IF(X26<-AB10*F39,(-X26-AB10*F39)-(-Z26-((INDEX(IPCC!$A$590:$AK$606,MATCH($I$7,IPCC!$A$590:$A$606,0),MATCH(H10,IPCC!$A$590:$AK$590,0))*INDEX(IPCC!$A$617:$BS$633,MATCH($I$7,IPCC!$A$617:$A$633,0),MATCH(H10,IPCC!$A$616:$BS$616,0))))*0.47*44/12*F39),0) | AK26: CO2 Biomass | AL26: =SUM(L37:L44)+SUM(H37:H44) | AM26: =SUM(I37:I44)+SUM(M37:M44)
B27: Affo 4 | C27: ='2.LUC'!$C39 | D27: ='2.LUC'!$I39 | E27: ='2.LUC'!$K39 | F27: ='2.LUC'!$G39 | H27: =IF('2.LUC'!$K39 = "Please select", IF('2.LUC'!$I39<>"Agroforestry", '2.LUC'!$I39, "Agroforestry - default"), '2.LUC'!$K39) | I27: =IF( '2.LUC'!$I39 <> "Please select", IF('2.LUC'!AT39=0, INDEX(IPCC!$D$1521:$Y$1680,MATCH(clim_moist_cont,IPCC!$C$1521:$C$1680,0),MATCH($H27,IPCC!$D$1520:$Y$1520,0)), '2.LUC'!AT39), 0) | J27: =IF( '2.LUC'!$I39 <> "Please select", INDEX(IPCC!$B$1689:$W$1698,MATCH(clim_moist, IPCC!$A$1689:$A$1698,0),MATCH(affo!$H27, IPCC!$B$1687:$W$1687,0)),0) | K27: =IF('2.LUC'!AW39=0, $J27*$Z11,'2.LUC'!AW39) | L27: =IF( '2.LUC'!$C39<> "Please select", VLOOKUP('2.LUC'!$C39, $H$8:$AA$15, 20, FALSE) - $K27, 0) | M27: =$L27*(-44/12)/20 | N27: =$I27*(1/0.4) | O27: =IF($H27 <> "Please select", VLOOKUP(H27, IPCC!$A$1473:$B$1495,2, FALSE), 0) | P27: =IF($H27<> "Please select", $N27*$O27*VLOOKUP($H27, IPCC!$A$1473:$E$1496, 4, FALSE), 0) | Q27: =IF($H27<> "Please select", $N27*$O27*VLOOKUP($H27, IPCC!$A$1473:$E$1496, 5, FALSE), 0) | R27: =($P27*methane + $Q27*Nitrous)/1000 | S27: =IF($C27<> "Please select", VLOOKUP($C27, $H$11:$U$15, 5, FALSE) + VLOOKUP($C27, $H$11:$U$15, 11, FALSE), 0) | T27: =IF($C27<> "Please select", VLOOKUP($C27, $H$11:$U$15, 8, FALSE) + VLOOKUP($C27, $H$11:$U$15, 14, FALSE), 0) | U27: =IF($C27<> "Please select", VLOOKUP($C27, $H$11:$Y$15, 16, FALSE) + VLOOKUP($C27, $H$11:$Y$15, 18, FALSE),0) | V27: =$U27*(-44/12) | W27: =-(44/12)*($S27*(IF(E40="Immediate",D40*MIN(20,time_tot),D40*IF(time_tot>time+20,20,IF(time_tot<20,(time*VLOOKUP(E40, list!$J$48:$K$50, 2,))+(time_tot-time),((MIN(20,time)*VLOOKUP(affo!E40, list!$J$48:$K$50, 2,)) + (time_tot-MIN(20,time))-IF(affo!E40="Exponential",time_tot-20+0.217*time*(EXP(4.606*(20-time_tot)/time)-1),((time_tot-20)^2)*(0.5/time)))))))+($T27*(IF(affo!E40="Immediate", affo!D40*(time_tot-MIN(20,time_tot)), affo!D40*IF(time_tot>time+20,(time*VLOOKUP(affo!E40, list!$J$48:$K$50,2,))+(time_tot-time-20),IF(time_tot<20,0,IF(affo!E40="Exponential",time_tot-20+0.217*time*(EXP(4.606*(20-time_tot)/time)-1),((time_tot-20)^2)*(0.5/time)))))))) | X27: =-(44/12)*($S27*(IF(G40="Immediate", F40*MIN(20,time_tot), F40*IF(time_tot>time+20,20,IF(time_tot<20,(time*VLOOKUP(G40, list!$J$48:$K$50, 2,))+(time_tot-time),((MIN(20,time)*VLOOKUP(affo!G40, list!$J$48:$K$50, 2,))+ (time_tot-MIN(20,time))-IF(affo!G40="Exponential",time_tot-20+0.217*time*(EXP(4.606*(20-time_tot)/time)-1),((time_tot-20)^2)*(0.5/time)))))))+($T27*(IF(affo!G40="Immediate", affo!F40*(time_tot-MIN(20,time_tot)), affo!F40*IF(time_tot>time+20,(time*VLOOKUP(affo!G40, list!$J$48:$K$50,2,))+(time_tot-time-20),IF(time_tot<20,0,IF(affo!G40="Exponential",time_tot-20+0.217*time*(EXP(4.606*(20-time_tot)/time)-1),((time_tot-20)^2)*(0.5/time)))))))) | Y27: =-(44/12)*(IF($C27<> "Please select", VLOOKUP($C27, $H$8:$U$15, 11, FALSE), 0)*(IF(E40="Immediate",D40*MIN(20,time_tot),D40*IF(time_tot>time+20,20,IF(time_tot<20,(time*VLOOKUP(E40, list!$J$48:$K$50, 2,))+(time_tot-time),((MIN(20,time)*VLOOKUP(affo!E40, list!$J$48:$K$50, 2,)) + (time_tot-MIN(20,time))-IF(affo!E40="Exponential",time_tot-20+0.217*time*(EXP(4.606*(20-time_tot)/time)-1),((time_tot-20)^2)*(0.5/time)))))))+(IF($C27<> "Please select", VLOOKUP($C27, $H$8:$U$15, 14, FALSE), 0)*(IF(affo!E40="Immediate", affo!D40*(time_tot-MIN(20,time_tot)), affo!D40*IF(time_tot>time+20,(time*VLOOKUP(affo!E40, list!$J$48:$K$50,2,))+(time_tot-time-20),IF(time_tot<20,0,IF(affo!E40="Exponential",time_tot-20+0.217*time*(EXP(4.606*(20-time_tot)/time)-1),((time_tot-20)^2)*(0.5/time)))))))) | Z27: =-(44/12)*(IF($C27<> "Please select", VLOOKUP($C27, $H$8:$U$15, 11, FALSE), 0)*(IF(G40="Immediate", F40*MIN(20,time_tot), F40*IF(time_tot>time+20,20,IF(time_tot<20,(time*VLOOKUP(G40, list!$J$48:$K$50, 2,))+(time_tot-time),((MIN(20,time)*VLOOKUP(affo!G40, list!$J$48:$K$50, 2,))+ (time_tot-MIN(20,time))-IF(affo!G40="Exponential",time_tot-20+0.217*time*(EXP(4.606*(20-time_tot)/time)-1),((time_tot-20)^2)*(0.5/time)))))))+(IF($C27<> "Please select", VLOOKUP($C27, $H$8:$U$15, 14, FALSE), 0)*(IF(affo!G40="Immediate", affo!F40*(time_tot-MIN(20,time_tot)), affo!F40*IF(time_tot>time+20,(time*VLOOKUP(affo!G40, list!$J$48:$K$50,2,))+(time_tot-time-20),IF(time_tot<20,0,IF(affo!G40="Exponential",time_tot-20+0.217*time*(EXP(4.606*(20-time_tot)/time)-1),((time_tot-20)^2)*(0.5/time)))))))) | AA27: =IF(W27<-AB11*D40,(-W27-AB11*D40)-(-Y27-((INDEX(IPCC!$A$590:$AK$606,MATCH($I$7,IPCC!$A$590:$A$606,0),MATCH(H11,IPCC!$A$590:$AK$590,0))*INDEX(IPCC!$A$617:$BS$633,MATCH($I$7,IPCC!$A$617:$A$633,0),MATCH(H11,IPCC!$A$616:$BS$616,0))))*0.47*44/12*D40),0) | AB27: =IF(X27<-AB11*F40,(-X27-AB11*F40)-(-Z27-((INDEX(IPCC!$A$590:$AK$606,MATCH($I$7,IPCC!$A$590:$A$606,0),MATCH(H11,IPCC!$A$590:$AK$590,0))*INDEX(IPCC!$A$617:$BS$633,MATCH($I$7,IPCC!$A$617:$A$633,0),MATCH(H11,IPCC!$A$616:$BS$616,0))))*0.47*44/12*F40),0) | AK27: CO2 DOM | AL27: =SUM(J37:J44) | AM27: =SUM(K37:K44)
B28: Affo 5 | C28: ='2.LUC'!$C40 | D28: ='2.LUC'!$I40 | E28: ='2.LUC'!$K40 | F28: ='2.LUC'!$G40 | H28: =IF('2.LUC'!$K40 = "Please select", IF('2.LUC'!$I40<>"Agroforestry", '2.LUC'!$I40, "Agroforestry - default"), '2.LUC'!$K40) | I28: =IF( '2.LUC'!$I40 <> "Please select", IF('2.LUC'!AT40=0, INDEX(IPCC!$D$1521:$Y$1680,MATCH(clim_moist_cont,IPCC!$C$1521:$C$1680,0),MATCH($H28,IPCC!$D$1520:$Y$1520,0)), '2.LUC'!AT40), 0) | J28: =IF( '2.LUC'!$I40 <> "Please select", INDEX(IPCC!$B$1689:$W$1698,MATCH(clim_moist, IPCC!$A$1689:$A$1698,0),MATCH(affo!$H28, IPCC!$B$1687:$W$1687,0)),0) | K28: =IF('2.LUC'!AW40=0, $J28*$Z12,'2.LUC'!AW40) | L28: =IF( '2.LUC'!$C40<> "Please select", VLOOKUP('2.LUC'!$C40, $H$8:$AA$15, 20, FALSE) - $K28, 0) | M28: =$L28*(-44/12)/20 | N28: =$I28*(1/0.4) | O28: =IF($H28 <> "Please select", VLOOKUP(H28, IPCC!$A$1473:$B$1495,2, FALSE), 0) | P28: =IF($H28<> "Please select", $N28*$O28*VLOOKUP($H28, IPCC!$A$1473:$E$1496, 4, FALSE), 0) | Q28: =IF($H28<> "Please select", $N28*$O28*VLOOKUP($H28, IPCC!$A$1473:$E$1496, 5, FALSE), 0) | R28: =($P28*methane + $Q28*Nitrous)/1000 | S28: =IF($C28<> "Please select", VLOOKUP($C28, $H$12:$U$15, 5, FALSE) + VLOOKUP($C28, $H$12:$U$15, 11, FALSE), 0) | T28: =IF($C28<> "Please select", VLOOKUP($C28, $H$12:$U$15, 8, FALSE) + VLOOKUP($C28, $H$12:$U$15, 14, FALSE), 0) | U28: =IF($C28<> "Please select", VLOOKUP($C28, $H$12:$Y$15, 16, FALSE) + VLOOKUP($C28, $H$12:$Y$15, 18, FALSE),0) | V28: =$U28*(-44/12) | W28: =-(44/12)*($S28*(IF(E41="Immediate",D41*MIN(20,time_tot),D41*IF(time_tot>time+20,20,IF(time_tot<20,(time*VLOOKUP(E41, list!$J$48:$K$50, 2,))+(time_tot-time),((MIN(20,time)*VLOOKUP(affo!E41, list!$J$48:$K$50, 2,)) + (time_tot-MIN(20,time))-IF(affo!E41="Exponential",time_tot-20+0.217*time*(EXP(4.606*(20-time_tot)/time)-1),((time_tot-20)^2)*(0.5/time)))))))+($T28*(IF(affo!E41="Immediate", affo!D41*(time_tot-MIN(20,time_tot)), affo!D41*IF(time_tot>time+20,(time*VLOOKUP(affo!E41, list!$J$48:$K$50,2,))+(time_tot-time-20),IF(time_tot<20,0,IF(affo!E41="Exponential",time_tot-20+0.217*time*(EXP(4.606*(20-time_tot)/time)-1),((time_tot-20)^2)*(0.5/time)))))))) | X28: =-(44/12)*($S28*(IF(G41="Immediate", F41*MIN(20,time_tot), F41*IF(time_tot>time+20,20,IF(time_tot<20,(time*VLOOKUP(G41, list!$J$48:$K$50, 2,))+(time_tot-time),((MIN(20,time)*VLOOKUP(affo!G41, list!$J$48:$K$50, 2,))+ (time_tot-MIN(20,time))-IF(affo!G41="Exponential",time_tot-20+0.217*time*(EXP(4.606*(20-time_tot)/time)-1),((time_tot-20)^2)*(0.5/time)))))))+($T28*(IF(affo!G41="Immediate", affo!F41*(time_tot-MIN(20,time_tot)), affo!F41*IF(time_tot>time+20,(time*VLOOKUP(affo!G41, list!$J$48:$K$50,2,))+(time_tot-time-20),IF(time_tot<20,0,IF(affo!G41="Exponential",time_tot-20+0.217*time*(EXP(4.606*(20-time_tot)/time)-1),((time_tot-20)^2)*(0.5/time)))))))) | Y28: =-(44/12)*(IF($C28<> "Please select", VLOOKUP($C28, $H$8:$U$15, 11, FALSE), 0)*(IF(E41="Immediate",D41*MIN(20,time_tot),D41*IF(time_tot>time+20,20,IF(time_tot<20,(time*VLOOKUP(E41, list!$J$48:$K$50, 2,))+(time_tot-time),((MIN(20,time)*VLOOKUP(affo!E41, list!$J$48:$K$50, 2,)) + (time_tot-MIN(20,time))-IF(affo!E41="Exponential",time_tot-20+0.217*time*(EXP(4.606*(20-time_tot)/time)-1),((time_tot-20)^2)*(0.5/time)))))))+(IF($C28<> "Please select", VLOOKUP($C28, $H$8:$U$15, 14, FALSE), 0)*(IF(affo!E41="Immediate", affo!D41*(time_tot-MIN(20,time_tot)), affo!D41*IF(time_tot>time+20,(time*VLOOKUP(affo!E41, list!$J$48:$K$50,2,))+(time_tot-time-20),IF(time_tot<20,0,IF(affo!E41="Exponential",time_tot-20+0.217*time*(EXP(4.606*(20-time_tot)/time)-1),((time_tot-20)^2)*(0.5/time)))))))) | Z28: =-(44/12)*(IF($C28<> "Please select", VLOOKUP($C28, $H$8:$U$15, 11, FALSE), 0)*(IF(G41="Immediate", F41*MIN(20,time_tot), F41*IF(time_tot>time+20,20,IF(time_tot<20,(time*VLOOKUP(G41, list!$J$48:$K$50, 2,))+(time_tot-time),((MIN(20,time)*VLOOKUP(affo!G41, list!$J$48:$K$50, 2,))+ (time_tot-MIN(20,time))-IF(affo!G41="Exponential",time_tot-20+0.217*time*(EXP(4.606*(20-time_tot)/time)-1),((time_tot-20)^2)*(0.5/time)))))))+(IF($C28<> "Please select", VLOOKUP($C28, $H$8:$U$15, 14, FALSE), 0)*(IF(affo!G41="Immediate", affo!F41*(time_tot-MIN(20,time_tot)), affo!F41*IF(time_tot>time+20,(time*VLOOKUP(affo!G41, list!$J$48:$K$50,2,))+(time_tot-time-20),IF(time_tot<20,0,IF(affo!G41="Exponential",time_tot-20+0.217*time*(EXP(4.606*(20-time_tot)/time)-1),((time_tot-20)^2)*(0.5/time)))))))) | AA28: =IF(W28<-AB12*D41,(-W28-AB12*D41)-(-Y28-((INDEX(IPCC!$A$590:$AK$606,MATCH($I$7,IPCC!$A$590:$A$606,0),MATCH(H12,IPCC!$A$590:$AK$590,0))*INDEX(IPCC!$A$617:$BS$633,MATCH($I$7,IPCC!$A$617:$A$633,0),MATCH(H12,IPCC!$A$616:$BS$616,0))))*0.47*44/12*D41),0) | AB28: =IF(X28<-AB12*F41,(-X28-AB12*F41)-(-Z28-((INDEX(IPCC!$A$590:$AK$606,MATCH($I$7,IPCC!$A$590:$A$606,0),MATCH(H12,IPCC!$A$590:$AK$590,0))*INDEX(IPCC!$A$617:$BS$633,MATCH($I$7,IPCC!$A$617:$A$633,0),MATCH(H12,IPCC!$A$616:$BS$616,0))))*0.47*44/12*F41),0) | AK28: CO2 soil | AL28: =SUM(N37:N44) | AM28: =SUM(O37:O44)
B29: Affo 6 | C29: ='2.LUC'!$C41 | D29: ='2.LUC'!$I41 | E29: ='2.LUC'!$K41 | F29: ='2.LUC'!$G41 | H29: =IF('2.LUC'!$K41 = "Please select", IF('2.LUC'!$I41<>"Agroforestry", '2.LUC'!$I41, "Agroforestry - default"), '2.LUC'!$K41) | I29: =IF( '2.LUC'!$I41 <> "Please select", IF('2.LUC'!AT41=0, INDEX(IPCC!$D$1521:$Y$1680,MATCH(clim_moist_cont,IPCC!$C$1521:$C$1680,0),MATCH($H29,IPCC!$D$1520:$Y$1520,0)), '2.LUC'!AT41), 0) | J29: =IF( '2.LUC'!$I41 <> "Please select", INDEX(IPCC!$B$1689:$W$1698,MATCH(clim_moist, IPCC!$A$1689:$A$1698,0),MATCH(affo!$H29, IPCC!$B$1687:$W$1687,0)),0) | K29: =IF('2.LUC'!AW41=0, $J29*$Z13,'2.LUC'!AW41) | L29: =IF( '2.LUC'!$C41<> "Please select", VLOOKUP('2.LUC'!$C41, $H$8:$AA$15, 20, FALSE) - $K29, 0) | M29: =$L29*(-44/12)/20 | N29: =$I29*(1/0.4) | O29: =IF($H29 <> "Please select", VLOOKUP(H29, IPCC!$A$1473:$B$1495,2, FALSE), 0) | P29: =IF($H29<> "Please select", $N29*$O29*VLOOKUP($H29, IPCC!$A$1473:$E$1496, 4, FALSE), 0) | Q29: =IF($H29<> "Please select", $N29*$O29*VLOOKUP($H29, IPCC!$A$1473:$E$1496, 5, FALSE), 0) | R29: =($P29*methane + $Q29*Nitrous)/1000 | S29: =IF($C29<> "Please select", VLOOKUP($C29, $H$13:$U$15, 5, FALSE) + VLOOKUP($C29, $H$13:$U$15, 11, FALSE), 0) | T29: =IF($C29<> "Please select", VLOOKUP($C29, $H$13:$U$15, 8, FALSE) + VLOOKUP($C29, $H$13:$U$15, 14, FALSE), 0) | U29: =IF($C29<> "Please select", VLOOKUP($C29, $H$13:$Y$15, 16, FALSE) + VLOOKUP($C29, $H$13:$Y$15, 18, FALSE),0) | V29: =$U29*(-44/12) | W29: =-(44/12)*($S29*(IF(E42="Immediate",D42*MIN(20,time_tot),D42*IF(time_tot>time+20,20,IF(time_tot<20,(time*VLOOKUP(E42, list!$J$48:$K$50, 2,))+(time_tot-time),((MIN(20,time)*VLOOKUP(affo!E42, list!$J$48:$K$50, 2,)) + (time_tot-MIN(20,time))-IF(affo!E42="Exponential",time_tot-20+0.217*time*(EXP(4.606*(20-time_tot)/time)-1),((time_tot-20)^2)*(0.5/time)))))))+($T29*(IF(affo!E42="Immediate", affo!D42*(time_tot-MIN(20,time_tot)), affo!D42*IF(time_tot>time+20,(time*VLOOKUP(affo!E42, list!$J$48:$K$50,2,))+(time_tot-time-20),IF(time_tot<20,0,IF(affo!E42="Exponential",time_tot-20+0.217*time*(EXP(4.606*(20-time_tot)/time)-1),((time_tot-20)^2)*(0.5/time)))))))) | X29: =-(44/12)*($S29*(IF(G42="Immediate", F42*MIN(20,time_tot), F42*IF(time_tot>time+20,20,IF(time_tot<20,(time*VLOOKUP(G42, list!$J$48:$K$50, 2,))+(time_tot-time),((MIN(20,time)*VLOOKUP(affo!G42, list!$J$48:$K$50, 2,))+ (time_tot-MIN(20,time))-IF(affo!G42="Exponential",time_tot-20+0.217*time*(EXP(4.606*(20-time_tot)/time)-1),((time_tot-20)^2)*(0.5/time)))))))+($T29*(IF(affo!G42="Immediate", affo!F42*(time_tot-MIN(20,time_tot)), affo!F42*IF(time_tot>time+20,(time*VLOOKUP(affo!G42, list!$J$48:$K$50,2,))+(time_tot-time-20),IF(time_tot<20,0,IF(affo!G42="Exponential",time_tot-20+0.217*time*(EXP(4.606*(20-time_tot)/time)-1),((time_tot-20)^2)*(0.5/time)))))))) | Y29: =-(44/12)*(IF($C29<> "Please select", VLOOKUP($C29, $H$8:$U$15, 11, FALSE), 0)*(IF(E42="Immediate",D42*MIN(20,time_tot),D42*IF(time_tot>time+20,20,IF(time_tot<20,(time*VLOOKUP(E42, list!$J$48:$K$50, 2,))+(time_tot-time),((MIN(20,time)*VLOOKUP(affo!E42, list!$J$48:$K$50, 2,)) + (time_tot-MIN(20,time))-IF(affo!E42="Exponential",time_tot-20+0.217*time*(EXP(4.606*(20-time_tot)/time)-1),((time_tot-20)^2)*(0.5/time)))))))+(IF($C29<> "Please select", VLOOKUP($C29, $H$8:$U$15, 14, FALSE), 0)*(IF(affo!E42="Immediate", affo!D42*(time_tot-MIN(20,time_tot)), affo!D42*IF(time_tot>time+20,(time*VLOOKUP(affo!E42, list!$J$48:$K$50,2,))+(time_tot-time-20),IF(time_tot<20,0,IF(affo!E42="Exponential",time_tot-20+0.217*time*(EXP(4.606*(20-time_tot)/time)-1),((time_tot-20)^2)*(0.5/time)))))))) | Z29: =-(44/12)*(IF($C29<> "Please select", VLOOKUP($C29, $H$8:$U$15, 11, FALSE), 0)*(IF(G42="Immediate", F42*MIN(20,time_tot), F42*IF(time_tot>time+20,20,IF(time_tot<20,(time*VLOOKUP(G42, list!$J$48:$K$50, 2,))+(time_tot-time),((MIN(20,time)*VLOOKUP(affo!G42, list!$J$48:$K$50, 2,))+ (time_tot-MIN(20,time))-IF(affo!G42="Exponential",time_tot-20+0.217*time*(EXP(4.606*(20-time_tot)/time)-1),((time_tot-20)^2)*(0.5/time)))))))+(IF($C29<> "Please select", VLOOKUP($C29, $H$8:$U$15, 14, FALSE), 0)*(IF(affo!G42="Immediate", affo!F42*(time_tot-MIN(20,time_tot)), affo!F42*IF(time_tot>time+20,(time*VLOOKUP(affo!G42, list!$J$48:$K$50,2,))+(time_tot-time-20),IF(time_tot<20,0,IF(affo!G42="Exponential",time_tot-20+0.217*time*(EXP(4.606*(20-time_tot)/time)-1),((time_tot-20)^2)*(0.5/time)))))))) | AA29: =IF(W29<-AB13*D42,(-W29-AB13*D42)-(-Y29-((INDEX(IPCC!$A$590:$AK$606,MATCH($I$7,IPCC!$A$590:$A$606,0),MATCH(H13,IPCC!$A$590:$AK$590,0))*INDEX(IPCC!$A$617:$BS$633,MATCH($I$7,IPCC!$A$617:$A$633,0),MATCH(H13,IPCC!$A$616:$BS$616,0))))*0.47*44/12*D42),0) | AB29: =IF(X29<-AB13*F42,(-X29-AB13*F42)-(-Z29-((INDEX(IPCC!$A$590:$AK$606,MATCH($I$7,IPCC!$A$590:$A$606,0),MATCH(H13,IPCC!$A$590:$AK$590,0))*INDEX(IPCC!$A$617:$BS$633,MATCH($I$7,IPCC!$A$617:$A$633,0),MATCH(H13,IPCC!$A$616:$BS$616,0))))*0.47*44/12*F42),0) | AK29: CH4 fire | AL29: =SUM(AF8:AF15) | AM29: =SUM(AG8:AG15)
B30: Affo 7 | C30: ='2.LUC'!$C42 | D30: ='2.LUC'!$I42 | E30: ='2.LUC'!$K42 | F30: ='2.LUC'!$G42 | H30: =IF('2.LUC'!$K42 = "Please select", IF('2.LUC'!$I42<>"Agroforestry", '2.LUC'!$I42, "Agroforestry - default"), '2.LUC'!$K42) | I30: =IF( '2.LUC'!$I42 <> "Please select", IF('2.LUC'!AT42=0, INDEX(IPCC!$D$1521:$Y$1680,MATCH(clim_moist_cont,IPCC!$C$1521:$C$1680,0),MATCH($H30,IPCC!$D$1520:$Y$1520,0)), '2.LUC'!AT42), 0) | J30: =IF( '2.LUC'!$I42 <> "Please select", INDEX(IPCC!$B$1689:$W$1698,MATCH(clim_moist, IPCC!$A$1689:$A$1698,0),MATCH(affo!$H30, IPCC!$B$1687:$W$1687,0)),0) | K30: =IF('2.LUC'!AW42=0, $J30*$Z14,'2.LUC'!AW42) | L30: =IF( '2.LUC'!$C42<> "Please select", VLOOKUP('2.LUC'!$C42, $H$8:$AA$15, 20, FALSE) - $K30, 0) | M30: =$L30*(-44/12)/20 | N30: =$I30*(1/0.4) | O30: =IF($H30 <> "Please select", VLOOKUP(H30, IPCC!$A$1473:$B$1495,2, FALSE), 0) | P30: =IF($H30<> "Please select", $N30*$O30*VLOOKUP($H30, IPCC!$A$1473:$E$1496, 4, FALSE), 0) | Q30: =IF($H30<> "Please select", $N30*$O30*VLOOKUP($H30, IPCC!$A$1473:$E$1496, 5, FALSE), 0) | R30: =($P30*methane + $Q30*Nitrous)/1000 | S30: =IF($C30<> "Please select", VLOOKUP($C30, $H$14:$U$15, 5, FALSE) + VLOOKUP($C30, $H$14:$U$15, 11, FALSE), 0) | T30: =IF($C30<> "Please select", VLOOKUP($C30, $H$14:$U$15, 8, FALSE) + VLOOKUP($C30, $H$14:$U$15, 14, FALSE), 0) | U30: =IF($C30<> "Please select", VLOOKUP($C30, $H$14:$Y$15, 16, FALSE) + VLOOKUP($C30, $H$14:$Y$15, 18, FALSE),0) | V30: =$U30*(-44/12) | W30: =-(44/12)*($S30*(IF(E43="Immediate",D43*MIN(20,time_tot),D43*IF(time_tot>time+20,20,IF(time_tot<20,(time*VLOOKUP(E43, list!$J$48:$K$50, 2,))+(time_tot-time),((MIN(20,time)*VLOOKUP(affo!E43, list!$J$48:$K$50, 2,)) + (time_tot-MIN(20,time))-IF(affo!E43="Exponential",time_tot-20+0.217*time*(EXP(4.606*(20-time_tot)/time)-1),((time_tot-20)^2)*(0.5/time)))))))+($T30*(IF(affo!E43="Immediate", affo!D43*(time_tot-MIN(20,time_tot)), affo!D43*IF(time_tot>time+20,(time*VLOOKUP(affo!E43, list!$J$48:$K$50,2,))+(time_tot-time-20),IF(time_tot<20,0,IF(affo!E43="Exponential",time_tot-20+0.217*time*(EXP(4.606*(20-time_tot)/time)-1),((time_tot-20)^2)*(0.5/time)))))))) | X30: =-(44/12)*($S30*(IF(G43="Immediate", F43*MIN(20,time_tot), F43*IF(time_tot>time+20,20,IF(time_tot<20,(time*VLOOKUP(G43, list!$J$48:$K$50, 2,))+(time_tot-time),((MIN(20,time)*VLOOKUP(affo!G43, list!$J$48:$K$50, 2,))+ (time_tot-MIN(20,time))-IF(affo!G43="Exponential",time_tot-20+0.217*time*(EXP(4.606*(20-time_tot)/time)-1),((time_tot-20)^2)*(0.5/time)))))))+($T30*(IF(affo!G43="Immediate", affo!F43*(time_tot-MIN(20,time_tot)), affo!F43*IF(time_tot>time+20,(time*VLOOKUP(affo!G43, list!$J$48:$K$50,2,))+(time_tot-time-20),IF(time_tot<20,0,IF(affo!G43="Exponential",time_tot-20+0.217*time*(EXP(4.606*(20-time_tot)/time)-1),((time_tot-20)^2)*(0.5/time)))))))) | Y30: =-(44/12)*(IF($C30<> "Please select", VLOOKUP($C30, $H$8:$U$15, 11, FALSE), 0)*(IF(E43="Immediate",D43*MIN(20,time_tot),D43*IF(time_tot>time+20,20,IF(time_tot<20,(time*VLOOKUP(E43, list!$J$48:$K$50, 2,))+(time_tot-time),((MIN(20,time)*VLOOKUP(affo!E43, list!$J$48:$K$50, 2,)) + (time_tot-MIN(20,time))-IF(affo!E43="Exponential",time_tot-20+0.217*time*(EXP(4.606*(20-time_tot)/time)-1),((time_tot-20)^2)*(0.5/time)))))))+(IF($C30<> "Please select", VLOOKUP($C30, $H$8:$U$15, 14, FALSE), 0)*(IF(affo!E43="Immediate", affo!D43*(time_tot-MIN(20,time_tot)), affo!D43*IF(time_tot>time+20,(time*VLOOKUP(affo!E43, list!$J$48:$K$50,2,))+(time_tot-time-20),IF(time_tot<20,0,IF(affo!E43="Exponential",time_tot-20+0.217*time*(EXP(4.606*(20-time_tot)/time)-1),((time_tot-20)^2)*(0.5/time)))))))) | Z30: =-(44/12)*(IF($C30<> "Please select", VLOOKUP($C30, $H$8:$U$15, 11, FALSE), 0)*(IF(G43="Immediate", F43*MIN(20,time_tot), F43*IF(time_tot>time+20,20,IF(time_tot<20,(time*VLOOKUP(G43, list!$J$48:$K$50, 2,))+(time_tot-time),((MIN(20,time)*VLOOKUP(affo!G43, list!$J$48:$K$50, 2,))+ (time_tot-MIN(20,time))-IF(affo!G43="Exponential",time_tot-20+0.217*time*(EXP(4.606*(20-time_tot)/time)-1),((time_tot-20)^2)*(0.5/time)))))))+(IF($C30<> "Please select", VLOOKUP($C30, $H$8:$U$15, 14, FALSE), 0)*(IF(affo!G43="Immediate", affo!F43*(time_tot-MIN(20,time_tot)), affo!F43*IF(time_tot>time+20,(time*VLOOKUP(affo!G43, list!$J$48:$K$50,2,))+(time_tot-time-20),IF(time_tot<20,0,IF(affo!G43="Exponential",time_tot-20+0.217*time*(EXP(4.606*(20-time_tot)/time)-1),((time_tot-20)^2)*(0.5/time)))))))) | AA30: =IF(W30<-AB14*D43,(-W30-AB14*D43)-(-Y30-((INDEX(IPCC!$A$590:$AK$606,MATCH($I$7,IPCC!$A$590:$A$606,0),MATCH(H14,IPCC!$A$590:$AK$590,0))*INDEX(IPCC!$A$617:$BS$633,MATCH($I$7,IPCC!$A$617:$A$633,0),MATCH(H14,IPCC!$A$616:$BS$616,0))))*0.47*44/12*D43),0) | AB30: =IF(X30<-AB14*F43,(-X30-AB14*F43)-(-Z30-((INDEX(IPCC!$A$590:$AK$606,MATCH($I$7,IPCC!$A$590:$A$606,0),MATCH(H14,IPCC!$A$590:$AK$590,0))*INDEX(IPCC!$A$617:$BS$633,MATCH($I$7,IPCC!$A$617:$A$633,0),MATCH(H14,IPCC!$A$616:$BS$616,0))))*0.47*44/12*F43),0) | AK30: N2O fire | AL30: =SUM(AH8:AH15) | AM30: =SUM(AI8:AI15)
B31: Affo 8 | C31: ='2.LUC'!$C43 | D31: ='2.LUC'!$I43 | E31: ='2.LUC'!$K43 | F31: ='2.LUC'!$G43 | H31: =IF('2.LUC'!$K43 = "Please select", IF('2.LUC'!$I43<>"Agroforestry", '2.LUC'!$I43, "Agroforestry - default"), '2.LUC'!$K43) | I31: =IF( '2.LUC'!$I43 <> "Please select", IF('2.LUC'!AT43=0, INDEX(IPCC!$D$1521:$Y$1680,MATCH(clim_moist_cont,IPCC!$C$1521:$C$1680,0),MATCH($H31,IPCC!$D$1520:$Y$1520,0)), '2.LUC'!AT43), 0) | J31: =IF( '2.LUC'!$I43 <> "Please select", INDEX(IPCC!$B$1689:$W$1698,MATCH(clim_moist, IPCC!$A$1689:$A$1698,0),MATCH(affo!$H31, IPCC!$B$1687:$W$1687,0)),0) | K31: =IF('2.LUC'!AW43=0, $J31*$Z15,'2.LUC'!AW43) | L31: =IF( '2.LUC'!$C43<> "Please select", VLOOKUP('2.LUC'!$C43, $H$8:$AA$15, 20, FALSE) - $K31, 0) | M31: =$L31*(-44/12)/20 | N31: =$I31*(1/0.4) | O31: =IF($H31 <> "Please select", VLOOKUP(H31, IPCC!$A$1473:$B$1495,2, FALSE), 0) | P31: =IF($H31<> "Please select", $N31*$O31*VLOOKUP($H31, IPCC!$A$1473:$E$1496, 4, FALSE), 0) | Q31: =IF($H31<> "Please select", $N31*$O31*VLOOKUP($H31, IPCC!$A$1473:$E$1496, 5, FALSE), 0) | R31: =($P31*methane + $Q31*Nitrous)/1000 | S31: =IF($C31<> "Please select", VLOOKUP($C31, $H$15:$U$15, 5, FALSE) + VLOOKUP($C31, $H$15:$U$15, 11, FALSE), 0) | T31: =IF($C31<> "Please select", VLOOKUP($C31, $H$15:$U$15, 8, FALSE) + VLOOKUP($C31, $H$15:$U$15, 14, FALSE), 0) | U31: =IF($C31<> "Please select", VLOOKUP($C31, $H$15:$Y$15, 16, FALSE) + VLOOKUP($C31, $H$15:$Y$15, 18, FALSE),0) | V31: =$U31*(-44/12) | W31: =-(44/12)*($S31*(IF(E44="Immediate",D44*MIN(20,time_tot),D44*IF(time_tot>time+20,20,IF(time_tot<20,(time*VLOOKUP(E44, list!$J$48:$K$50, 2,))+(time_tot-time),((MIN(20,time)*VLOOKUP(affo!E44, list!$J$48:$K$50, 2,)) + (time_tot-MIN(20,time))-IF(affo!E44="Exponential",time_tot-20+0.217*time*(EXP(4.606*(20-time_tot)/time)-1),((time_tot-20)^2)*(0.5/time)))))))+($T31*(IF(affo!E44="Immediate", affo!D44*(time_tot-MIN(20,time_tot)), affo!D44*IF(time_tot>time+20,(time*VLOOKUP(affo!E44, list!$J$48:$K$50,2,))+(time_tot-time-20),IF(time_tot<20,0,IF(affo!E44="Exponential",time_tot-20+0.217*time*(EXP(4.606*(20-time_tot)/time)-1),((time_tot-20)^2)*(0.5/time)))))))) | X31: =-(44/12)*($S31*(IF(G44="Immediate", F44*MIN(20,time_tot), F44*IF(time_tot>time+20,20,IF(time_tot<20,(time*VLOOKUP(G44, list!$J$48:$K$50, 2,))+(time_tot-time),((MIN(20,time)*VLOOKUP(affo!G44, list!$J$48:$K$50, 2,))+ (time_tot-MIN(20,time))-IF(affo!G44="Exponential",time_tot-20+0.217*time*(EXP(4.606*(20-time_tot)/time)-1),((time_tot-20)^2)*(0.5/time)))))))+($T31*(IF(affo!G44="Immediate", affo!F44*(time_tot-MIN(20,time_tot)), affo!F44*IF(time_tot>time+20,(time*VLOOKUP(affo!G44, list!$J$48:$K$50,2,))+(time_tot-time-20),IF(time_tot<20,0,IF(affo!G44="Exponential",time_tot-20+0.217*time*(EXP(4.606*(20-time_tot)/time)-1),((time_tot-20)^2)*(0.5/time)))))))) | Y31: =-(44/12)*(IF($C31<> "Please select", VLOOKUP($C31, $H$8:$U$15, 11, FALSE), 0)*(IF(E44="Immediate",D44*MIN(20,time_tot),D44*IF(time_tot>time+20,20,IF(time_tot<20,(time*VLOOKUP(E44, list!$J$48:$K$50, 2,))+(time_tot-time),((MIN(20,time)*VLOOKUP(affo!E44, list!$J$48:$K$50, 2,)) + (time_tot-MIN(20,time))-IF(affo!E44="Exponential",time_tot-20+0.217*time*(EXP(4.606*(20-time_tot)/time)-1),((time_tot-20)^2)*(0.5/time)))))))+(IF($C31<> "Please select", VLOOKUP($C31, $H$8:$U$15, 14, FALSE), 0)*(IF(affo!E44="Immediate", affo!D44*(time_tot-MIN(20,time_tot)), affo!D44*IF(time_tot>time+20,(time*VLOOKUP(affo!E44, list!$J$48:$K$50,2,))+(time_tot-time-20),IF(time_tot<20,0,IF(affo!E44="Exponential",time_tot-20+0.217*time*(EXP(4.606*(20-time_tot)/time)-1),((time_tot-20)^2)*(0.5/time)))))))) | Z31: =-(44/12)*(IF($C31<> "Please select", VLOOKUP($C31, $H$8:$U$15, 11, FALSE), 0)*(IF(G44="Immediate", F44*MIN(20,time_tot), F44*IF(time_tot>time+20,20,IF(time_tot<20,(time*VLOOKUP(G44, list!$J$48:$K$50, 2,))+(time_tot-time),((MIN(20,time)*VLOOKUP(affo!G44, list!$J$48:$K$50, 2,))+ (time_tot-MIN(20,time))-IF(affo!G44="Exponential",time_tot-20+0.217*time*(EXP(4.606*(20-time_tot)/time)-1),((time_tot-20)^2)*(0.5/time)))))))+(IF($C31<> "Please select", VLOOKUP($C31, $H$8:$U$15, 14, FALSE), 0)*(IF(affo!G44="Immediate", affo!F44*(time_tot-MIN(20,time_tot)), affo!F44*IF(time_tot>time+20,(time*VLOOKUP(affo!G44, list!$J$48:$K$50,2,))+(time_tot-time-20),IF(time_tot<20,0,IF(affo!G44="Exponential",time_tot-20+0.217*time*(EXP(4.606*(20-time_tot)/time)-1),((time_tot-20)^2)*(0.5/time)))))))) | AA31: =IF(W31<-AB15*D44,(-W31-AB15*D44)-(-Y31-((INDEX(IPCC!$A$590:$AK$606,MATCH($I$7,IPCC!$A$590:$A$606,0),MATCH(H15,IPCC!$A$590:$AK$590,0))*INDEX(IPCC!$A$617:$BS$633,MATCH($I$7,IPCC!$A$617:$A$633,0),MATCH(H15,IPCC!$A$616:$BS$616,0))))*0.47*44/12*D44),0) | AB31: =IF(X31<-AB15*F44,(-X31-AB15*F44)-(-Z31-((INDEX(IPCC!$A$590:$AK$606,MATCH($I$7,IPCC!$A$590:$A$606,0),MATCH(H15,IPCC!$A$590:$AK$590,0))*INDEX(IPCC!$A$617:$BS$633,MATCH($I$7,IPCC!$A$617:$A$633,0),MATCH(H15,IPCC!$A$616:$BS$616,0))))*0.47*44/12*F44),0) | AK31: Total | AL31: =SUM(AL26:AL30) | AM31: =SUM(AM26:AM30) | AN31: =AM31-AL31
AK33: Balance in tCO2-e
C34: Afforested/Reforested Area (ha) | H34: Total Biomass Gain (AGB + BGB) | J34: DOM Gain (Dead wood + litter) | L34: Biomass Loss | N34: Soil | P34: Fire | AK34: Categories | AL34: Total | AM34: Implementation | AN34: Capitalization
B35: GHG emissions | C35: Start | D35: Without Project | F35: With Project | H35: Without Project | I35: With Project | J35: Without Project | K35: With Project | L35: Without Project | M35: With Project | N35: Without Project | O35: With Project | P35: Without Project | Q35: With Project | S35: Total Balance (tCO2-e) | AK35: CO2 Biomass | AL35: =SUM(I37:I44)+SUM(M37:M44)-SUM(H37:H44)-SUM(L37:L44) | AM35: =IF(time=0, 0, SUM(AK8:AK15)-SUM(AJ8:AJ15)+SUM(AM8:AM15)-SUM(AL8:AL15)) | AN35: =AL35-AM35
B36: Name | C36: t0 | D36: Area (ha) | E36: Rate | F36: Area (ha) | G36: Rate | H36: tCO2 | I36: tCO2 | J36: tCO2 | K36: tCO2 | L36: tCO2 | M36: tCO2 | N36: tCO2 | O36: tCO2 | P36: tCO2 | Q36: tCO2 | S36: WITHOUT | T36: WITH | U36: BALANCE | AK36: CO2 DOM | AL36: =SUM(K37:K44)-SUM(J37:J44) | AM36: =SUM(AO8:AO15)-SUM(AN8:AN15) | AN36: =AL36-AM36
B37: Affo 1 | C37: 0 | D37: ='2.LUC'!$N36 | E37: =VLOOKUP('2.LUC'!$O36, list!$I$48:$J$50,2,FALSE ) | F37: ='2.LUC'!$P36 | G37: =VLOOKUP('2.LUC'!$Q36, list!$I$48:$J$50,2,FALSE ) | H37: =IF(W24<-AB8*D37,-AB8*D37,W24) | I37: =IF(X24<-AB8*F37,-AB8*F37,X24) | J37: =$V24*$D37 | K37: =$F37*$V24 | L37: =IF('2.LUC'!$C36<> "Please select", ((affo!$D37*affo!I24)*44/12), 0) | M37: =IF('2.LUC'!$C36<> "Please select", ((affo!$F37*affo!I24)*44/12), 0) | N37: =IF(ABS($M24*(IF(E37="Immediate", D37*MIN(20,time_tot), D37*IF(time_tot>time+20,20,IF(time_tot<20,(time*VLOOKUP(E37, list!$J$48:$K$50, 2,))+(time_tot-time),((MIN(20,time)*VLOOKUP(affo!E37, list!$J$48:$K$50,2,))+(time_tot-MIN(20,time))-IF(affo!E37="Exponential",time_tot-20+0.217*time*(EXP(4.606*(20-time_tot)/time)-1),((time_tot-20)^2)*(0.5/time))))))))>=ABS(L24*-44/12*D37),L24*-44/12*D37,$M24*(IF(E37="Immediate", D37*MIN(20,time_tot), D37*IF(time_tot>time+20,20,IF(time_tot<20,(time*VLOOKUP(E37, list!$J$48:$K$50, 2,))+(time_tot-time),((MIN(20,time)*VLOOKUP(affo!E37, list!$J$48:$K$50,2,))+(time_tot-MIN(20,time))-IF(affo!E37="Exponential",time_tot-20+0.217*time*(EXP(4.606*(20-time_tot)/time)-1),((time_tot-20)^2)*(0.5/time)))))))) | O37: =IF(ABS($M24*(IF(G37="Immediate", F37*MIN(20,time_tot), F37*IF(time_tot>time+20,20,IF(time_tot<20,(time*VLOOKUP( G37, list!$J$48:$K$50, 2,))+(time_tot-time),((MIN(20,time)*VLOOKUP(affo!G37, list!$J$48:$K$50,2,))+(time_tot-MIN(20,time))-IF(affo!G37="Exponential",time_tot-20+0.217*time*(EXP(4.606*(20-time_tot)/time)-1),((time_tot-20)^2)*(0.5/time))))))))>=ABS(L24*-44/12*F37),L24*-44/12*F37,$M24*(IF(G37="Immediate", F37*MIN(20,time_tot), F37*IF(time_tot>time+20,20,IF(time_tot<20,(time*VLOOKUP( G37, list!$J$48:$K$50, 2,))+(time_tot-time),((MIN(20,time)*VLOOKUP(affo!G37, list!$J$48:$K$50,2,))+(time_tot-MIN(20,time))-IF(affo!G37="Exponential",time_tot-20+0.217*time*(EXP(4.606*(20-time_tot)/time)-1),((time_tot-20)^2)*(0.5/time)))))))) | P37: =IF(F24="YES", $D37*$R24, 0) | Q37: =IF(F24="YES", $F37*$R24, 0) | S37: =H37+J37+L37+N37+P37 | T37: =I37+K37+M37+O37+Q37 | U37: =T37-S37 | AK37: CO2 soil | AL37: =SUM(O37:O44)-SUM(N37:N44) | AM37: =SUM(AQ8:AQ15)-SUM(AP8:AP15) | AN37: =AL37-AM37
B38: Affo 2 | C38: 0 | D38: ='2.LUC'!$N37 | E38: =VLOOKUP('2.LUC'!$O37, list!$I$48:$J$50,2,FALSE ) | F38: ='2.LUC'!$P37 | G38: =VLOOKUP('2.LUC'!$Q37, list!$I$48:$J$50,2,FALSE ) | H38: =IF(W25<-AB9*D38,-AB9*D38,W25) | I38: =IF(X25<-AB9*F38,-AB9*F38,X25) | J38: =$V25*$D38 | K38: =$F38*$V25 | L38: =IF('2.LUC'!$C37<> "Please select", ((affo!$D38*affo!I25)*44/12), 0) | M38: =IF('2.LUC'!$C37<> "Please select", ((affo!$F38*affo!I25)*44/12), 0) | N38: =IF(ABS($M25*(IF(E38="Immediate", D38*MIN(20,time_tot), D38*IF(time_tot>time+20,20,IF(time_tot<20,(time*VLOOKUP(E38, list!$J$48:$K$50, 2,))+(time_tot-time),((MIN(20,time)*VLOOKUP(affo!E38, list!$J$48:$K$50,2,))+(time_tot-MIN(20,time))-IF(affo!E38="Exponential",time_tot-20+0.217*time*(EXP(4.606*(20-time_tot)/time)-1),((time_tot-20)^2)*(0.5/time))))))))>=ABS(L25*-44/12*D38),L25*-44/12*D38,$M25*(IF(E38="Immediate", D38*MIN(20,time_tot), D38*IF(time_tot>time+20,20,IF(time_tot<20,(time*VLOOKUP(E38, list!$J$48:$K$50, 2,))+(time_tot-time),((MIN(20,time)*VLOOKUP(affo!E38, list!$J$48:$K$50,2,))+(time_tot-MIN(20,time))-IF(affo!E38="Exponential",time_tot-20+0.217*time*(EXP(4.606*(20-time_tot)/time)-1),((time_tot-20)^2)*(0.5/time)))))))) | O38: =IF(ABS($M25*(IF(G38="Immediate", F38*MIN(20,time_tot), F38*IF(time_tot>time+20,20,IF(time_tot<20,(time*VLOOKUP( G38, list!$J$48:$K$50, 2,))+(time_tot-time),((MIN(20,time)*VLOOKUP(affo!G38, list!$J$48:$K$50,2,))+(time_tot-MIN(20,time))-IF(affo!G38="Exponential",time_tot-20+0.217*time*(EXP(4.606*(20-time_tot)/time)-1),((time_tot-20)^2)*(0.5/time))))))))>=ABS(L25*-44/12*F38),L25*-44/12*F38,$M25*(IF(G38="Immediate", F38*MIN(20,time_tot), F38*IF(time_tot>time+20,20,IF(time_tot<20,(time*VLOOKUP( G38, list!$J$48:$K$50, 2,))+(time_tot-time),((MIN(20,time)*VLOOKUP(affo!G38, list!$J$48:$K$50,2,))+(time_tot-MIN(20,time))-IF(affo!G38="Exponential",time_tot-20+0.217*time*(EXP(4.606*(20-time_tot)/time)-1),((time_tot-20)^2)*(0.5/time)))))))) | P38: =IF(F25="YES", $D38*$R25, 0) | Q38: =IF(F25="YES", $F38*$R25, 0) | S38: =H38+J38+L38+N38+P38 | T38: =I38+K38+M38+O38+Q38 | U38: =T38-S38 | AK38: CH4 fire | AL38: =SUM(AG8:AG15)-SUM(AF8:AF15) | AM38: =IF(time=0,0, AL38) | AN38: =AL38-AM38
B39: Affo 3 | C39: 0 | D39: ='2.LUC'!$N38 | E39: =VLOOKUP('2.LUC'!$O38, list!$I$48:$J$50,2,FALSE ) | F39: ='2.LUC'!$P38 | G39: =VLOOKUP('2.LUC'!$Q38, list!$I$48:$J$50,2,FALSE ) | H39: =IF(W26<-AB10*D39,-AB10*D39,W26) | I39: =IF(X26<-AB10*F39,-AB10*F39,X26) | J39: =$V26*$D39 | K39: =$F39*$V26 | L39: =IF('2.LUC'!$C38<> "Please select", ((affo!$D39*affo!I26)*44/12), 0) | M39: =IF('2.LUC'!$C38<> "Please select", ((affo!$F39*affo!I26)*44/12), 0) | N39: =IF(ABS($M26*(IF(E39="Immediate", D39*MIN(20,time_tot), D39*IF(time_tot>time+20,20,IF(time_tot<20,(time*VLOOKUP(E39, list!$J$48:$K$50, 2,))+(time_tot-time),((MIN(20,time)*VLOOKUP(affo!E39, list!$J$48:$K$50,2,))+(time_tot-MIN(20,time))-IF(affo!E39="Exponential",time_tot-20+0.217*time*(EXP(4.606*(20-time_tot)/time)-1),((time_tot-20)^2)*(0.5/time))))))))>=ABS(L26*-44/12*D39),L26*-44/12*D39,$M26*(IF(E39="Immediate", D39*MIN(20,time_tot), D39*IF(time_tot>time+20,20,IF(time_tot<20,(time*VLOOKUP(E39, list!$J$48:$K$50, 2,))+(time_tot-time),((MIN(20,time)*VLOOKUP(affo!E39, list!$J$48:$K$50,2,))+(time_tot-MIN(20,time))-IF(affo!E39="Exponential",time_tot-20+0.217*time*(EXP(4.606*(20-time_tot)/time)-1),((time_tot-20)^2)*(0.5/time)))))))) | O39: =IF(ABS($M26*(IF(G39="Immediate", F39*MIN(20,time_tot), F39*IF(time_tot>time+20,20,IF(time_tot<20,(time*VLOOKUP( G39, list!$J$48:$K$50, 2,))+(time_tot-time),((MIN(20,time)*VLOOKUP(affo!G39, list!$J$48:$K$50,2,))+(time_tot-MIN(20,time))-IF(affo!G39="Exponential",time_tot-20+0.217*time*(EXP(4.606*(20-time_tot)/time)-1),((time_tot-20)^2)*(0.5/time))))))))>=ABS(L26*-44/12*F39),L26*-44/12*F39,$M26*(IF(G39="Immediate", F39*MIN(20,time_tot), F39*IF(time_tot>time+20,20,IF(time_tot<20,(time*VLOOKUP( G39, list!$J$48:$K$50, 2,))+(time_tot-time),((MIN(20,time)*VLOOKUP(affo!G39, list!$J$48:$K$50,2,))+(time_tot-MIN(20,time))-IF(affo!G39="Exponential",time_tot-20+0.217*time*(EXP(4.606*(20-time_tot)/time)-1),((time_tot-20)^2)*(0.5/time)))))))) | P39: =IF(F26="YES", $D39*$R26, 0) | Q39: =IF(F26="YES", $F39*$R26, 0) | S39: =H39+J39+L39+N39+P39 | T39: =I39+K39+M39+O39+Q39 | U39: =T39-S39 | AK39: N2O fire | AL39: =SUM(AI8:AI15)-SUM(AH8:AH15) | AM39: =IF(time=0, 0, AL39) | AN39: =AL39-AM39
B40: Affo 4 | C40: 0 | D40: ='2.LUC'!$N39 | E40: =VLOOKUP('2.LUC'!$O39, list!$I$48:$J$50,2,FALSE ) | F40: ='2.LUC'!$P39 | G40: =VLOOKUP('2.LUC'!$Q39, list!$I$48:$J$50,2,FALSE ) | H40: =IF(W27<-AB11*D40,-AB11*D40,W27) | I40: =IF(X27<-AB11*F40,-AB11*F40,X27) | J40: =$V27*$D40 | K40: =$F40*$V27 | L40: =IF('2.LUC'!$C39<> "Please select", ((affo!$D40*affo!I27)*44/12), 0) | M40: =IF('2.LUC'!$C39<> "Please select", ((affo!$F40*affo!I27)*44/12), 0) | N40: =IF(ABS($M27*(IF(E40="Immediate", D40*MIN(20,time_tot), D40*IF(time_tot>time+20,20,IF(time_tot<20,(time*VLOOKUP(E40, list!$J$48:$K$50, 2,))+(time_tot-time),((MIN(20,time)*VLOOKUP(affo!E40, list!$J$48:$K$50,2,))+(time_tot-MIN(20,time))-IF(affo!E40="Exponential",time_tot-20+0.217*time*(EXP(4.606*(20-time_tot)/time)-1),((time_tot-20)^2)*(0.5/time))))))))>=ABS(L27*-44/12*D40),L27*-44/12*D40,$M27*(IF(E40="Immediate", D40*MIN(20,time_tot), D40*IF(time_tot>time+20,20,IF(time_tot<20,(time*VLOOKUP(E40, list!$J$48:$K$50, 2,))+(time_tot-time),((MIN(20,time)*VLOOKUP(affo!E40, list!$J$48:$K$50,2,))+(time_tot-MIN(20,time))-IF(affo!E40="Exponential",time_tot-20+0.217*time*(EXP(4.606*(20-time_tot)/time)-1),((time_tot-20)^2)*(0.5/time)))))))) | O40: =IF(ABS($M27*(IF(G40="Immediate", F40*MIN(20,time_tot), F40*IF(time_tot>time+20,20,IF(time_tot<20,(time*VLOOKUP( G40, list!$J$48:$K$50, 2,))+(time_tot-time),((MIN(20,time)*VLOOKUP(affo!G40, list!$J$48:$K$50,2,))+(time_tot-MIN(20,time))-IF(affo!G40="Exponential",time_tot-20+0.217*time*(EXP(4.606*(20-time_tot)/time)-1),((time_tot-20)^2)*(0.5/time))))))))>=ABS(L27*-44/12*F40),L27*-44/12*F40,$M27*(IF(G40="Immediate", F40*MIN(20,time_tot), F40*IF(time_tot>time+20,20,IF(time_tot<20,(time*VLOOKUP( G40, list!$J$48:$K$50, 2,))+(time_tot-time),((MIN(20,time)*VLOOKUP(affo!G40, list!$J$48:$K$50,2,))+(time_tot-MIN(20,time))-IF(affo!G40="Exponential",time_tot-20+0.217*time*(EXP(4.606*(20-time_tot)/time)-1),((time_tot-20)^2)*(0.5/time)))))))) | P40: =IF(F27="YES", $D40*$R27, 0) | Q40: =IF(F27="YES", $F40*$R27, 0) | S40: =H40+J40+L40+N40+P40 | T40: =I40+K40+M40+O40+Q40 | U40: =T40-S40 | AK40: Total | AL40: =SUM(AL35:AL39) | AM40: =SUM(AM35:AM39) | AN40: =SUM(AN35:AN39)
B41: Affo 5 | C41: 0 | D41: ='2.LUC'!$N40 | E41: =VLOOKUP('2.LUC'!$O40, list!$I$48:$J$50,2,FALSE ) | F41: ='2.LUC'!$P40 | G41: =VLOOKUP('2.LUC'!$Q40, list!$I$48:$J$50,2,FALSE ) | H41: =IF(W28<-AB12*D41,-AB12*D41,W28) | I41: =IF(X28<-AB12*F41,-AB12*F41,X28) | J41: =$V28*$D41 | K41: =$F41*$V28 | L41: =IF('2.LUC'!$C40<> "Please select", ((affo!$D41*affo!I28)*44/12), 0) | M41: =IF('2.LUC'!$C40<> "Please select", ((affo!$F41*affo!I28)*44/12), 0) | N41: =IF(ABS($M28*(IF(E41="Immediate", D41*MIN(20,time_tot), D41*IF(time_tot>time+20,20,IF(time_tot<20,(time*VLOOKUP(E41, list!$J$48:$K$50, 2,))+(time_tot-time),((MIN(20,time)*VLOOKUP(affo!E41, list!$J$48:$K$50,2,))+(time_tot-MIN(20,time))-IF(affo!E41="Exponential",time_tot-20+0.217*time*(EXP(4.606*(20-time_tot)/time)-1),((time_tot-20)^2)*(0.5/time))))))))>=ABS(L28*-44/12*D41),L28*-44/12*D41,$M28*(IF(E41="Immediate", D41*MIN(20,time_tot), D41*IF(time_tot>time+20,20,IF(time_tot<20,(time*VLOOKUP(E41, list!$J$48:$K$50, 2,))+(time_tot-time),((MIN(20,time)*VLOOKUP(affo!E41, list!$J$48:$K$50,2,))+(time_tot-MIN(20,time))-IF(affo!E41="Exponential",time_tot-20+0.217*time*(EXP(4.606*(20-time_tot)/time)-1),((time_tot-20)^2)*(0.5/time)))))))) | O41: =IF(ABS($M28*(IF(G41="Immediate", F41*MIN(20,time_tot), F41*IF(time_tot>time+20,20,IF(time_tot<20,(time*VLOOKUP( G41, list!$J$48:$K$50, 2,))+(time_tot-time),((MIN(20,time)*VLOOKUP(affo!G41, list!$J$48:$K$50,2,))+(time_tot-MIN(20,time))-IF(affo!G41="Exponential",time_tot-20+0.217*time*(EXP(4.606*(20-time_tot)/time)-1),((time_tot-20)^2)*(0.5/time))))))))>=ABS(L28*-44/12*F41),L28*-44/12*F41,$M28*(IF(G41="Immediate", F41*MIN(20,time_tot), F41*IF(time_tot>time+20,20,IF(time_tot<20,(time*VLOOKUP( G41, list!$J$48:$K$50, 2,))+(time_tot-time),((MIN(20,time)*VLOOKUP(affo!G41, list!$J$48:$K$50,2,))+(time_tot-MIN(20,time))-IF(affo!G41="Exponential",time_tot-20+0.217*time*(EXP(4.606*(20-time_tot)/time)-1),((time_tot-20)^2)*(0.5/time)))))))) | P41: =IF(F28="YES", $D41*$R28, 0) | Q41: =IF(F28="YES", $F41*$R28, 0) | S41: =H41+J41+L41+N41+P41 | T41: =I41+K41+M41+O41+Q41 | U41: =T41-S41
B42: Affo 6 | C42: 0 | D42: ='2.LUC'!$N41 | E42: =VLOOKUP('2.LUC'!$O41, list!$I$48:$J$50,2,FALSE ) | F42: ='2.LUC'!$P41 | G42: =VLOOKUP('2.LUC'!$Q41, list!$I$48:$J$50,2,FALSE ) | H42: =IF(W29<-AB13*D42,-AB13*D42,W29) | I42: =IF(X29<-AB13*F42,-AB13*F42,X29) | J42: =$V29*$D42 | K42: =$F42*$V29 | L42: =IF('2.LUC'!$C41<> "Please select", ((affo!$D42*affo!I29)*44/12), 0) | M42: =IF('2.LUC'!$C41<> "Please select", ((affo!$F42*affo!I29)*44/12), 0) | N42: =IF(ABS($M29*(IF(E42="Immediate", D42*MIN(20,time_tot), D42*IF(time_tot>time+20,20,IF(time_tot<20,(time*VLOOKUP(E42, list!$J$48:$K$50, 2,))+(time_tot-time),((MIN(20,time)*VLOOKUP(affo!E42, list!$J$48:$K$50,2,))+(time_tot-MIN(20,time))-IF(affo!E42="Exponential",time_tot-20+0.217*time*(EXP(4.606*(20-time_tot)/time)-1),((time_tot-20)^2)*(0.5/time))))))))>=ABS(L29*-44/12*D42),L29*-44/12*D42,$M29*(IF(E42="Immediate", D42*MIN(20,time_tot), D42*IF(time_tot>time+20,20,IF(time_tot<20,(time*VLOOKUP(E42, list!$J$48:$K$50, 2,))+(time_tot-time),((MIN(20,time)*VLOOKUP(affo!E42, list!$J$48:$K$50,2,))+(time_tot-MIN(20,time))-IF(affo!E42="Exponential",time_tot-20+0.217*time*(EXP(4.606*(20-time_tot)/time)-1),((time_tot-20)^2)*(0.5/time)))))))) | O42: =IF(ABS($M29*(IF(G42="Immediate", F42*MIN(20,time_tot), F42*IF(time_tot>time+20,20,IF(time_tot<20,(time*VLOOKUP( G42, list!$J$48:$K$50, 2,))+(time_tot-time),((MIN(20,time)*VLOOKUP(affo!G42, list!$J$48:$K$50,2,))+(time_tot-MIN(20,time))-IF(affo!G42="Exponential",time_tot-20+0.217*time*(EXP(4.606*(20-time_tot)/time)-1),((time_tot-20)^2)*(0.5/time))))))))>=ABS(L29*-44/12*F42),L29*-44/12*F42,$M29*(IF(G42="Immediate", F42*MIN(20,time_tot), F42*IF(time_tot>time+20,20,IF(time_tot<20,(time*VLOOKUP( G42, list!$J$48:$K$50, 2,))+(time_tot-time),((MIN(20,time)*VLOOKUP(affo!G42, list!$J$48:$K$50,2,))+(time_tot-MIN(20,time))-IF(affo!G42="Exponential",time_tot-20+0.217*time*(EXP(4.606*(20-time_tot)/time)-1),((time_tot-20)^2)*(0.5/time)))))))) | P42: =IF(F29="YES", $D42*$R29, 0) | Q42: =IF(F29="YES", $F42*$R29, 0) | S42: =H42+J42+L42+N42+P42 | T42: =I42+K42+M42+O42+Q42 | U42: =T42-S42
B43: Affo 7 | C43: 0 | D43: ='2.LUC'!$N42 | E43: =VLOOKUP('2.LUC'!$O42, list!$I$48:$J$50,2,FALSE ) | F43: ='2.LUC'!$P42 | G43: =VLOOKUP('2.LUC'!$Q42, list!$I$48:$J$50,2,FALSE ) | H43: =IF(W30<-AB14*D43,-AB14*D43,W30) | I43: =IF(X30<-AB14*F43,-AB14*F43,X30) | J43: =$V30*$D43 | K43: =$F43*$V30 | L43: =IF('2.LUC'!$C42<> "Please select", ((affo!$D43*affo!I30)*44/12), 0) | M43: =IF('2.LUC'!$C42<> "Please select", ((affo!$F43*affo!I30)*44/12), 0) | N43: =IF(ABS($M30*(IF(E43="Immediate", D43*MIN(20,time_tot), D43*IF(time_tot>time+20,20,IF(time_tot<20,(time*VLOOKUP(E43, list!$J$48:$K$50, 2,))+(time_tot-time),((MIN(20,time)*VLOOKUP(affo!E43, list!$J$48:$K$50,2,))+(time_tot-MIN(20,time))-IF(affo!E43="Exponential",time_tot-20+0.217*time*(EXP(4.606*(20-time_tot)/time)-1),((time_tot-20)^2)*(0.5/time))))))))>=ABS(L30*-44/12*D43),L30*-44/12*D43,$M30*(IF(E43="Immediate", D43*MIN(20,time_tot), D43*IF(time_tot>time+20,20,IF(time_tot<20,(time*VLOOKUP(E43, list!$J$48:$K$50, 2,))+(time_tot-time),((MIN(20,time)*VLOOKUP(affo!E43, list!$J$48:$K$50,2,))+(time_tot-MIN(20,time))-IF(affo!E43="Exponential",time_tot-20+0.217*time*(EXP(4.606*(20-time_tot)/time)-1),((time_tot-20)^2)*(0.5/time)))))))) | O43: =IF(ABS($M30*(IF(G43="Immediate", F43*MIN(20,time_tot), F43*IF(time_tot>time+20,20,IF(time_tot<20,(time*VLOOKUP( G43, list!$J$48:$K$50, 2,))+(time_tot-time),((MIN(20,time)*VLOOKUP(affo!G43, list!$J$48:$K$50,2,))+(time_tot-MIN(20,time))-IF(affo!G43="Exponential",time_tot-20+0.217*time*(EXP(4.606*(20-time_tot)/time)-1),((time_tot-20)^2)*(0.5/time))))))))>=ABS(L30*-44/12*F43),L30*-44/12*F43,$M30*(IF(G43="Immediate", F43*MIN(20,time_tot), F43*IF(time_tot>time+20,20,IF(time_tot<20,(time*VLOOKUP( G43, list!$J$48:$K$50, 2,))+(time_tot-time),((MIN(20,time)*VLOOKUP(affo!G43, list!$J$48:$K$50,2,))+(time_tot-MIN(20,time))-IF(affo!G43="Exponential",time_tot-20+0.217*time*(EXP(4.606*(20-time_tot)/time)-1),((time_tot-20)^2)*(0.5/time)))))))) | P43: =IF(F30="YES", $D43*$R30, 0) | Q43: =IF(F30="YES", $F43*$R30, 0) | S43: =H43+J43+L43+N43+P43 | T43: =I43+K43+M43+O43+Q43 | U43: =T43-S43
B44: Affo 8 | C44: 0 | D44: ='2.LUC'!$N43 | E44: =VLOOKUP('2.LUC'!$O43, list!$I$48:$J$50,2,FALSE ) | F44: ='2.LUC'!$P43 | G44: =VLOOKUP('2.LUC'!$Q43, list!$I$48:$J$50,2,FALSE ) | H44: =IF(W31<-AB15*D44,-AB15*D44,W31) | I44: =IF(X31<-AB15*F44,-AB15*F44,X31) | J44: =$V31*$D44 | K44: =$F44*$V31 | L44: =IF('2.LUC'!$C43<> "Please select", ((affo!$D44*affo!I31)*44/12), 0) | M44: =IF('2.LUC'!$C43<> "Please select", ((affo!$F44*affo!I31)*44/12), 0) | N44: =IF(ABS($M31*(IF(E44="Immediate", D44*MIN(20,time_tot), D44*IF(time_tot>time+20,20,IF(time_tot<20,(time*VLOOKUP(E44, list!$J$48:$K$50, 2,))+(time_tot-time),((MIN(20,time)*VLOOKUP(affo!E44, list!$J$48:$K$50,2,))+(time_tot-MIN(20,time))-IF(affo!E44="Exponential",time_tot-20+0.217*time*(EXP(4.606*(20-time_tot)/time)-1),((time_tot-20)^2)*(0.5/time))))))))>=ABS(L31*-44/12*D44),L31*-44/12*D44,$M31*(IF(E44="Immediate", D44*MIN(20,time_tot), D44*IF(time_tot>time+20,20,IF(time_tot<20,(time*VLOOKUP(E44, list!$J$48:$K$50, 2,))+(time_tot-time),((MIN(20,time)*VLOOKUP(affo!E44, list!$J$48:$K$50,2,))+(time_tot-MIN(20,time))-IF(affo!E44="Exponential",time_tot-20+0.217*time*(EXP(4.606*(20-time_tot)/time)-1),((time_tot-20)^2)*(0.5/time)))))))) | O44: =IF(ABS($M31*(IF(G44="Immediate", F44*MIN(20,time_tot), F44*IF(time_tot>time+20,20,IF(time_tot<20,(time*VLOOKUP( G44, list!$J$48:$K$50, 2,))+(time_tot-time),((MIN(20,time)*VLOOKUP(affo!G44, list!$J$48:$K$50,2,))+(time_tot-MIN(20,time))-IF(affo!G44="Exponential",time_tot-20+0.217*time*(EXP(4.606*(20-time_tot)/time)-1),((time_tot-20)^2)*(0.5/time))))))))>=ABS(L31*-44/12*F44),L31*-44/12*F44,$M31*(IF(G44="Immediate", F44*MIN(20,time_tot), F44*IF(time_tot>time+20,20,IF(time_tot<20,(time*VLOOKUP( G44, list!$J$48:$K$50, 2,))+(time_tot-time),((MIN(20,time)*VLOOKUP(affo!G44, list!$J$48:$K$50,2,))+(time_tot-MIN(20,time))-IF(affo!G44="Exponential",time_tot-20+0.217*time*(EXP(4.606*(20-time_tot)/time)-1),((time_tot-20)^2)*(0.5/time)))))))) | P44: =IF(F31="YES", $D44*$R31, 0) | Q44: =IF(F31="YES", $F44*$R31, 0) | S44: =H44+J44+L44+N44+P44 | T44: =I44+K44+M44+O44+Q44 | U44: =T44-S44
R46: Total Afforestation | S46: =SUM(S37:S44) | T46: =SUM(T37:T44) | U46: =T46-S46
T49: TEST TIER 2 biomass | U49: =SUM('2.LUC'!BC36:BC43,'2.LUC'!BI36:BI43)

Sheet defo
A3: 2.1 Deforestation
A7: IPCC forest classes stratified by climate | G7: No | H7: Forest classes per IPCC climate region | I7: AGB default | J7: AGB default | K7: AGB tier 2 | L7: BGB | M7: BGB default | N7: BGB tier 2 | O7: Litter | P7: Litter default | Q7: Dead Wood | R7: DW Tier 2 | S7: SOC(0-T) | T7: SOC Tier 2
A8: Tropical | B8: WarmTemperate | C8: CoolTemperate | D8: Boreal | E8: TropicalMontane | H8: =climate2 | I8: t d.m./ha | J8: t C/ha | K8: tC/ha | L8: t d.m./ha | M8: t C/ha | N8: tC/ha | O8: t C/ha | P8: tC/ha | Q8: t C/ha | R8: tC/ha | S8: tC/ha | T8: tC/ha
A9: Tropical rainforest | B9: Subtropical humid forest | C9: Temperate oceanic forest | D9: Boreal coniferous forest | E9: Tropical mountain systems | G9: 1 | H9: =B23 | I9: =IF(H9="Please select",0,IF(H9="Mangrove Forest",VLOOKUP(clim_moist,IPCC!$A$1502:$G$1510,2,FALSE),INDEX(IPCC!$B$590:$AK$606,MATCH(continent_selected,IPCC!$A$590:$A$606,0),MATCH(H9,IPCC!$B$590:$AK$590,0)))) | J9: =IF(H9="Please select",0,IF(H9="Mangrove Forest",$I9*0.451,$I9*0.47)) | K9: =IF('2.LUC'!$AT11="",'2.LUC'!$AS11,'2.LUC'!$AT11) | L9: =IF(H9 = "Please select",0, IF(H9="Mangrove Forest",VLOOKUP(clim_moist,IPCC!$A$1502:$G$1511,6,FALSE),IF(OR(I9<=125,I9<=75),INDEX(IPCC!$B$618:$AI$633,MATCH(continent_selected,IPCC!$A$618:$A$633,0),MATCH(H9,IPCC!$B$616:$AI$616,0)),(IF(OR(I9>125,I9>75),INDEX(IPCC!$AJ$616:$BS$633,MATCH(continent_selected,IPCC!$A$616:$A$633,0),MATCH(H9,IPCC!$AJ$616:$BS$616,0)),""))))*I9) | M9: =IF(H9="Please select",0,IF(H9="Mangrove Forest",L9*0.451,L9*0.47)) | N9: =IF('2.LUC'!AW11="",'2.LUC'!AV11,'2.LUC'!AW11) | O9: =IF(H9 = "Please select", 0, IF(H9 = "Mangrove Forest", VLOOKUP(clim_moist, IPCC!$A$1502:$J$1511, 8, FALSE),VLOOKUP(H9, IPCC!$A$643:$B$677, 2, FALSE))) | P9: =IF('2.LUC'!$AZ11="",'2.LUC'!$AY11,'2.LUC'!$AZ11) | Q9: =IF(H9 = "Please select", 0, IF(H9= "Mangrove Forest", VLOOKUP(clim_moist, IPCC!$A$1502:$J$1511, 9, FALSE), VLOOKUP(H9, IPCC!$A$643:$C$677, 3, FALSE))) | R9: =IF('2.LUC'!$BC11="",'2.LUC'!$BB11,'2.LUC'!$BC11) | S9: =IF(H9= "Please select", 0, IF(H9="Mangrove Forest",VLOOKUP(clim_moist,IPCC!$A$1502:$J$1511,10,FALSE),SOCref)) | T9: =IF('2.LUC'!$BF11="",'2.LUC'!$BE11,'2.LUC'!$BF11)
A10: Tropical moist deciduous forest | B10: Subtropical dry forest | C10: Temperate continental forest | D10: Boreal tundra woodland | E10: Planted Tropical mountain systems | G10: 2 | H10: =B24 | I10: =IF(H10="Please select",0,IF(H10="Mangrove Forest",VLOOKUP(clim_moist,IPCC!$A$1502:$G$1510,2,FALSE),INDEX(IPCC!$B$590:$AK$606,MATCH(continent_selected,IPCC!$A$590:$A$606,0),MATCH(H10,IPCC!$B$590:$AK$590,0)))) | J10: =IF(H10="Please select",0,IF(H10="Mangrove Forest",$I10*0.451,$I10*0.47)) | K10: =IF('2.LUC'!$AT12="",'2.LUC'!$AS12,'2.LUC'!$AT12) | L10: =IF(H10 = "Please select",0, IF(H10="Mangrove Forest",VLOOKUP(clim_moist,IPCC!$A$1502:$G$1511,6,FALSE),IF(OR(I10<=125,I10<=75),INDEX(IPCC!$B$618:$AI$633,MATCH(continent_selected,IPCC!$A$618:$A$633,0),MATCH(H10,IPCC!$B$616:$AI$616,0)),(IF(OR(I10>125,I10>75),INDEX(IPCC!$AJ$616:$BS$633,MATCH(continent_selected,IPCC!$A$616:$A$633,0),MATCH(H10,IPCC!$AJ$616:$BS$616,0)),""))))*I10) | M10: =IF(H10="Please select",0,IF(H10="Mangrove Forest",L10*0.451,L10*0.47)) | N10: =IF('2.LUC'!AW12="",'2.LUC'!AV12,'2.LUC'!AW12) | O10: =IF(H10 = "Please select", 0, IF(H10 = "Mangrove Forest", VLOOKUP(clim_moist, IPCC!$A$1502:$J$1511, 8, FALSE),VLOOKUP(H10, IPCC!$A$643:$B$677, 2, FALSE))) | P10: =IF('2.LUC'!$AZ12="",'2.LUC'!$AY12,'2.LUC'!$AZ12) | Q10: =IF(H10 = "Please select", 0, IF(H10= "Mangrove Forest", VLOOKUP(clim_moist, IPCC!$A$1502:$J$1511, 9, FALSE), VLOOKUP(H10, IPCC!$A$643:$C$677, 3, FALSE))) | R10: =IF('2.LUC'!$BC12="",'2.LUC'!$BB12,'2.LUC'!$BC12) | S10: =IF(H10= "Please select", 0, IF(H10="Mangrove Forest",VLOOKUP(clim_moist,IPCC!$A$1502:$J$1511,10,FALSE),SOCref)) | T10: =IF('2.LUC'!$BF12="",'2.LUC'!$BE12,'2.LUC'!$BF12)
A11: Tropical dry forest | B11: Subtropical steppe | C11: Temperate mountain systems | D11: Boreal mountain systems | G11: 3 | H11: =B25 | I11: =IF(H11="Please select",0,IF(H11="Mangrove Forest",VLOOKUP(clim_moist,IPCC!$A$1502:$G$1510,2,FALSE),INDEX(IPCC!$B$590:$AK$606,MATCH(continent_selected,IPCC!$A$590:$A$606,0),MATCH(H11,IPCC!$B$590:$AK$590,0)))) | J11: =IF(H11="Please select",0,IF(H11="Mangrove Forest",$I11*0.451,$I11*0.47)) | K11: =IF('2.LUC'!$AT13="",'2.LUC'!$AS13,'2.LUC'!$AT13) | L11: =IF(H11 = "Please select",0, IF(H11="Mangrove Forest",VLOOKUP(clim_moist,IPCC!$A$1502:$G$1511,6,FALSE),IF(OR(I11<=125,I11<=75),INDEX(IPCC!$B$618:$AI$633,MATCH(continent_selected,IPCC!$A$618:$A$633,0),MATCH(H11,IPCC!$B$616:$AI$616,0)),(IF(OR(I11>125,I11>75),INDEX(IPCC!$AJ$616:$BS$633,MATCH(continent_selected,IPCC!$A$616:$A$633,0),MATCH(H11,IPCC!$AJ$616:$BS$616,0)),""))))*I11) | M11: =IF(H11="Please select",0,IF(H11="Mangrove Forest",L11*0.451,L11*0.47)) | N11: =IF('2.LUC'!AW13="",'2.LUC'!AV13,'2.LUC'!AW13) | O11: =IF(H11 = "Please select", 0, IF(H11 = "Mangrove Forest", VLOOKUP(clim_moist, IPCC!$A$1502:$J$1511, 8, FALSE),VLOOKUP(H11, IPCC!$A$643:$B$677, 2, FALSE))) | P11: =IF('2.LUC'!$AZ13="",'2.LUC'!$AY13,'2.LUC'!$AZ13) | Q11: =IF(H11 = "Please select", 0, IF(H11= "Mangrove Forest", VLOOKUP(clim_moist, IPCC!$A$1502:$J$1511, 9, FALSE), VLOOKUP(H11, IPCC!$A$643:$C$677, 3, FALSE))) | R11: =IF('2.LUC'!$BC13="",'2.LUC'!$BB13,'2.LUC'!$BC13) | S11: =IF(H11= "Please select", 0, IF(H11="Mangrove Forest",VLOOKUP(clim_moist,IPCC!$A$1502:$J$1511,10,FALSE),SOCref)) | T11: =IF('2.LUC'!$BF13="",'2.LUC'!$BE13,'2.LUC'!$BF13)
A12: Tropical shrubland | B12: Subtropical mountain systems | C12: Temperate desert | D12: Planted Boreal coniferous forest | G12: 4 | H12: =B26 | I12: =IF(H12="Please select",0,IF(H12="Mangrove Forest",VLOOKUP(clim_moist,IPCC!$A$1502:$G$1510,2,FALSE),INDEX(IPCC!$B$590:$AK$606,MATCH(continent_selected,IPCC!$A$590:$A$606,0),MATCH(H12,IPCC!$B$590:$AK$590,0)))) | J12: =IF(H12="Please select",0,IF(H12="Mangrove Forest",$I12*0.451,$I12*0.47)) | K12: =IF('2.LUC'!$AT14="",'2.LUC'!$AS14,'2.LUC'!$AT14) | L12: =IF(H12 = "Please select",0, IF(H12="Mangrove Forest",VLOOKUP(clim_moist,IPCC!$A$1502:$G$1511,6,FALSE),IF(OR(I12<=125,I12<=75),INDEX(IPCC!$B$618:$AI$633,MATCH(continent_selected,IPCC!$A$618:$A$633,0),MATCH(H12,IPCC!$B$616:$AI$616,0)),(IF(OR(I12>125,I12>75),INDEX(IPCC!$AJ$616:$BS$633,MATCH(continent_selected,IPCC!$A$616:$A$633,0),MATCH(H12,IPCC!$AJ$616:$BS$616,0)),""))))*I12) | M12: =IF(H12="Please select",0,IF(H12="Mangrove Forest",L12*0.451,L12*0.47)) | N12: =IF('2.LUC'!AW14="",'2.LUC'!AV14,'2.LUC'!AW14) | O12: =IF(H12 = "Please select", 0, IF(H12 = "Mangrove Forest", VLOOKUP(clim_moist, IPCC!$A$1502:$J$1511, 8, FALSE),VLOOKUP(H12, IPCC!$A$643:$B$677, 2, FALSE))) | P12: =IF('2.LUC'!$AZ14="",'2.LUC'!$AY14,'2.LUC'!$AZ14) | Q12: =IF(H12 = "Please select", 0, IF(H12= "Mangrove Forest", VLOOKUP(clim_moist, IPCC!$A$1502:$J$1511, 9, FALSE), VLOOKUP(H12, IPCC!$A$643:$C$677, 3, FALSE))) | R12: =IF('2.LUC'!$BC14="",'2.LUC'!$BB14,'2.LUC'!$BC14) | S12: =IF(H12= "Please select", 0, IF(H12="Mangrove Forest",VLOOKUP(clim_moist,IPCC!$A$1502:$J$1511,10,FALSE),SOCref)) | T12: =IF('2.LUC'!$BF14="",'2.LUC'!$BE14,'2.LUC'!$BF14)
A13: Mangrove Forest | B13: Planted Subtropical humid forest | C13: Temperate steppe | D13: Planted Boreal tundra woodland | G13: 5 | H13: =B27 | I13: =IF(H13="Please select",0,IF(H13="Mangrove Forest",VLOOKUP(clim_moist,IPCC!$A$1502:$G$1510,2,FALSE),INDEX(IPCC!$B$590:$AK$606,MATCH(continent_selected,IPCC!$A$590:$A$606,0),MATCH(H13,IPCC!$B$590:$AK$590,0)))) | J13: =IF(H13="Please select",0,IF(H13="Mangrove Forest",$I13*0.451,$I13*0.47)) | K13: =IF('2.LUC'!$AT15="",'2.LUC'!$AS15,'2.LUC'!$AT15) | L13: =IF(H13 = "Please select",0, IF(H13="Mangrove Forest",VLOOKUP(clim_moist,IPCC!$A$1502:$G$1511,6,FALSE),IF(OR(I13<=125,I13<=75),INDEX(IPCC!$B$618:$AI$633,MATCH(continent_selected,IPCC!$A$618:$A$633,0),MATCH(H13,IPCC!$B$616:$AI$616,0)),(IF(OR(I13>125,I13>75),INDEX(IPCC!$AJ$616:$BS$633,MATCH(continent_selected,IPCC!$A$616:$A$633,0),MATCH(H13,IPCC!$AJ$616:$BS$616,0)),""))))*I13) | M13: =IF(H13="Please select",0,IF(H13="Mangrove Forest",L13*0.451,L13*0.47)) | N13: =IF('2.LUC'!AW15="",'2.LUC'!AV15,'2.LUC'!AW15) | O13: =IF(H13 = "Please select", 0, IF(H13 = "Mangrove Forest", VLOOKUP(clim_moist, IPCC!$A$1502:$J$1511, 8, FALSE),VLOOKUP(H13, IPCC!$A$643:$B$677, 2, FALSE))) | P13: =IF('2.LUC'!$AZ15="",'2.LUC'!$AY15,'2.LUC'!$AZ15) | Q13: =IF(H13 = "Please select", 0, IF(H13= "Mangrove Forest", VLOOKUP(clim_moist, IPCC!$A$1502:$J$1511, 9, FALSE), VLOOKUP(H13, IPCC!$A$643:$C$677, 3, FALSE))) | R13: =IF('2.LUC'!$BC15="",'2.LUC'!$BB15,'2.LUC'!$BC15) | S13: =IF(H13= "Please select", 0, IF(H13="Mangrove Forest",VLOOKUP(clim_moist,IPCC!$A$1502:$J$1511,10,FALSE),SOCref)) | T13: =IF('2.LUC'!$BF15="",'2.LUC'!$BE15,'2.LUC'!$BF15)
A14: Planted Tropical rainforest | B14: Planted Subtropical dry forest | C14: Planted Temperate oceanic forest | D14: Planted Boreal mountain systems | G14: 6 | H14: =B28 | I14: =IF(H14="Please select",0,IF(H14="Mangrove Forest",VLOOKUP(clim_moist,IPCC!$A$1502:$G$1510,2,FALSE),INDEX(IPCC!$B$590:$AK$606,MATCH(continent_selected,IPCC!$A$590:$A$606,0),MATCH(H14,IPCC!$B$590:$AK$590,0)))) | J14: =IF(H14="Please select",0,IF(H14="Mangrove Forest",$I14*0.451,$I14*0.47)) | K14: =IF('2.LUC'!$AT16="",'2.LUC'!$AS16,'2.LUC'!$AT16) | L14: =IF(H14 = "Please select",0, IF(H14="Mangrove Forest",VLOOKUP(clim_moist,IPCC!$A$1502:$G$1511,6,FALSE),IF(OR(I14<=125,I14<=75),INDEX(IPCC!$B$618:$AI$633,MATCH(continent_selected,IPCC!$A$618:$A$633,0),MATCH(H14,IPCC!$B$616:$AI$616,0)),(IF(OR(I14>125,I14>75),INDEX(IPCC!$AJ$616:$BS$633,MATCH(continent_selected,IPCC!$A$616:$A$633,0),MATCH(H14,IPCC!$AJ$616:$BS$616,0)),""))))*I14) | M14: =IF(H14="Please select",0,IF(H14="Mangrove Forest",L14*0.451,L14*0.47)) | N14: =IF('2.LUC'!AW16="",'2.LUC'!AV16,'2.LUC'!AW16) | O14: =IF(H14 = "Please select", 0, IF(H14 = "Mangrove Forest", VLOOKUP(clim_moist, IPCC!$A$1502:$J$1511, 8, FALSE),VLOOKUP(H14, IPCC!$A$643:$B$677, 2, FALSE))) | P14: =IF('2.LUC'!$AZ16="",'2.LUC'!$AY16,'2.LUC'!$AZ16) | Q14: =IF(H14 = "Please select", 0, IF(H14= "Mangrove Forest", VLOOKUP(clim_moist, IPCC!$A$1502:$J$1511, 9, FALSE), VLOOKUP(H14, IPCC!$A$643:$C$677, 3, FALSE))) | R14: =IF('2.LUC'!$BC16="",'2.LUC'!$BB16,'2.LUC'!$BC16) | S14: =IF(H14= "Please select", 0, IF(H14="Mangrove Forest",VLOOKUP(clim_moist,IPCC!$A$1502:$J$1511,10,FALSE),SOCref)) | T14: =IF('2.LUC'!$BF16="",'2.LUC'!$BE16,'2.LUC'!$BF16)
A15: Planted Tropical moist deciduous forest | B15: Planted Subtropical steppe | C15: Planted Temperate continental forest | G15: 7 | H15: =B29 | I15: =IF(H15="Please select",0,IF(H15="Mangrove Forest",VLOOKUP(clim_moist,IPCC!$A$1502:$G$1510,2,FALSE),INDEX(IPCC!$B$590:$AK$606,MATCH(continent_selected,IPCC!$A$590:$A$606,0),MATCH(H15,IPCC!$B$590:$AK$590,0)))) | J15: =IF(H15="Please select",0,IF(H15="Mangrove Forest",$I15*0.451,$I15*0.47)) | K15: =IF('2.LUC'!$AT17="",'2.LUC'!$AS17,'2.LUC'!$AT17) | L15: =IF(H15 = "Please select",0, IF(H15="Mangrove Forest",VLOOKUP(clim_moist,IPCC!$A$1502:$G$1511,6,FALSE),IF(OR(I15<=125,I15<=75),INDEX(IPCC!$B$618:$AI$633,MATCH(continent_selected,IPCC!$A$618:$A$633,0),MATCH(H15,IPCC!$B$616:$AI$616,0)),(IF(OR(I15>125,I15>75),INDEX(IPCC!$AJ$616:$BS$633,MATCH(continent_selected,IPCC!$A$616:$A$633,0),MATCH(H15,IPCC!$AJ$616:$BS$616,0)),""))))*I15) | M15: =IF(H15="Please select",0,IF(H15="Mangrove Forest",L15*0.451,L15*0.47)) | N15: =IF('2.LUC'!AW17="",'2.LUC'!AV17,'2.LUC'!AW17) | O15: =IF(H15 = "Please select", 0, IF(H15 = "Mangrove Forest", VLOOKUP(clim_moist, IPCC!$A$1502:$J$1511, 8, FALSE),VLOOKUP(H15, IPCC!$A$643:$B$677, 2, FALSE))) | P15: =IF('2.LUC'!$AZ17="",'2.LUC'!$AY17,'2.LUC'!$AZ17) | Q15: =IF(H15 = "Please select", 0, IF(H15= "Mangrove Forest", VLOOKUP(clim_moist, IPCC!$A$1502:$J$1511, 9, FALSE), VLOOKUP(H15, IPCC!$A$643:$C$677, 3, FALSE))) | R15: =IF('2.LUC'!$BC17="",'2.LUC'!$BB17,'2.LUC'!$BC17) | S15: =IF(H15= "Please select", 0, IF(H15="Mangrove Forest",VLOOKUP(clim_moist,IPCC!$A$1502:$J$1511,10,FALSE),SOCref)) | T15: =IF('2.LUC'!$BF17="",'2.LUC'!$BE17,'2.LUC'!$BF17)
A16: Planted Tropical dry forest | B16: Planted Subtropical mountain systems | C16: Planted Temperate mountain systems | G16: 8 | H16: =B30 | I16: =IF(H16="Please select",0,IF(H16="Mangrove Forest",VLOOKUP(clim_moist,IPCC!$A$1502:$G$1510,2,FALSE),INDEX(IPCC!$B$590:$AK$606,MATCH(continent_selected,IPCC!$A$590:$A$606,0),MATCH(H16,IPCC!$B$590:$AK$590,0)))) | J16: =IF(H16="Please select",0,IF(H16="Mangrove Forest",$I16*0.451,$I16*0.47)) | K16: =IF('2.LUC'!$AT18="",'2.LUC'!$AS18,'2.LUC'!$AT18) | L16: =IF(H16 = "Please select",0, IF(H16="Mangrove Forest",VLOOKUP(clim_moist,IPCC!$A$1502:$G$1511,6,FALSE),IF(OR(I16<=125,I16<=75),INDEX(IPCC!$B$618:$AI$633,MATCH(continent_selected,IPCC!$A$618:$A$633,0),MATCH(H16,IPCC!$B$616:$AI$616,0)),(IF(OR(I16>125,I16>75),INDEX(IPCC!$AJ$616:$BS$633,MATCH(continent_selected,IPCC!$A$616:$A$633,0),MATCH(H16,IPCC!$AJ$616:$BS$616,0)),""))))*I16) | M16: =IF(H16="Please select",0,IF(H16="Mangrove Forest",L16*0.451,L16*0.47)) | N16: =IF('2.LUC'!AW18="",'2.LUC'!AV18,'2.LUC'!AW18) | O16: =IF(H16 = "Please select", 0, IF(H16 = "Mangrove Forest", VLOOKUP(clim_moist, IPCC!$A$1502:$J$1511, 8, FALSE),VLOOKUP(H16, IPCC!$A$643:$B$677, 2, FALSE))) | P16: =IF('2.LUC'!$AZ18="",'2.LUC'!$AY18,'2.LUC'!$AZ18) | Q16: =IF(H16 = "Please select", 0, IF(H16= "Mangrove Forest", VLOOKUP(clim_moist, IPCC!$A$1502:$J$1511, 9, FALSE), VLOOKUP(H16, IPCC!$A$643:$C$677, 3, FALSE))) | R16: =IF('2.LUC'!$BC18="",'2.LUC'!$BB18,'2.LUC'!$BC18) | S16: =IF(H16= "Please select", 0, IF(H16="Mangrove Forest",VLOOKUP(clim_moist,IPCC!$A$1502:$J$1511,10,FALSE),SOCref)) | T16: =IF('2.LUC'!$BF18="",'2.LUC'!$BE18,'2.LUC'!$BF18)
A17: Planted Tropical shrubland | B17: Mangrove Forest | C17: Planted Temperate desert
C18: Planted Temperate steppe
F20: Combustion factor (Cf) | G20: FINAL LAND USE | J20: BIOMASS FINAL | K20: BIOMASS FOREST | O20: Soil | R20: Fire | S20: Fire | T20: Fire | U20: SOM mineralization due to LUC | V20: soil N2O | W20: Total CH4 & N2O | Z20: CH4 fire | AB20: N2O fire | AD20: N2O SOM
A21: Name | B21: Vegetation Type | C21: HWP before | E21: Fire use | F21: the fraction (%) | G21: Final land use | H21: Final agroforestry | I21: incl. agroforestry systems | J21: After 1 yr of growth of Final LU | K21: AGB+BGB | M21: DOM (DW + litter) | O21: FLU | P21: ΔC Mineral | Q21: ΔC Mineral | R21: MB = AGB - HWP | S21: CH4 | T21: N2O | U21: FSOM - kg N mineralized | Z21: Without | AA21: With | AB21: Without | AC21: With | AD21: Without | AE21: With | AG21: Fire occurrence
B22: deforested | C22: t DM/ha | D22: t C exported/ha | E22: yes/no | F22: combusted | G22: after deforestation | H22: After deforestation | J22: tC/ha | K22: t C/ha | L22: t CO2/ha | M22: t C/ha | N22: t CO2/ha | O22: ( - ) | P22: tC/ha | Q22: tCO2/ha/yr | R22: t dm/ha | S22: kgCH4 | T22: kgN2O | U22: kg N /year | V22: kg | W22: tCO2 eq | Z22: tCO2 | AA22: tCO2 | AB22: tCO2 | AC22: tCO2 | AD22: tCO2 | AE22: tCO2 | AG22: START | AH22: WITHOUT | AI22: WITH
A23: Deforestation 1 | B23: ='2.LUC'!$C11 | C23: ='2.LUC'!$E11 | D23: =IF('2.LUC'!$C11="Please select",0,IF(C23>VLOOKUP($B23,defo!$H$9:$K$16,2,FALSE),VLOOKUP($B23,defo!$H$9:$K$16,2,FALSE),'2.LUC'!$E11))*IF(B23="Mangrove Forest",0.451, 0.47) | E23: ='2.LUC'!$G11 | F23: =IF($B23<> "Please select", IF($E23="YES", VLOOKUP($B23, IPCC!$A$871:$B$906, 2, FALSE),0), 0) | G23: ='2.LUC'!$I11 | H23: ='2.LUC'!$K11 | I23: =IF('2.LUC'!$K11 <> "Please select", '2.LUC'!$K11, IF('2.LUC'!$I11<>"Agroforestry", '2.LUC'!$I11, "Agroforestry - default")) | J23: =IF('2.LUC'!$I11 <> "Please select", IF('2.LUC'!BM11=0, INDEX(IPCC!$D$686:$Y$845,MATCH(clim_moist_cont,IPCC!$C$686:$C$845,0),MATCH($I23,IPCC!$D$682:$Y$682,0)), '2.LUC'!BM11), 0) | K23: =IF('2.LUC'!$C11<>"Please select",$K9-$D23+$N9,0) | L23: =K23*44/12 | M23: =IF('2.LUC'!$C11<>"Please select",P9+R9,0) | N23: =M23*44/12 | O23: =IF($I23<> "Please select", INDEX(IPCC!$B$852:$W$863,MATCH(clim_moist,IPCC!$A$852:$A$863,0),MATCH($I23,IPCC!$B$852:$W$852,0)),0) | P23: =IF($I23<>"Please select",IF('2.LUC'!BP11=0, $T9*$O23-$T9, '2.LUC'!BP11-$T9),0) | Q23: =P23*(-44/12)/20 | R23: =IF($E23="NO",0,(VLOOKUP($B23,$H$9:$I$16,2,FALSE)-$C23)) | S23: =IF($E23="YES", ($R23*VLOOKUP($B23, IPCC!$A$871:$E$906,2, FALSE)*VLOOKUP($B23, IPCC!$A$871:$E$906, 4, FALSE)), 0) | T23: =IF($E23="YES", ($R23*VLOOKUP($B23, IPCC!$A$871:$E$906,2, FALSE)*VLOOKUP($B23, IPCC!$A$871:$E$906, 5, FALSE)), 0) | U23: =IF($P23>=0, 0, ((-1)*(($P23/20*1/IPCC!$B$913)*1000))) | V23: =IF(country_selected="Please select",0,U23*VLOOKUP(moist_type, IPCC!$B$99:$C$101, 2, FALSE)*N2O_N_conversion) | W23: =($S23*methane+($T23+$V23)*Nitrous)/1000 | Z23: =IF($E23= "YES", $G35*$S23*methane/1000,0) | AA23: =IF($E23= "YES", $H35*$S23*methane/1000,0) | AB23: =$G35*$T23*Nitrous/1000 | AC23: =$H35*$T23*Nitrous/1000 | AD23: =$G35*$V23*Nitrous/1000 | AE23: =$H35*$V23*Nitrous/1000 | AG23: 0 | AH23: =IF($F23>0, $G35, 0) | AI23: =IF($F23>0, $H35, 0)
A24: Deforestation 2 | B24: ='2.LUC'!$C12 | C24: ='2.LUC'!$E12 | D24: =IF('2.LUC'!$C12="Please select",0,IF(C24>VLOOKUP($B24,defo!$H$9:$K$16,2,FALSE),VLOOKUP($B24,defo!$H$9:$K$16,2,FALSE),'2.LUC'!$E12))*IF(B24="Mangrove Forest",0.451, 0.47) | E24: ='2.LUC'!$G12 | F24: =IF($B24<> "Please select", IF($E24="YES", VLOOKUP($B24, IPCC!$A$871:$B$906, 2, FALSE),0), 0) | G24: ='2.LUC'!$I12 | H24: ='2.LUC'!$K12 | I24: =IF('2.LUC'!$K12 <> "Please select", '2.LUC'!$K12, IF('2.LUC'!$I12<>"Agroforestry", '2.LUC'!$I12, "Agroforestry - default")) | J24: =IF('2.LUC'!$I12 <> "Please select", IF('2.LUC'!BM12=0, INDEX(IPCC!$D$686:$Y$845,MATCH(clim_moist_cont,IPCC!$C$686:$C$845,0),MATCH($I24,IPCC!$D$682:$Y$682,0)), '2.LUC'!BM12), 0) | K24: =IF('2.LUC'!$C12<>"Please select",$K10-$D24+$N10,0) | L24: =K24*44/12 | M24: =IF('2.LUC'!$C12<>"Please select",P10+R10,0) | N24: =M24*44/12 | O24: =IF($I24<> "Please select", INDEX(IPCC!$B$852:$W$863,MATCH(clim_moist,IPCC!$A$852:$A$863,0),MATCH($I24,IPCC!$B$852:$W$852,0)),0) | P24: =IF($I24<>"Please select",IF('2.LUC'!BP12=0, $T10*$O24-$T10, '2.LUC'!BP12-$T10),0) | Q24: =P24*(-44/12)/20 | R24: =IF($E24="NO",0,(VLOOKUP($B24,$H$9:$I$16,2,FALSE)-$C24)) | S24: =IF($E24="YES", ($R24*VLOOKUP($B24, IPCC!$A$871:$E$906,2, FALSE)*VLOOKUP($B24, IPCC!$A$871:$E$906, 4, FALSE)), 0) | T24: =IF($E24="YES", ($R24*VLOOKUP($B24, IPCC!$A$871:$E$906,2, FALSE)*VLOOKUP($B24, IPCC!$A$871:$E$906, 5, FALSE)), 0) | U24: =IF($P24>=0, 0, ((-1)*(($P24/20*1/IPCC!$B$913)*1000))) | V24: =IF(country_selected="Please select",0,U24*VLOOKUP(moist_type, IPCC!$B$99:$C$101, 2, FALSE)*N2O_N_conversion) | W24: =($S24*methane+($T24+$V24)*Nitrous)/1000 | Z24: =IF($E24= "YES", $G36*$S24*methane/1000,0) | AA24: =IF($E24= "YES", $H36*$S24*methane/1000,0) | AB24: =$G36*$T24*Nitrous/1000 | AC24: =$H36*$T24*Nitrous/1000 | AD24: =$G36*$V24*Nitrous/1000 | AE24: =$H36*$V24*Nitrous/1000 | AG24: 0 | AH24: =IF($F24>0, $G36, 0) | AI24: =IF($F24>0, $H36, 0)
A25: Deforestation 3 | B25: ='2.LUC'!$C13 | C25: ='2.LUC'!$E13 | D25: =IF('2.LUC'!$C13="Please select",0,IF(C25>VLOOKUP($B25,defo!$H$9:$K$16,2,FALSE),VLOOKUP($B25,defo!$H$9:$K$16,2,FALSE),'2.LUC'!$E13))*IF(B25="Mangrove Forest",0.451, 0.47) | E25: ='2.LUC'!$G13 | F25: =IF($B25<> "Please select", IF($E25="YES", VLOOKUP($B25, IPCC!$A$871:$B$906, 2, FALSE),0), 0) | G25: ='2.LUC'!$I13 | H25: ='2.LUC'!$K13 | I25: =IF('2.LUC'!$K13 <> "Please select", '2.LUC'!$K13, IF('2.LUC'!$I13<>"Agroforestry", '2.LUC'!$I13, "Agroforestry - default")) | J25: =IF('2.LUC'!$I13 <> "Please select", IF('2.LUC'!BM13=0, INDEX(IPCC!$D$686:$Y$845,MATCH(clim_moist_cont,IPCC!$C$686:$C$845,0),MATCH($I25,IPCC!$D$682:$Y$682,0)), '2.LUC'!BM13), 0) | K25: =IF('2.LUC'!$C13<>"Please select",$K11-$D25+$N11,0) | L25: =K25*44/12 | M25: =IF('2.LUC'!$C13<>"Please select",P11+R11,0) | N25: =M25*44/12 | O25: =IF($I25<> "Please select", INDEX(IPCC!$B$852:$W$863,MATCH(clim_moist,IPCC!$A$852:$A$863,0),MATCH($I25,IPCC!$B$852:$W$852,0)),0) | P25: =IF($I25<>"Please select",IF('2.LUC'!BP13=0, $T11*$O25-$T11, '2.LUC'!BP13-$T11),0) | Q25: =P25*(-44/12)/20 | R25: =IF($E25="NO",0,(VLOOKUP($B25,$H$9:$I$16,2,FALSE)-$C25)) | S25: =IF($E25="YES", ($R25*VLOOKUP($B25, IPCC!$A$871:$E$906,2, FALSE)*VLOOKUP($B25, IPCC!$A$871:$E$906, 4, FALSE)), 0) | T25: =IF($E25="YES", ($R25*VLOOKUP($B25, IPCC!$A$871:$E$906,2, FALSE)*VLOOKUP($B25, IPCC!$A$871:$E$906, 5, FALSE)), 0) | U25: =IF($P25>=0, 0, ((-1)*(($P25/20*1/IPCC!$B$913)*1000))) | V25: =IF(country_selected="Please select",0,U25*VLOOKUP(moist_type, IPCC!$B$99:$C$101, 2, FALSE)*N2O_N_conversion) | W25: =($S25*methane+($T25+$V25)*Nitrous)/1000 | Z25: =IF($E25= "YES", $G37*$S25*methane/1000,0) | AA25: =IF($E25= "YES", $H37*$S25*methane/1000,0) | AB25: =$G37*$T25*Nitrous/1000 | AC25: =$H37*$T25*Nitrous/1000 | AD25: =$G37*$V25*Nitrous/1000 | AE25: =$H37*$V25*Nitrous/1000 | AG25: 0 | AH25: =IF($F25>0, $G37, 0) | AI25: =IF($F25>0, $H37, 0)
A26: Deforestation 4 | B26: ='2.LUC'!$C14 | C26: ='2.LUC'!$E14 | D26: =IF('2.LUC'!$C14="Please select",0,IF(C26>VLOOKUP($B26,defo!$H$9:$K$16,2,FALSE),VLOOKUP($B26,defo!$H$9:$K$16,2,FALSE),'2.LUC'!$E14))*IF(B26="Mangrove Forest",0.451, 0.47) | E26: ='2.LUC'!$G14 | F26: =IF($B26<> "Please select", IF($E26="YES", VLOOKUP($B26, IPCC!$A$871:$B$906, 2, FALSE),0), 0) | G26: ='2.LUC'!$I14 | H26: ='2.LUC'!$K14 | I26: =IF('2.LUC'!$K14 <> "Please select", '2.LUC'!$K14, IF('2.LUC'!$I14<>"Agroforestry", '2.LUC'!$I14, "Agroforestry - default")) | J26: =IF('2.LUC'!$I14 <> "Please select", IF('2.LUC'!BM14=0, INDEX(IPCC!$D$686:$Y$845,MATCH(clim_moist_cont,IPCC!$C$686:$C$845,0),MATCH($I26,IPCC!$D$682:$Y$682,0)), '2.LUC'!BM14), 0) | K26: =IF('2.LUC'!$C14<>"Please select",$K12-$D26+$N12,0) | L26: =K26*44/12 | M26: =IF('2.LUC'!$C14<>"Please select",P12+R12,0) | N26: =M26*44/12 | O26: =IF($I26<> "Please select", INDEX(IPCC!$B$852:$W$863,MATCH(clim_moist,IPCC!$A$852:$A$863,0),MATCH($I26,IPCC!$B$852:$W$852,0)),0) | P26: =IF($I26<>"Please select",IF('2.LUC'!BP14=0, $T12*$O26-$T12, '2.LUC'!BP14-$T12),0) | Q26: =P26*(-44/12)/20 | R26: =IF($E26="NO",0,(VLOOKUP($B26,$H$9:$I$16,2,FALSE)-$C26)) | S26: =IF($E26="YES", ($R26*VLOOKUP($B26, IPCC!$A$871:$E$906,2, FALSE)*VLOOKUP($B26, IPCC!$A$871:$E$906, 4, FALSE)), 0) | T26: =IF($E26="YES", ($R26*VLOOKUP($B26, IPCC!$A$871:$E$906,2, FALSE)*VLOOKUP($B26, IPCC!$A$871:$E$906, 5, FALSE)), 0) | U26: =IF($P26>=0, 0, ((-1)*(($P26/20*1/IPCC!$B$913)*1000))) | V26: =IF(country_selected="Please select",0,U26*VLOOKUP(moist_type, IPCC!$B$99:$C$101, 2, FALSE)*N2O_N_conversion) | W26: =($S26*methane+($T26+$V26)*Nitrous)/1000 | Z26: =IF($E26= "YES", $G38*$S26*methane/1000,0) | AA26: =IF($E26= "YES", $H38*$S26*methane/1000,0) | AB26: =$G38*$T26*Nitrous/1000 | AC26: =$H38*$T26*Nitrous/1000 | AD26: =$G38*$V26*Nitrous/1000 | AE26: =$H38*$V26*Nitrous/1000 | AG26: 0 | AH26: =IF($F26>0, $G38, 0) | AI26: =IF($F26>0, $H38, 0)
A27: Deforestation 5 | B27: ='2.LUC'!$C15 | C27: ='2.LUC'!$E15 | D27: =IF('2.LUC'!$C15="Please select",0,IF(C27>VLOOKUP($B27,defo!$H$9:$K$16,2,FALSE),VLOOKUP($B27,defo!$H$9:$K$16,2,FALSE),'2.LUC'!$E15))*IF(B27="Mangrove Forest",0.451, 0.47) | E27: ='2.LUC'!$G15 | F27: =IF($B27<> "Please select", IF($E27="YES", VLOOKUP($B27, IPCC!$A$871:$B$906, 2, FALSE),0), 0) | G27: ='2.LUC'!$I15 | H27: ='2.LUC'!$K15 | I27: =IF('2.LUC'!$K15 <> "Please select", '2.LUC'!$K15, IF('2.LUC'!$I15<>"Agroforestry", '2.LUC'!$I15, "Agroforestry - default")) | J27: =IF('2.LUC'!$I15 <> "Please select", IF('2.LUC'!BM15=0, INDEX(IPCC!$D$686:$Y$845,MATCH(clim_moist_cont,IPCC!$C$686:$C$845,0),MATCH($I27,IPCC!$D$682:$Y$682,0)), '2.LUC'!BM15), 0) | K27: =IF('2.LUC'!$C15<>"Please select",$K13-$D27+$N13,0) | L27: =K27*44/12 | M27: =IF('2.LUC'!$C15<>"Please select",P13+R13,0) | N27: =M27*44/12 | O27: =IF($I27<> "Please select", INDEX(IPCC!$B$852:$W$863,MATCH(clim_moist,IPCC!$A$852:$A$863,0),MATCH($I27,IPCC!$B$852:$W$852,0)),0) | P27: =IF($I27<>"Please select",IF('2.LUC'!BP15=0, $T13*$O27-$T13, '2.LUC'!BP15-$T13),0) | Q27: =P27*(-44/12)/20 | R27: =IF($E27="NO",0,(VLOOKUP($B27,$H$9:$I$16,2,FALSE)-$C27)) | S27: =IF($E27="YES", ($R27*VLOOKUP($B27, IPCC!$A$871:$E$906,2, FALSE)*VLOOKUP($B27, IPCC!$A$871:$E$906, 4, FALSE)), 0) | T27: =IF($E27="YES", ($R27*VLOOKUP($B27, IPCC!$A$871:$E$906,2, FALSE)*VLOOKUP($B27, IPCC!$A$871:$E$906, 5, FALSE)), 0) | U27: =IF($P27>=0, 0, ((-1)*(($P27/20*1/IPCC!$B$913)*1000))) | V27: =IF(country_selected="Please select",0,U27*VLOOKUP(moist_type, IPCC!$B$99:$C$101, 2, FALSE)*N2O_N_conversion) | W27: =($S27*methane+($T27+$V27)*Nitrous)/1000 | Z27: =IF($E27= "YES", $G39*$S27*methane/1000,0) | AA27: =IF($E27= "YES", $H39*$S27*methane/1000,0) | AB27: =$G39*$T27*Nitrous/1000 | AC27: =$H39*$T27*Nitrous/1000 | AD27: =$G39*$V27*Nitrous/1000 | AE27: =$H39*$V27*Nitrous/1000 | AG27: 0 | AH27: =IF($F27>0, $G39, 0) | AI27: =IF($F27>0, $H39, 0)
A28: Deforestation 6 | B28: ='2.LUC'!$C16 | C28: ='2.LUC'!$E16 | D28: =IF('2.LUC'!$C16="Please select",0,IF(C28>VLOOKUP($B28,defo!$H$9:$K$16,2,FALSE),VLOOKUP($B28,defo!$H$9:$K$16,2,FALSE),'2.LUC'!$E16))*IF(B28="Mangrove Forest",0.451, 0.47) | E28: ='2.LUC'!$G16 | F28: =IF($B28<> "Please select", IF($E28="YES", VLOOKUP($B28, IPCC!$A$871:$B$906, 2, FALSE),0), 0) | G28: ='2.LUC'!$I16 | H28: ='2.LUC'!$K16 | I28: =IF('2.LUC'!$K16 <> "Please select", '2.LUC'!$K16, IF('2.LUC'!$I16<>"Agroforestry", '2.LUC'!$I16, "Agroforestry - default")) | J28: =IF('2.LUC'!$I16 <> "Please select", IF('2.LUC'!BM16=0, INDEX(IPCC!$D$686:$Y$845,MATCH(clim_moist_cont,IPCC!$C$686:$C$845,0),MATCH($I28,IPCC!$D$682:$Y$682,0)), '2.LUC'!BM16), 0) | K28: =IF('2.LUC'!$C16<>"Please select",$K14-$D28+$N14,0) | L28: =K28*44/12 | M28: =IF('2.LUC'!$C16<>"Please select",P14+R14,0) | N28: =M28*44/12 | O28: =IF($I28<> "Please select", INDEX(IPCC!$B$852:$W$863,MATCH(clim_moist,IPCC!$A$852:$A$863,0),MATCH($I28,IPCC!$B$852:$W$852,0)),0) | P28: =IF($I28<>"Please select",IF('2.LUC'!BP16=0, $T14*$O28-$T14, '2.LUC'!BP16-$T14),0) | Q28: =P28*(-44/12)/20 | R28: =IF($E28="NO",0,(VLOOKUP($B28,$H$9:$I$16,2,FALSE)-$C28)) | S28: =IF($E28="YES", ($R28*VLOOKUP($B28, IPCC!$A$871:$E$906,2, FALSE)*VLOOKUP($B28, IPCC!$A$871:$E$906, 4, FALSE)), 0) | T28: =IF($E28="YES", ($R28*VLOOKUP($B28, IPCC!$A$871:$E$906,2, FALSE)*VLOOKUP($B28, IPCC!$A$871:$E$906, 5, FALSE)), 0) | U28: =IF($P28>=0, 0, ((-1)*(($P28/20*1/IPCC!$B$913)*1000))) | V28: =IF(country_selected="Please select",0,U28*VLOOKUP(moist_type, IPCC!$B$99:$C$101, 2, FALSE)*N2O_N_conversion) | W28: =($S28*methane+($T28+$V28)*Nitrous)/1000 | Z28: =IF($E28= "YES", $G40*$S28*methane/1000,0) | AA28: =IF($E28= "YES", $H40*$S28*methane/1000,0) | AB28: =$G40*$T28*Nitrous/1000 | AC28: =$H40*$T28*Nitrous/1000 | AD28: =$G40*$V28*Nitrous/1000 | AE28: =$H40*$V28*Nitrous/1000 | AG28: 0 | AH28: =IF($F28>0, $G40, 0) | AI28: =IF($F28>0, $H40, 0)
A29: Deforestation 7 | B29: ='2.LUC'!$C17 | C29: ='2.LUC'!$E17 | D29: =IF('2.LUC'!$C17="Please select",0,IF(C29>VLOOKUP($B29,defo!$H$9:$K$16,2,FALSE),VLOOKUP($B29,defo!$H$9:$K$16,2,FALSE),'2.LUC'!$E17))*IF(B29="Mangrove Forest",0.451, 0.47) | E29: ='2.LUC'!$G17 | F29: =IF($B29<> "Please select", IF($E29="YES", VLOOKUP($B29, IPCC!$A$871:$B$906, 2, FALSE),0), 0) | G29: ='2.LUC'!$I17 | H29: ='2.LUC'!$K17 | I29: =IF('2.LUC'!$K17 <> "Please select", '2.LUC'!$K17, IF('2.LUC'!$I17<>"Agroforestry", '2.LUC'!$I17, "Agroforestry - default")) | J29: =IF('2.LUC'!$I17 <> "Please select", IF('2.LUC'!BM17=0, INDEX(IPCC!$D$686:$Y$845,MATCH(clim_moist_cont,IPCC!$C$686:$C$845,0),MATCH($I29,IPCC!$D$682:$Y$682,0)), '2.LUC'!BM17), 0) | K29: =IF('2.LUC'!$C17<>"Please select",$K15-$D29+$N15,0) | L29: =K29*44/12 | M29: =IF('2.LUC'!$C17<>"Please select",P15+R15,0) | N29: =M29*44/12 | O29: =IF($I29<> "Please select", INDEX(IPCC!$B$852:$W$863,MATCH(clim_moist,IPCC!$A$852:$A$863,0),MATCH($I29,IPCC!$B$852:$W$852,0)),0) | P29: =IF($I29<>"Please select",IF('2.LUC'!BP17=0, $T15*$O29-$T15, '2.LUC'!BP17-$T15),0) | Q29: =P29*(-44/12)/20 | R29: =IF($E29="NO",0,(VLOOKUP($B29,$H$9:$I$16,2,FALSE)-$C29)) | S29: =IF($E29="YES", ($R29*VLOOKUP($B29, IPCC!$A$871:$E$906,2, FALSE)*VLOOKUP($B29, IPCC!$A$871:$E$906, 4, FALSE)), 0) | T29: =IF($E29="YES", ($R29*VLOOKUP($B29, IPCC!$A$871:$E$906,2, FALSE)*VLOOKUP($B29, IPCC!$A$871:$E$906, 5, FALSE)), 0) | U29: =IF($P29>=0, 0, ((-1)*(($P29/20*1/IPCC!$B$913)*1000))) | V29: =IF(country_selected="Please select",0,U29*VLOOKUP(moist_type, IPCC!$B$99:$C$101, 2, FALSE)*N2O_N_conversion) | W29: =($S29*methane+($T29+$V29)*Nitrous)/1000 | Z29: =IF($E29= "YES", $G41*$S29*methane/1000,0) | AA29: =IF($E29= "YES", $H41*$S29*methane/1000,0) | AB29: =$G41*$T29*Nitrous/1000 | AC29: =$H41*$T29*Nitrous/1000 | AD29: =$G41*$V29*Nitrous/1000 | AE29: =$H41*$V29*Nitrous/1000 | AG29: 0 | AH29: =IF($F29>0, $G41, 0) | AI29: =IF($F29>0, $H41, 0)
A30: Deforestation 8 | B30: ='2.LUC'!$C18 | C30: ='2.LUC'!$E18 | D30: =IF('2.LUC'!$C18="Please select",0,IF(C30>VLOOKUP($B30,defo!$H$9:$K$16,2,FALSE),VLOOKUP($B30,defo!$H$9:$K$16,2,FALSE),'2.LUC'!$E18))*IF(B30="Mangrove Forest",0.451, 0.47) | E30: ='2.LUC'!$G18 | F30: =IF($B30<> "Please select", IF($E30="YES", VLOOKUP($B30, IPCC!$A$871:$B$906, 2, FALSE),0), 0) | G30: ='2.LUC'!$I18 | H30: ='2.LUC'!$K18 | I30: =IF('2.LUC'!$K18 <> "Please select", '2.LUC'!$K18, IF('2.LUC'!$I18<>"Agroforestry", '2.LUC'!$I18, "Agroforestry - default")) | J30: =IF('2.LUC'!$I18 <> "Please select", IF('2.LUC'!BM18=0, INDEX(IPCC!$D$686:$Y$845,MATCH(clim_moist_cont,IPCC!$C$686:$C$845,0),MATCH($I30,IPCC!$D$682:$Y$682,0)), '2.LUC'!BM18), 0) | K30: =IF('2.LUC'!$C18<>"Please select",$K16-$D30+$N16,0) | L30: =K30*44/12 | M30: =IF('2.LUC'!$C18<>"Please select",P16+R16,0) | N30: =M30*44/12 | O30: =IF($I30<> "Please select", INDEX(IPCC!$B$852:$W$863,MATCH(clim_moist,IPCC!$A$852:$A$863,0),MATCH($I30,IPCC!$B$852:$W$852,0)),0) | P30: =IF($I30<>"Please select",IF('2.LUC'!BP18=0, $T16*$O30-$T16, '2.LUC'!BP18-$T16),0) | Q30: =P30*(-44/12)/20 | R30: =IF($E30="NO",0,(VLOOKUP($B30,$H$9:$I$16,2,FALSE)-$C30)) | S30: =IF($E30="YES", ($R30*VLOOKUP($B30, IPCC!$A$871:$E$906,2, FALSE)*VLOOKUP($B30, IPCC!$A$871:$E$906, 4, FALSE)), 0) | T30: =IF($E30="YES", ($R30*VLOOKUP($B30, IPCC!$A$871:$E$906,2, FALSE)*VLOOKUP($B30, IPCC!$A$871:$E$906, 5, FALSE)), 0) | U30: =IF($P30>=0, 0, ((-1)*(($P30/20*1/IPCC!$B$913)*1000))) | V30: =IF(country_selected="Please select",0,U30*VLOOKUP(moist_type, IPCC!$B$99:$C$101, 2, FALSE)*N2O_N_conversion) | W30: =($S30*methane+($T30+$V30)*Nitrous)/1000 | Z30: =IF($E30= "YES", $G42*$S30*methane/1000,0) | AA30: =IF($E30= "YES", $H42*$S30*methane/1000,0) | AB30: =$G42*$T30*Nitrous/1000 | AC30: =$H42*$T30*Nitrous/1000 | AD30: =$G42*$V30*Nitrous/1000 | AE30: =$H42*$V30*Nitrous/1000 | AG30: 0 | AH30: =IF($F30>0, $G42, 0) | AI30: =IF($F30>0, $H42, 0)
AG31: =SUM(AG23:AG30) | AH31: =SUM(AH23:AH30) | AI31: =SUM(AI23:AI30)
A32: GHG emissions | B32: Forested Area (ha) | G32: Area deforested (ha) | I32: Biomass loss (AGB + BGB) | K32: Biomass gain (1yr after) | M32: DOM loss (DW + litter) | O32: Soil emissions/removals | Q32: Fire + FSOM - kg N mineralized | S32: Total Balance | U32: Total
A33: Name | B33: Start | C33: Without Project | E33: With Project | G33: Without | H33: With | I33: Without | J33: With | K33: Without | L33: With | M33: Without | N33: With | O33: Without | P33: With | Q33: Without | R33: With | S33: Without | T33: With | U33: Deforestation
B34: t0 | C34: End | D34: Rate | E34: End | F34: Rate | G34: (ha) | H34: (ha) | I34: tCO2 | J34: tCO2 | K34: tCO2 | L34: tCO2 | M34: tCO2 | N34: tCO2 | O34: tCO2-e | P34: tCO2-e | Q34: tCO2-e | R34: tCO2-e | S34: tCO2-e | T34: tCO2-e | U34: tCO2-e | X34: Categories | Y34: Total | Z34: Implementation | AA34: Capitalization
A35: Deforestation 1 | B35: ='2.LUC'!$M11 | C35: ='2.LUC'!$N11 | D35: =VLOOKUP('2.LUC'!$O11, list!$I$48:$J$50,2,FALSE ) | E35: ='2.LUC'!$P11 | F35: =VLOOKUP('2.LUC'!$Q11, list!$I$48:$J$50,2,FALSE ) | G35: =IF($C35>$B35,0, $B35-$C35) | H35: =IF($E35>$B35,0, $B35-$E35) | I35: =$L23*($G35) | J35: =$H35*($L23) | K35: =IF($I35=0,0,IF('2.LUC'!$C11="Please select",0,-($G35*$J23*44/12))) | L35: =IF($J35=0,0,IF('2.LUC'!$C11="Please select",0,-($H35*$J23*44/12))) | M35: =$N23*($G35) | N35: =$N23*$H35 | O35: =IF(ABS($Q23*(IF($D35="Immediate",IF($G35>0, $G35*MIN(20,time_tot),0), $G35*IF(time_tot>time+20, 20, IF(time_tot<20,(time*VLOOKUP($D35, list!$J$48:$K$50,2,))+(time_tot-time),((MIN(20,time)*VLOOKUP($D35, list!$J$48:$K$50,2,)) + (time_tot-MIN(20,time))-IF($D35="Exponential",time_tot-20+0.217*time*(EXP(4.606*(20-time_tot)/time)-1),((time_tot-20)^2)*(0.5/time))))))))>=ABS(G35*P23*-44/12), G35*P23*-44/12, $Q23*(IF($D35="Immediate",IF($G35>0, $G35*MIN(20,time_tot),0), $G35*IF(time_tot>time+20, 20, IF(time_tot<20,(time*VLOOKUP($D35, list!$J$48:$K$50,2,))+(time_tot-time),((MIN(20,time)*VLOOKUP($D35, list!$J$48:$K$50,2,)) + (time_tot-MIN(20,time))-IF($D35="Exponential",time_tot-20+0.217*time*(EXP(4.606*(20-time_tot)/time)-1),((time_tot-20)^2)*(0.5/time)))))))) | P35: =IF(ABS($Q23*(IF($F35="Immediate",IF($H35 > 0, $H35*MIN(20,time_tot),0), $H35*IF(time_tot>time+20,20,IF(time_tot<20,(time*VLOOKUP($F35, list!$J$48:$K$50,2,))+(time_tot-time),((MIN(20,time)*VLOOKUP($F35,list!$J$48:$K$50,2,))+ (time_tot-MIN(20,time))-IF(F35="Exponential",time_tot-20+0.217*time*(EXP(4.606*(20-time_tot)/time)-1),((time_tot-20)^2)*(0.5/time))))))))>=ABS(H35*P23*-44/12),H35*P23*-44/12,$Q23*(IF($F35="Immediate",IF($H35 > 0, $H35*MIN(20,time_tot),0), $H35*IF(time_tot>time+20,20,IF(time_tot<20,(time*VLOOKUP($F35, list!$J$48:$K$50,2,))+(time_tot-time),((MIN(20,time)*VLOOKUP($F35,list!$J$48:$K$50,2,))+ (time_tot-MIN(20,time))-IF(F35="Exponential",time_tot-20+0.217*time*(EXP(4.606*(20-time_tot)/time)-1),((time_tot-20)^2)*(0.5/time)))))))) | Q35: =$G35*$W23 | R35: =$H35*$W23 | S35: =I35+K35+M35+O35+Q35 | T35: =J35+L35+N35+P35+R35 | U35: =$T35-$S35 | X35: CO2 Biomass | Y35: =SUM(J35:J42)+ SUM(L35:L42)-SUM(I35:I42)-SUM(K35:K42) | Z35: =IF(time=0,0,Y35) | AA35: =Y35-Z35
A36: Deforestation 2 | B36: ='2.LUC'!$M12 | C36: ='2.LUC'!$N12 | D36: =VLOOKUP('2.LUC'!$O12, list!$I$48:$J$50,2,FALSE ) | E36: ='2.LUC'!$P12 | F36: =VLOOKUP('2.LUC'!$Q12, list!$I$48:$J$50,2,FALSE ) | G36: =IF($C36>$B36,0, $B36-$C36) | H36: =IF($E36>$B36,0, $B36-$E36) | I36: =$L24*($G36) | J36: =$H36*($L24) | K36: =IF($I36=0,0,IF('2.LUC'!$C12="Please select",0,-($G36*$J24*44/12))) | L36: =IF($J36=0,0,IF('2.LUC'!$C12="Please select",0,-($H36*$J24*44/12))) | M36: =$N24*($G36) | N36: =$N24*$H36 | O36: =IF(ABS($Q24*(IF($D36="Immediate",IF($G36>0, $G36*MIN(20,time_tot),0), $G36*IF(time_tot>time+20, 20, IF(time_tot<20,(time*VLOOKUP($D36, list!$J$48:$K$50,2,))+(time_tot-time),((MIN(20,time)*VLOOKUP($D36, list!$J$48:$K$50,2,)) + (time_tot-MIN(20,time))-IF($D36="Exponential",time_tot-20+0.217*time*(EXP(4.606*(20-time_tot)/time)-1),((time_tot-20)^2)*(0.5/time))))))))>=ABS(G36*P24*-44/12), G36*P24*-44/12, $Q24*(IF($D36="Immediate",IF($G36>0, $G36*MIN(20,time_tot),0), $G36*IF(time_tot>time+20, 20, IF(time_tot<20,(time*VLOOKUP($D36, list!$J$48:$K$50,2,))+(time_tot-time),((MIN(20,time)*VLOOKUP($D36, list!$J$48:$K$50,2,)) + (time_tot-MIN(20,time))-IF($D36="Exponential",time_tot-20+0.217*time*(EXP(4.606*(20-time_tot)/time)-1),((time_tot-20)^2)*(0.5/time)))))))) | P36: =IF(ABS($Q24*(IF($F36="Immediate",IF($H36 > 0, $H36*MIN(20,time_tot),0), $H36*IF(time_tot>time+20,20,IF(time_tot<20,(time*VLOOKUP($F36, list!$J$48:$K$50,2,))+(time_tot-time),((MIN(20,time)*VLOOKUP($F36,list!$J$48:$K$50,2,))+ (time_tot-MIN(20,time))-IF(F36="Exponential",time_tot-20+0.217*time*(EXP(4.606*(20-time_tot)/time)-1),((time_tot-20)^2)*(0.5/time))))))))>=ABS(H36*P24*-44/12),H36*P24*-44/12,$Q24*(IF($F36="Immediate",IF($H36 > 0, $H36*MIN(20,time_tot),0), $H36*IF(time_tot>time+20,20,IF(time_tot<20,(time*VLOOKUP($F36, list!$J$48:$K$50,2,))+(time_tot-time),((MIN(20,time)*VLOOKUP($F36,list!$J$48:$K$50,2,))+ (time_tot-MIN(20,time))-IF(F36="Exponential",time_tot-20+0.217*time*(EXP(4.606*(20-time_tot)/time)-1),((time_tot-20)^2)*(0.5/time)))))))) | Q36: =$G36*$W24 | R36: =$H36*$W24 | S36: =I36+K36+M36+O36+Q36 | T36: =J36+L36+N36+P36+R36 | U36: =$T36-$S36 | X36: CO2 DOM | Y36: =SUM(N35:N42)-SUM(M35:M42) | Z36: =IF(time=0,0,Y36) | AA36: =Y36-Z36
A37: Deforestation 3 | B37: ='2.LUC'!$M13 | C37: ='2.LUC'!$N13 | D37: =VLOOKUP('2.LUC'!$O13, list!$I$48:$J$50,2,FALSE ) | E37: ='2.LUC'!$P13 | F37: =VLOOKUP('2.LUC'!$Q13, list!$I$48:$J$50,2,FALSE ) | G37: =IF($C37>$B37,0, $B37-$C37) | H37: =IF($E37>$B37,0, $B37-$E37) | I37: =$L25*($G37) | J37: =$H37*($L25) | K37: =IF($I37=0,0,IF('2.LUC'!$C13="Please select",0,-($G37*$J25*44/12))) | L37: =IF($J37=0,0,IF('2.LUC'!$C13="Please select",0,-($H37*$J25*44/12))) | M37: =$N25*($G37) | N37: =$N25*$H37 | O37: =IF(ABS($Q25*(IF($D37="Immediate",IF($G37>0, $G37*MIN(20,time_tot),0), $G37*IF(time_tot>time+20, 20, IF(time_tot<20,(time*VLOOKUP($D37, list!$J$48:$K$50,2,))+(time_tot-time),((MIN(20,time)*VLOOKUP($D37, list!$J$48:$K$50,2,)) + (time_tot-MIN(20,time))-IF($D37="Exponential",time_tot-20+0.217*time*(EXP(4.606*(20-time_tot)/time)-1),((time_tot-20)^2)*(0.5/time))))))))>=ABS(G37*P25*-44/12), G37*P25*-44/12, $Q25*(IF($D37="Immediate",IF($G37>0, $G37*MIN(20,time_tot),0), $G37*IF(time_tot>time+20, 20, IF(time_tot<20,(time*VLOOKUP($D37, list!$J$48:$K$50,2,))+(time_tot-time),((MIN(20,time)*VLOOKUP($D37, list!$J$48:$K$50,2,)) + (time_tot-MIN(20,time))-IF($D37="Exponential",time_tot-20+0.217*time*(EXP(4.606*(20-time_tot)/time)-1),((time_tot-20)^2)*(0.5/time)))))))) | P37: =IF(ABS($Q25*(IF($F37="Immediate",IF($H37 > 0, $H37*MIN(20,time_tot),0), $H37*IF(time_tot>time+20,20,IF(time_tot<20,(time*VLOOKUP($F37, list!$J$48:$K$50,2,))+(time_tot-time),((MIN(20,time)*VLOOKUP($F37,list!$J$48:$K$50,2,))+ (time_tot-MIN(20,time))-IF(F37="Exponential",time_tot-20+0.217*time*(EXP(4.606*(20-time_tot)/time)-1),((time_tot-20)^2)*(0.5/time))))))))>=ABS(H37*P25*-44/12),H37*P25*-44/12,$Q25*(IF($F37="Immediate",IF($H37 > 0, $H37*MIN(20,time_tot),0), $H37*IF(time_tot>time+20,20,IF(time_tot<20,(time*VLOOKUP($F37, list!$J$48:$K$50,2,))+(time_tot-time),((MIN(20,time)*VLOOKUP($F37,list!$J$48:$K$50,2,))+ (time_tot-MIN(20,time))-IF(F37="Exponential",time_tot-20+0.217*time*(EXP(4.606*(20-time_tot)/time)-1),((time_tot-20)^2)*(0.5/time)))))))) | Q37: =$G37*$W25 | R37: =$H37*$W25 | S37: =I37+K37+M37+O37+Q37 | T37: =J37+L37+N37+P37+R37 | U37: =$T37-$S37 | V37: =P23*H35*44/12 | X37: CO2 soil | Y37: =SUM(P35:P42)-SUM(O35:O42) | Z37: =IF(time=0,0,SUM(P35:P42)-SUM(O35:O42)) | AA37: =Y37-Z37
A38: Deforestation 4 | B38: ='2.LUC'!$M14 | C38: ='2.LUC'!$N14 | D38: =VLOOKUP('2.LUC'!$O14, list!$I$48:$J$50,2,FALSE ) | E38: ='2.LUC'!$P14 | F38: =VLOOKUP('2.LUC'!$Q14, list!$I$48:$J$50,2,FALSE ) | G38: =IF($C38>$B38,0, $B38-$C38) | H38: =IF($E38>$B38,0, $B38-$E38) | I38: =$L26*($G38) | J38: =$H38*($L26) | K38: =IF($I38=0,0,IF('2.LUC'!$C14="Please select",0,-($G38*$J26*44/12))) | L38: =IF($J38=0,0,IF('2.LUC'!$C14="Please select",0,-($H38*$J26*44/12))) | M38: =$N26*($G38) | N38: =$N26*$H38 | O38: =IF(ABS($Q26*(IF($D38="Immediate",IF($G38>0, $G38*MIN(20,time_tot),0), $G38*IF(time_tot>time+20, 20, IF(time_tot<20,(time*VLOOKUP($D38, list!$J$48:$K$50,2,))+(time_tot-time),((MIN(20,time)*VLOOKUP($D38, list!$J$48:$K$50,2,)) + (time_tot-MIN(20,time))-IF($D38="Exponential",time_tot-20+0.217*time*(EXP(4.606*(20-time_tot)/time)-1),((time_tot-20)^2)*(0.5/time))))))))>=ABS(G38*P26*-44/12), G38*P26*-44/12, $Q26*(IF($D38="Immediate",IF($G38>0, $G38*MIN(20,time_tot),0), $G38*IF(time_tot>time+20, 20, IF(time_tot<20,(time*VLOOKUP($D38, list!$J$48:$K$50,2,))+(time_tot-time),((MIN(20,time)*VLOOKUP($D38, list!$J$48:$K$50,2,)) + (time_tot-MIN(20,time))-IF($D38="Exponential",time_tot-20+0.217*time*(EXP(4.606*(20-time_tot)/time)-1),((time_tot-20)^2)*(0.5/time)))))))) | P38: =IF(ABS($Q26*(IF($F38="Immediate",IF($H38 > 0, $H38*MIN(20,time_tot),0), $H38*IF(time_tot>time+20,20,IF(time_tot<20,(time*VLOOKUP($F38, list!$J$48:$K$50,2,))+(time_tot-time),((MIN(20,time)*VLOOKUP($F38,list!$J$48:$K$50,2,))+ (time_tot-MIN(20,time))-IF(F38="Exponential",time_tot-20+0.217*time*(EXP(4.606*(20-time_tot)/time)-1),((time_tot-20)^2)*(0.5/time))))))))>=ABS(H38*P26*-44/12),H38*P26*-44/12,$Q26*(IF($F38="Immediate",IF($H38 > 0, $H38*MIN(20,time_tot),0), $H38*IF(time_tot>time+20,20,IF(time_tot<20,(time*VLOOKUP($F38, list!$J$48:$K$50,2,))+(time_tot-time),((MIN(20,time)*VLOOKUP($F38,list!$J$48:$K$50,2,))+ (time_tot-MIN(20,time))-IF(F38="Exponential",time_tot-20+0.217*time*(EXP(4.606*(20-time_tot)/time)-1),((time_tot-20)^2)*(0.5/time)))))))) | Q38: =$G38*$W26 | R38: =$H38*$W26 | S38: =I38+K38+M38+O38+Q38 | T38: =J38+L38+N38+P38+R38 | U38: =$T38-$S38 | X38: CH4 fire | Y38: =SUM(AA23:AA30)-SUM(Z23:Z30) | Z38: =IF(time=0, 0, Y38) | AA38: =Y38-Z38
A39: Deforestation 5 | B39: ='2.LUC'!$M15 | C39: ='2.LUC'!$N15 | D39: =VLOOKUP('2.LUC'!$O15, list!$I$48:$J$50,2,FALSE ) | E39: ='2.LUC'!$P15 | F39: =VLOOKUP('2.LUC'!$Q15, list!$I$48:$J$50,2,FALSE ) | G39: =IF($C39>$B39,0, $B39-$C39) | H39: =IF($E39>$B39,0, $B39-$E39) | I39: =$L27*($G39) | J39: =$H39*($L27) | K39: =IF($I39=0,0,IF('2.LUC'!$C15="Please select",0,-($G39*$J27*44/12))) | L39: =IF($J39=0,0,IF('2.LUC'!$C15="Please select",0,-($H39*$J27*44/12))) | M39: =$N27*($G39) | N39: =$N27*$H39 | O39: =IF(ABS($Q27*(IF($D39="Immediate",IF($G39>0, $G39*MIN(20,time_tot),0), $G39*IF(time_tot>time+20, 20, IF(time_tot<20,(time*VLOOKUP($D39, list!$J$48:$K$50,2,))+(time_tot-time),((MIN(20,time)*VLOOKUP($D39, list!$J$48:$K$50,2,)) + (time_tot-MIN(20,time))-IF($D39="Exponential",time_tot-20+0.217*time*(EXP(4.606*(20-time_tot)/time)-1),((time_tot-20)^2)*(0.5/time))))))))>=ABS(G39*P27*-44/12), G39*P27*-44/12, $Q27*(IF($D39="Immediate",IF($G39>0, $G39*MIN(20,time_tot),0), $G39*IF(time_tot>time+20, 20, IF(time_tot<20,(time*VLOOKUP($D39, list!$J$48:$K$50,2,))+(time_tot-time),((MIN(20,time)*VLOOKUP($D39, list!$J$48:$K$50,2,)) + (time_tot-MIN(20,time))-IF($D39="Exponential",time_tot-20+0.217*time*(EXP(4.606*(20-time_tot)/time)-1),((time_tot-20)^2)*(0.5/time)))))))) | P39: =IF(ABS($Q27*(IF($F39="Immediate",IF($H39 > 0, $H39*MIN(20,time_tot),0), $H39*IF(time_tot>time+20,20,IF(time_tot<20,(time*VLOOKUP($F39, list!$J$48:$K$50,2,))+(time_tot-time),((MIN(20,time)*VLOOKUP($F39,list!$J$48:$K$50,2,))+ (time_tot-MIN(20,time))-IF(F39="Exponential",time_tot-20+0.217*time*(EXP(4.606*(20-time_tot)/time)-1),((time_tot-20)^2)*(0.5/time))))))))>=ABS(H39*P27*-44/12),H39*P27*-44/12,$Q27*(IF($F39="Immediate",IF($H39 > 0, $H39*MIN(20,time_tot),0), $H39*IF(time_tot>time+20,20,IF(time_tot<20,(time*VLOOKUP($F39, list!$J$48:$K$50,2,))+(time_tot-time),((MIN(20,time)*VLOOKUP($F39,list!$J$48:$K$50,2,))+ (time_tot-MIN(20,time))-IF(F39="Exponential",time_tot-20+0.217*time*(EXP(4.606*(20-time_tot)/time)-1),((time_tot-20)^2)*(0.5/time)))))))) | Q39: =$G39*$W27 | R39: =$H39*$W27 | S39: =I39+K39+M39+O39+Q39 | T39: =J39+L39+N39+P39+R39 | U39: =$T39-$S39 | X39: N2O fire | Y39: =SUM(AC23:AC30)-SUM(AB23:AB30) | Z39: =IF(time=0, 0, Y39) | AA39: =Y39-Z39
A40: Deforestation 6 | B40: ='2.LUC'!$M16 | C40: ='2.LUC'!$N16 | D40: =VLOOKUP('2.LUC'!$O16, list!$I$48:$J$50,2,FALSE ) | E40: ='2.LUC'!$P16 | F40: =VLOOKUP('2.LUC'!$Q16, list!$I$48:$J$50,2,FALSE ) | G40: =IF($C40>$B40,0, $B40-$C40) | H40: =IF($E40>$B40,0, $B40-$E40) | I40: =$L28*($G40) | J40: =$H40*($L28) | K40: =IF($I40=0,0,IF('2.LUC'!$C16="Please select",0,-($G40*$J28*44/12))) | L40: =IF($J40=0,0,IF('2.LUC'!$C16="Please select",0,-($H40*$J28*44/12))) | M40: =$N28*($G40) | N40: =$N28*$H40 | O40: =IF(ABS($Q28*(IF($D40="Immediate",IF($G40>0, $G40*MIN(20,time_tot),0), $G40*IF(time_tot>time+20, 20, IF(time_tot<20,(time*VLOOKUP($D40, list!$J$48:$K$50,2,))+(time_tot-time),((MIN(20,time)*VLOOKUP($D40, list!$J$48:$K$50,2,)) + (time_tot-MIN(20,time))-IF($D40="Exponential",time_tot-20+0.217*time*(EXP(4.606*(20-time_tot)/time)-1),((time_tot-20)^2)*(0.5/time))))))))>=ABS(G40*P28*-44/12), G40*P28*-44/12, $Q28*(IF($D40="Immediate",IF($G40>0, $G40*MIN(20,time_tot),0), $G40*IF(time_tot>time+20, 20, IF(time_tot<20,(time*VLOOKUP($D40, list!$J$48:$K$50,2,))+(time_tot-time),((MIN(20,time)*VLOOKUP($D40, list!$J$48:$K$50,2,)) + (time_tot-MIN(20,time))-IF($D40="Exponential",time_tot-20+0.217*time*(EXP(4.606*(20-time_tot)/time)-1),((time_tot-20)^2)*(0.5/time)))))))) | P40: =IF(ABS($Q28*(IF($F40="Immediate",IF($H40 > 0, $H40*MIN(20,time_tot),0), $H40*IF(time_tot>time+20,20,IF(time_tot<20,(time*VLOOKUP($F40, list!$J$48:$K$50,2,))+(time_tot-time),((MIN(20,time)*VLOOKUP($F40,list!$J$48:$K$50,2,))+ (time_tot-MIN(20,time))-IF(F40="Exponential",time_tot-20+0.217*time*(EXP(4.606*(20-time_tot)/time)-1),((time_tot-20)^2)*(0.5/time))))))))>=ABS(H40*P28*-44/12),H40*P28*-44/12,$Q28*(IF($F40="Immediate",IF($H40 > 0, $H40*MIN(20,time_tot),0), $H40*IF(time_tot>time+20,20,IF(time_tot<20,(time*VLOOKUP($F40, list!$J$48:$K$50,2,))+(time_tot-time),((MIN(20,time)*VLOOKUP($F40,list!$J$48:$K$50,2,))+ (time_tot-MIN(20,time))-IF(F40="Exponential",time_tot-20+0.217*time*(EXP(4.606*(20-time_tot)/time)-1),((time_tot-20)^2)*(0.5/time)))))))) | Q40: =$G40*$W28 | R40: =$H40*$W28 | S40: =I40+K40+M40+O40+Q40 | T40: =J40+L40+N40+P40+R40 | U40: =$T40-$S40 | X40: N2O SOM | Y40: =SUM(AE23:AE30)-SUM(AD23:AD30) | Z40: =IF(time=0, 0, Y40) | AA40: =Y40-Z40
A41: Deforestation 7 | B41: ='2.LUC'!$M17 | C41: ='2.LUC'!$N17 | D41: =VLOOKUP('2.LUC'!$O17, list!$I$48:$J$50,2,FALSE ) | E41: ='2.LUC'!$P17 | F41: =VLOOKUP('2.LUC'!$Q17, list!$I$48:$J$50,2,FALSE ) | G41: =IF($C41>$B41,0, $B41-$C41) | H41: =IF($E41>$B41,0, $B41-$E41) | I41: =$L29*($G41) | J41: =$H41*($L29) | K41: =IF($I41=0,0,IF('2.LUC'!$C17="Please select",0,-($G41*$J29*44/12))) | L41: =IF($J41=0,0,IF('2.LUC'!$C17="Please select",0,-($H41*$J29*44/12))) | M41: =$N29*($G41) | N41: =$N29*$H41 | O41: =IF(ABS($Q29*(IF($D41="Immediate",IF($G41>0, $G41*MIN(20,time_tot),0), $G41*IF(time_tot>time+20, 20, IF(time_tot<20,(time*VLOOKUP($D41, list!$J$48:$K$50,2,))+(time_tot-time),((MIN(20,time)*VLOOKUP($D41, list!$J$48:$K$50,2,)) + (time_tot-MIN(20,time))-IF($D41="Exponential",time_tot-20+0.217*time*(EXP(4.606*(20-time_tot)/time)-1),((time_tot-20)^2)*(0.5/time))))))))>=ABS(G41*P29*-44/12), G41*P29*-44/12, $Q29*(IF($D41="Immediate",IF($G41>0, $G41*MIN(20,time_tot),0), $G41*IF(time_tot>time+20, 20, IF(time_tot<20,(time*VLOOKUP($D41, list!$J$48:$K$50,2,))+(time_tot-time),((MIN(20,time)*VLOOKUP($D41, list!$J$48:$K$50,2,)) + (time_tot-MIN(20,time))-IF($D41="Exponential",time_tot-20+0.217*time*(EXP(4.606*(20-time_tot)/time)-1),((time_tot-20)^2)*(0.5/time)))))))) | P41: =IF(ABS($Q29*(IF($F41="Immediate",IF($H41 > 0, $H41*MIN(20,time_tot),0), $H41*IF(time_tot>time+20,20,IF(time_tot<20,(time*VLOOKUP($F41, list!$J$48:$K$50,2,))+(time_tot-time),((MIN(20,time)*VLOOKUP($F41,list!$J$48:$K$50,2,))+ (time_tot-MIN(20,time))-IF(F41="Exponential",time_tot-20+0.217*time*(EXP(4.606*(20-time_tot)/time)-1),((time_tot-20)^2)*(0.5/time))))))))>=ABS(H41*P29*-44/12),H41*P29*-44/12,$Q29*(IF($F41="Immediate",IF($H41 > 0, $H41*MIN(20,time_tot),0), $H41*IF(time_tot>time+20,20,IF(time_tot<20,(time*VLOOKUP($F41, list!$J$48:$K$50,2,))+(time_tot-time),((MIN(20,time)*VLOOKUP($F41,list!$J$48:$K$50,2,))+ (time_tot-MIN(20,time))-IF(F41="Exponential",time_tot-20+0.217*time*(EXP(4.606*(20-time_tot)/time)-1),((time_tot-20)^2)*(0.5/time)))))))) | Q41: =$G41*$W29 | R41: =$H41*$W29 | S41: =I41+K41+M41+O41+Q41 | T41: =J41+L41+N41+P41+R41 | U41: =$T41-$S41 | X41: Total | Y41: =SUM(Y35:Y40) | Z41: =SUM(Z35:Z40) | AA41: =SUM(AA35:AA40)
A42: Deforestation 8 | B42: ='2.LUC'!$M18 | C42: ='2.LUC'!$N18 | D42: =VLOOKUP('2.LUC'!$O18, list!$I$48:$J$50,2,FALSE ) | E42: ='2.LUC'!$P18 | F42: =VLOOKUP('2.LUC'!$Q18, list!$I$48:$J$50,2,FALSE ) | G42: =IF($C42>$B42,0, $B42-$C42) | H42: =IF($E42>$B42,0, $B42-$E42) | I42: =$L30*($G42) | J42: =$H42*($L30) | K42: =IF($I42=0,0,IF('2.LUC'!$C18="Please select",0,-($G42*$J30*44/12))) | L42: =IF($J42=0,0,IF('2.LUC'!$C18="Please select",0,-($H42*$J30*44/12))) | M42: =$N30*($G42) | N42: =$N30*$H42 | O42: =IF(ABS($Q30*(IF($D42="Immediate",IF($G42>0, $G42*MIN(20,time_tot),0), $G42*IF(time_tot>time+20, 20, IF(time_tot<20,(time*VLOOKUP($D42, list!$J$48:$K$50,2,))+(time_tot-time),((MIN(20,time)*VLOOKUP($D42, list!$J$48:$K$50,2,)) + (time_tot-MIN(20,time))-IF($D42="Exponential",time_tot-20+0.217*time*(EXP(4.606*(20-time_tot)/time)-1),((time_tot-20)^2)*(0.5/time))))))))>=ABS(G42*P30*-44/12), G42*P30*-44/12, $Q30*(IF($D42="Immediate",IF($G42>0, $G42*MIN(20,time_tot),0), $G42*IF(time_tot>time+20, 20, IF(time_tot<20,(time*VLOOKUP($D42, list!$J$48:$K$50,2,))+(time_tot-time),((MIN(20,time)*VLOOKUP($D42, list!$J$48:$K$50,2,)) + (time_tot-MIN(20,time))-IF($D42="Exponential",time_tot-20+0.217*time*(EXP(4.606*(20-time_tot)/time)-1),((time_tot-20)^2)*(0.5/time)))))))) | P42: =IF(ABS($Q30*(IF($F42="Immediate",IF($H42 > 0, $H42*MIN(20,time_tot),0), $H42*IF(time_tot>time+20,20,IF(time_tot<20,(time*VLOOKUP($F42, list!$J$48:$K$50,2,))+(time_tot-time),((MIN(20,time)*VLOOKUP($F42,list!$J$48:$K$50,2,))+ (time_tot-MIN(20,time))-IF(F42="Exponential",time_tot-20+0.217*time*(EXP(4.606*(20-time_tot)/time)-1),((time_tot-20)^2)*(0.5/time))))))))>=ABS(H42*P30*-44/12),H42*P30*-44/12,$Q30*(IF($F42="Immediate",IF($H42 > 0, $H42*MIN(20,time_tot),0), $H42*IF(time_tot>time+20,20,IF(time_tot<20,(time*VLOOKUP($F42, list!$J$48:$K$50,2,))+(time_tot-time),((MIN(20,time)*VLOOKUP($F42,list!$J$48:$K$50,2,))+ (time_tot-MIN(20,time))-IF(F42="Exponential",time_tot-20+0.217*time*(EXP(4.606*(20-time_tot)/time)-1),((time_tot-20)^2)*(0.5/time)))))))) | Q42: =$G42*$W30 | R42: =$H42*$W30 | S42: =I42+K42+M42+O42+Q42 | T42: =J42+L42+N42+P42+R42 | U42: =$T42-$S42
R44: Total deforestation | S44: =SUM(S35:S42) | T44: =SUM(T35:T42) | U44: =SUM(U35:U42)
T46: TEST TIER 2 biomass | U46: =SUM('2.LUC'!AT11:AT18,'2.LUC'!AW11:AW18)

Sheet luc
C2: 2.3 Other land-use and cropland management changes
C3: changes in biomass refer to the first year in which the land use change occurs
S4: Categories | T4: Total | U4: Implementation | V4: Capitalization
S5: CO2 Biomass | T5: =SUM(H41:H50)-SUM(G41:G50) | U5: =IF(time=0,0,T5) | V5: =T5-U5
H6: Biomass (tC/ha) | L6: SOC (tC/ha) | S6: CO2 soil | T6: =SUM(J41:J50)-SUM(I41:I50) | U6: =SUM(X24:X33)-SUM(W24:W33) | V6: =T6-U6
C7: User | D7: Burnt before | E7: Initial | F7: Final | G7: ERROR! | H7: pick Tier 2, if available | L7: pick Tier 2, if available | S7: N2O soil | T7: =SUM(V24:V33)-SUM(U24:U33) | U7: =IF(time=0,0,T7) | V7: =T7-U7
B8: SI | C8: Description | D8: LU change | E8: LU | F8: LU | G8: Message | H8: Initial LU Default | I8: Initial LU Tier 2 | J8: Final LU Default | K8: Final LU Tier 2 | L8: Initial LU Default | M8: Initial LU Tier 2 | N8: Final LU Default | O8: Final LU Tier 2 | S8: CH4 | T8: =SUM(R24:R33)-SUM(Q24:Q33) | U8: =IF(time=0,0,T8) | V8: =T8-U8
B9: 1 | C9: =IF('2.LUC'!$C61 = "", "", '2.LUC'!$C61) | D9: ='2.LUC'!$G61 | E9: ='2.LUC'!$I61 | F9: ='2.LUC'!$K61 | H9: =IF($E9 <> "Please select",INDEX(IPCC!$D$1520:$Y$1680,MATCH(clim_moist_cont,IPCC!$C$1520:$C$1680,0),MATCH($E9,IPCC!$D$1520:$Y$1520,0)),0) | I9: =IF('2.LUC'!AW61="",'2.LUC'!AV61,'2.LUC'!AW61) | J9: =IF($F9 <> "Please select", INDEX(IPCC!$D$682:$Y$845,MATCH(clim_moist_cont,IPCC!$C$682:$C$845,0),MATCH($F9,IPCC!$D$682:$Y$682,0)),0) | K9: =IF('2.LUC'!BE61="",'2.LUC'!BD61,'2.LUC'!BE61) | L9: =IF($E9<> "Please select", SOCref*INDEX(IPCC!$B$1687:$W$1698,MATCH(clim_moist, IPCC!$A$1687:$A$1698,0),MATCH($E9, IPCC!$B$1687:$W$1687,0)),0) | M9: =IF('2.LUC'!AZ61="",'2.LUC'!AY61,'2.LUC'!AZ61) | N9: =IF($F9<> "Please select",SOCref*INDEX(IPCC!$B$852:$W$863,MATCH(clim_moist, IPCC!$A$852:$A$863,0),MATCH($F9, IPCC!$B$852:$W$852,0)),0) | O9: =IF('2.LUC'!BH61="",'2.LUC'!BG61,'2.LUC'!BH61) | S9: N2O fire | T9: =SUM(T24:T33)-SUM(S24:S33) | U9: =IF(time=0,0,T9) | V9: =T9-U9
B10: 2 | C10: =IF('2.LUC'!$C62 = "", "", '2.LUC'!$C62) | D10: ='2.LUC'!$G62 | E10: ='2.LUC'!$I62 | F10: ='2.LUC'!$K62 | H10: =IF($E10 <> "Please select",INDEX(IPCC!$D$1520:$Y$1680,MATCH(clim_moist_cont,IPCC!$C$1520:$C$1680,0),MATCH($E10,IPCC!$D$1520:$Y$1520,0)),0) | I10: =IF('2.LUC'!AW62="",'2.LUC'!AV62,'2.LUC'!AW62) | J10: =IF($F10 <> "Please select", INDEX(IPCC!$D$682:$Y$845,MATCH(clim_moist_cont,IPCC!$C$682:$C$845,0),MATCH($F10,IPCC!$D$682:$Y$682,0)),0) | K10: =IF('2.LUC'!BE62="",'2.LUC'!BD62,'2.LUC'!BE62) | L10: =IF($E10<> "Please select", SOCref*INDEX(IPCC!$B$1687:$W$1698,MATCH(clim_moist, IPCC!$A$1687:$A$1698,0),MATCH($E10, IPCC!$B$1687:$W$1687,0)),0) | M10: =IF('2.LUC'!AZ62="",'2.LUC'!AY62,'2.LUC'!AZ62) | N10: =IF($F10<> "Please select",SOCref*INDEX(IPCC!$B$852:$W$863,MATCH(clim_moist, IPCC!$A$852:$A$863,0),MATCH($F10, IPCC!$B$852:$W$852,0)),0) | O10: =IF('2.LUC'!BH62="",'2.LUC'!BG62,'2.LUC'!BH62) | S10: Total | T10: =SUM(T5:T9) | U10: =SUM(U5:U9) | V10: =SUM(V5:V9)
B11: 3 | C11: =IF('2.LUC'!$C63 = "", "", '2.LUC'!$C63) | D11: ='2.LUC'!$G63 | E11: ='2.LUC'!$I63 | F11: ='2.LUC'!$K63 | H11: =IF($E11 <> "Please select",INDEX(IPCC!$D$1520:$Y$1680,MATCH(clim_moist_cont,IPCC!$C$1520:$C$1680,0),MATCH($E11,IPCC!$D$1520:$Y$1520,0)),0) | I11: =IF('2.LUC'!AW63="",'2.LUC'!AV63,'2.LUC'!AW63) | J11: =IF($F11 <> "Please select", INDEX(IPCC!$D$682:$Y$845,MATCH(clim_moist_cont,IPCC!$C$682:$C$845,0),MATCH($F11,IPCC!$D$682:$Y$682,0)),0) | K11: =IF('2.LUC'!BE63="",'2.LUC'!BD63,'2.LUC'!BE63) | L11: =IF($E11<> "Please select", SOCref*INDEX(IPCC!$B$1687:$W$1698,MATCH(clim_moist, IPCC!$A$1687:$A$1698,0),MATCH($E11, IPCC!$B$1687:$W$1687,0)),0) | M11: =IF('2.LUC'!AZ63="",'2.LUC'!AY63,'2.LUC'!AZ63) | N11: =IF($F11<> "Please select",SOCref*INDEX(IPCC!$B$852:$W$863,MATCH(clim_moist, IPCC!$A$852:$A$863,0),MATCH($F11, IPCC!$B$852:$W$852,0)),0) | O11: =IF('2.LUC'!BH63="",'2.LUC'!BG63,'2.LUC'!BH63)
B12: 4 | C12: =IF('2.LUC'!#REF! = "", "", '2.LUC'!#REF!) | D12: ='2.LUC'!$G64 | E12: ='2.LUC'!$I64 | F12: ='2.LUC'!$K64 | H12: =IF($E12 <> "Please select",INDEX(IPCC!$D$1520:$Y$1680,MATCH(clim_moist_cont,IPCC!$C$1520:$C$1680,0),MATCH($E12,IPCC!$D$1520:$Y$1520,0)),0) | I12: =IF('2.LUC'!AW64="",'2.LUC'!AV64,'2.LUC'!AW64) | J12: =IF($F12 <> "Please select", INDEX(IPCC!$D$682:$Y$845,MATCH(clim_moist_cont,IPCC!$C$682:$C$845,0),MATCH($F12,IPCC!$D$682:$Y$682,0)),0) | K12: =IF('2.LUC'!BE64="",'2.LUC'!BD64,'2.LUC'!BE64) | L12: =IF($E12<> "Please select", SOCref*INDEX(IPCC!$B$1687:$W$1698,MATCH(clim_moist, IPCC!$A$1687:$A$1698,0),MATCH($E12, IPCC!$B$1687:$W$1687,0)),0) | M12: =IF('2.LUC'!AZ64="",'2.LUC'!AY64,'2.LUC'!AZ64) | N12: =IF($F12<> "Please select",SOCref*INDEX(IPCC!$B$852:$W$863,MATCH(clim_moist, IPCC!$A$852:$A$863,0),MATCH($F12, IPCC!$B$852:$W$852,0)),0) | O12: =IF('2.LUC'!BH64="",'2.LUC'!BG64,'2.LUC'!BH64) | S12: All period
B13: 5 | C13: =IF('2.LUC'!$C64 = "", "", '2.LUC'!$C64) | D13: ='2.LUC'!$G65 | E13: ='2.LUC'!$I65 | F13: ='2.LUC'!$K65 | H13: =IF($E13 <> "Please select",INDEX(IPCC!$D$1520:$Y$1680,MATCH(clim_moist_cont,IPCC!$C$1520:$C$1680,0),MATCH($E13,IPCC!$D$1520:$Y$1520,0)),0) | I13: =IF('2.LUC'!AW65="",'2.LUC'!AV65,'2.LUC'!AW65) | J13: =IF($F13 <> "Please select", INDEX(IPCC!$D$682:$Y$845,MATCH(clim_moist_cont,IPCC!$C$682:$C$845,0),MATCH($F13,IPCC!$D$682:$Y$682,0)),0) | K13: =IF('2.LUC'!BE65="",'2.LUC'!BD65,'2.LUC'!BE65) | L13: =IF($E13<> "Please select", SOCref*INDEX(IPCC!$B$1687:$W$1698,MATCH(clim_moist, IPCC!$A$1687:$A$1698,0),MATCH($E13, IPCC!$B$1687:$W$1687,0)),0) | M13: =IF('2.LUC'!AZ65="",'2.LUC'!AY65,'2.LUC'!AZ65) | N13: =IF($F13<> "Please select",SOCref*INDEX(IPCC!$B$852:$W$863,MATCH(clim_moist, IPCC!$A$852:$A$863,0),MATCH($F13, IPCC!$B$852:$W$852,0)),0) | O13: =IF('2.LUC'!BH65="",'2.LUC'!BG65,'2.LUC'!BH65) | S13: Categories | T13: Without | U13: With
B14: 6 | C14: =IF('2.LUC'!$C66 = "", "", '2.LUC'!$C66) | D14: ='2.LUC'!$G66 | E14: ='2.LUC'!$I66 | F14: ='2.LUC'!$K66 | H14: =IF($E14 <> "Please select",INDEX(IPCC!$D$1520:$Y$1680,MATCH(clim_moist_cont,IPCC!$C$1520:$C$1680,0),MATCH($E14,IPCC!$D$1520:$Y$1520,0)),0) | I14: =IF('2.LUC'!AW66="",'2.LUC'!AV66,'2.LUC'!AW66) | J14: =IF($F14 <> "Please select", INDEX(IPCC!$D$682:$Y$845,MATCH(clim_moist_cont,IPCC!$C$682:$C$845,0),MATCH($F14,IPCC!$D$682:$Y$682,0)),0) | K14: =IF('2.LUC'!BE66="",'2.LUC'!BD66,'2.LUC'!BE66) | L14: =IF($E14<> "Please select", SOCref*INDEX(IPCC!$B$1687:$W$1698,MATCH(clim_moist, IPCC!$A$1687:$A$1698,0),MATCH($E14, IPCC!$B$1687:$W$1687,0)),0) | M14: =IF('2.LUC'!AZ66="",'2.LUC'!AY66,'2.LUC'!AZ66) | N14: =IF($F14<> "Please select",SOCref*INDEX(IPCC!$B$852:$W$863,MATCH(clim_moist, IPCC!$A$852:$A$863,0),MATCH($F14, IPCC!$B$852:$W$852,0)),0) | O14: =IF('2.LUC'!BH66="",'2.LUC'!BG66,'2.LUC'!BH66) | S14: CO2 Biomass | T14: =SUM(G41:G50) | U14: =SUM(H41:H50)
B15: 7 | C15: =IF('2.LUC'!$C67 = "", "", '2.LUC'!$C67) | D15: ='2.LUC'!$G67 | E15: ='2.LUC'!$I67 | F15: ='2.LUC'!$K67 | H15: =IF($E15 <> "Please select",INDEX(IPCC!$D$1520:$Y$1680,MATCH(clim_moist_cont,IPCC!$C$1520:$C$1680,0),MATCH($E15,IPCC!$D$1520:$Y$1520,0)),0) | I15: =IF('2.LUC'!AW67="",'2.LUC'!AV67,'2.LUC'!AW67) | J15: =IF($F15 <> "Please select", INDEX(IPCC!$D$682:$Y$845,MATCH(clim_moist_cont,IPCC!$C$682:$C$845,0),MATCH($F15,IPCC!$D$682:$Y$682,0)),0) | K15: =IF('2.LUC'!BE67="",'2.LUC'!BD67,'2.LUC'!BE67) | L15: =IF($E15<> "Please select", SOCref*INDEX(IPCC!$B$1687:$W$1698,MATCH(clim_moist, IPCC!$A$1687:$A$1698,0),MATCH($E15, IPCC!$B$1687:$W$1687,0)),0) | M15: =IF('2.LUC'!AZ67="",'2.LUC'!AY67,'2.LUC'!AZ67) | N15: =IF($F15<> "Please select",SOCref*INDEX(IPCC!$B$852:$W$863,MATCH(clim_moist, IPCC!$A$852:$A$863,0),MATCH($F15, IPCC!$B$852:$W$852,0)),0) | O15: =IF('2.LUC'!BH67="",'2.LUC'!BG67,'2.LUC'!BH67) | S15: CO2 soil | T15: =SUM(I41:I50) | U15: =SUM(J41:J50)
B16: 8 | C16: =IF('2.LUC'!$C68 = "", "", '2.LUC'!$C68) | D16: ='2.LUC'!$G68 | E16: ='2.LUC'!$I68 | F16: ='2.LUC'!$K68 | H16: =IF($E16 <> "Please select",INDEX(IPCC!$D$1520:$Y$1680,MATCH(clim_moist_cont,IPCC!$C$1520:$C$1680,0),MATCH($E16,IPCC!$D$1520:$Y$1520,0)),0) | I16: =IF('2.LUC'!AW68="",'2.LUC'!AV68,'2.LUC'!AW68) | J16: =IF($F16 <> "Please select", INDEX(IPCC!$D$682:$Y$845,MATCH(clim_moist_cont,IPCC!$C$682:$C$845,0),MATCH($F16,IPCC!$D$682:$Y$682,0)),0) | K16: =IF('2.LUC'!BE68="",'2.LUC'!BD68,'2.LUC'!BE68) | L16: =IF($E16<> "Please select", SOCref*INDEX(IPCC!$B$1687:$W$1698,MATCH(clim_moist, IPCC!$A$1687:$A$1698,0),MATCH($E16, IPCC!$B$1687:$W$1687,0)),0) | M16: =IF('2.LUC'!AZ68="",'2.LUC'!AY68,'2.LUC'!AZ68) | N16: =IF($F16<> "Please select",SOCref*INDEX(IPCC!$B$852:$W$863,MATCH(clim_moist, IPCC!$A$852:$A$863,0),MATCH($F16, IPCC!$B$852:$W$852,0)),0) | O16: =IF('2.LUC'!BH68="",'2.LUC'!BG68,'2.LUC'!BH68) | S16: N2O soil | T16: =SUM(U24:U33) | U16: =SUM(V24:V33)
B17: 9 | C17: =IF('2.LUC'!$C69 = "", "", '2.LUC'!$C69) | D17: ='2.LUC'!$G69 | E17: ='2.LUC'!$I69 | F17: ='2.LUC'!$K69 | H17: =IF($E17 <> "Please select",INDEX(IPCC!$D$1520:$Y$1680,MATCH(clim_moist_cont,IPCC!$C$1520:$C$1680,0),MATCH($E17,IPCC!$D$1520:$Y$1520,0)),0) | I17: =IF('2.LUC'!AW69="",'2.LUC'!AV69,'2.LUC'!AW69) | J17: =IF($F17 <> "Please select", INDEX(IPCC!$D$682:$Y$845,MATCH(clim_moist_cont,IPCC!$C$682:$C$845,0),MATCH($F17,IPCC!$D$682:$Y$682,0)),0) | K17: =IF('2.LUC'!BE69="",'2.LUC'!BD69,'2.LUC'!BE69) | L17: =IF($E17<> "Please select", SOCref*INDEX(IPCC!$B$1687:$W$1698,MATCH(clim_moist, IPCC!$A$1687:$A$1698,0),MATCH($E17, IPCC!$B$1687:$W$1687,0)),0) | M17: =IF('2.LUC'!AZ69="",'2.LUC'!AY69,'2.LUC'!AZ69) | N17: =IF($F17<> "Please select",SOCref*INDEX(IPCC!$B$852:$W$863,MATCH(clim_moist, IPCC!$A$852:$A$863,0),MATCH($F17, IPCC!$B$852:$W$852,0)),0) | O17: =IF('2.LUC'!BH69="",'2.LUC'!BG69,'2.LUC'!BH69) | S17: CH4 | T17: =SUM(Q24:Q33) | U17: =SUM(R24:R33)
B18: 10 | C18: =IF('2.LUC'!$C70 = "", "", '2.LUC'!$C70) | D18: ='2.LUC'!$G70 | E18: ='2.LUC'!$I70 | F18: ='2.LUC'!$K70 | H18: =IF($E18 <> "Please select",INDEX(IPCC!$D$1520:$Y$1680,MATCH(clim_moist_cont,IPCC!$C$1520:$C$1680,0),MATCH($E18,IPCC!$D$1520:$Y$1520,0)),0) | I18: =IF('2.LUC'!AW70="",'2.LUC'!AV70,'2.LUC'!AW70) | J18: =IF($F18 <> "Please select", INDEX(IPCC!$D$682:$Y$845,MATCH(clim_moist_cont,IPCC!$C$682:$C$845,0),MATCH($F18,IPCC!$D$682:$Y$682,0)),0) | K18: =IF('2.LUC'!BE70="",'2.LUC'!BD70,'2.LUC'!BE70) | L18: =IF($E18<> "Please select", SOCref*INDEX(IPCC!$B$1687:$W$1698,MATCH(clim_moist, IPCC!$A$1687:$A$1698,0),MATCH($E18, IPCC!$B$1687:$W$1687,0)),0) | M18: =IF('2.LUC'!AZ70="",'2.LUC'!AY70,'2.LUC'!AZ70) | N18: =IF($F18<> "Please select",SOCref*INDEX(IPCC!$B$852:$W$863,MATCH(clim_moist, IPCC!$A$852:$A$863,0),MATCH($F18, IPCC!$B$852:$W$852,0)),0) | O18: =IF('2.LUC'!BH70="",'2.LUC'!BG70,'2.LUC'!BH70) | S18: N2O fire | T18: =SUM(S24:S33) | U18: =SUM(T24:T33)
F20: *limited to 20 yrs | G20: *limited to 20 yrs | H20: SOM mineralization due to LUC | J20: Fire | K20: Fire emissions | Q20: All period | W20: Soil Implementation phase alone | Y20: Area burnt
E21: ΔC | F21: ΔC | G21: ΔC | H21: FSOM | I21: soil N2O | J21: MB | K21: CH4 | L21: N2O | M21: CH4 | N21: N2O | O21: Total non-GHGs | Q21: CH4 | S21: N2O fire | U21: N2O soil | W21: time_tot= time and time_cap = 0
C22: Initial | D22: Final | E22: Biomass | F22: Mineral soil | G22: Mineral soil | H22: N mineralised in mineral soils due to LUC | J22: Initial LU | O22: fire + Fsom | Q22: w/out | R22: with | S22: w/out | T22: with | U22: w/out | V22: with | W22: w/out | X22: with | Y22: w/out | Z22: with
C23: LU | D23: LU | E23: tCO2/ha | F23: tCO2/ha/year | G23: tC/ha/year | H23: kg N mineralized/year | I23: kg N2O | J23: t dm/ha | K23: kg CH4 | L23: kg N2O | M23: kgCO2-e | N23: kCO2-e | O23: tCO2-e | Q23: tCO2-e | R23: tCO2-e | S23: tCO2-e | T23: tCO2-e | U23: tCO2-e | V23: tCO2-e | W23: tCO2-e | X23: tCO2-e | Y23: ha | Z23: ha
C24: =E9 | D24: =F9 | E24: =($K9-$I9)*(-44/12) | F24: =(($O9-$M9)/20)*(-44/12) | G24: =($O9-$M9)/20 | H24: =IF($G24>=0,0,IF($C24="Grassland",((-1)*(($G24*1/IPCC!$B$913)*1000)),((-1)*(($G24*1/IPCC!$B$914)*1000)))) | I24: =IF($E9="Please select", 0, $H24*VLOOKUP(moist_type, IPCC!$B$99:$C$101, 2, FALSE)*N2O_N_conversion) | J24: =IF($D9="YES", $I9*(1/0.4), 0) | K24: =IF('2.LUC'!$G61 = "YES", J24 *VLOOKUP('2.LUC'!$I61, IPCC!$A$1473:$E$1496, 2, FALSE) * VLOOKUP('2.LUC'!$I61, IPCC!$A$1473:$E$1496, 4, FALSE), 0) | L24: =IF('2.LUC'!$G61 = "YES", luc!$I9 * 2.5 *VLOOKUP('2.LUC'!$I61, IPCC!$A$1473:$E$1496, 2, FALSE) * VLOOKUP('2.LUC'!$I61, IPCC!$A$1473:$E$1496, 5, FALSE), 0) | M24: =K24*methane | N24: =($I24+$L24)*Nitrous | O24: =($N24+$M24)/1000 | Q24: =IF($D9="YES", $C41*$K24*methane/1000,0) | R24: =IF($D9="YES", $E41*$K24*methane/1000,0) | S24: =IF($D9="YES", $C41*$L24*Nitrous/1000,0) | T24: =IF($D9="YES", $E41*$L24*Nitrous/1000,0) | U24: =$C41*$I24*Nitrous/1000 | V24: =$E41*$I24*Nitrous/1000 | W24: =$F24*(IF(D41="Immediate",IF(C41>0,C41*MIN(20,time),0),C41*IF(time>time+20,20,IF(time<20,(time*VLOOKUP(D41, list!$J$48:$K$50,2,))+(time-time),((MIN(20,time)*VLOOKUP(D41, list!$J$48:$K$50,2,))+(time-MIN(20,time))-IF(D41="Exponential",time-20+0.217*time*(EXP(4.606*(20-time)/time)-1),((time-20)^2)*(0.5/time))))))) | X24: =$F24*(IF(F41="Immediate",IF(E41>0,E41*MIN(20,time),0),E41*IF(time>time+20,20,IF(time<20,(time*VLOOKUP(F41, list!$J$48:$K$50,2,))+(time-time),((MIN(20,time)*VLOOKUP(F41, list!$J$48:$K$50,2,))+(time-MIN(20,time))-IF(F41="Exponential",time-20+0.217*time*(EXP(4.606*(20-time)/time)-1),((time-20)^2)*(0.5/time))))))) | Y24: =IF($K24>0, $C41, 0) | Z24: =IF($K24>0, $E41, 0)
C25: =E10 | D25: =F10 | E25: =($K10-$I10)*(-44/12) | F25: =(($O10-$M10)/20)*(-44/12) | G25: =($O10-$M10)/20 | H25: =IF($G25>=0,0,IF($C25="Grassland",((-1)*(($G25*1/IPCC!$B$913)*1000)),((-1)*(($G25*1/IPCC!$B$914)*1000)))) | I25: =IF($E10="Please select", 0, $H25*VLOOKUP(moist_type, IPCC!$B$99:$C$101, 2, FALSE)*N2O_N_conversion) | J25: =IF($D10="YES", $I10*(1/0.4), 0) | K25: =IF('2.LUC'!$G62 = "YES", J25 *VLOOKUP('2.LUC'!$I62, IPCC!$A$1473:$E$1496, 2, FALSE) * VLOOKUP('2.LUC'!$I62, IPCC!$A$1473:$E$1496, 4, FALSE), 0) | L25: =IF('2.LUC'!$G62 = "YES", luc!$I10 * 2.5 *VLOOKUP('2.LUC'!$I62, IPCC!$A$1473:$E$1496, 2, FALSE) * VLOOKUP('2.LUC'!$I62, IPCC!$A$1473:$E$1496, 5, FALSE), 0) | M25: =K25*methane | N25: =($I25+$L25)*Nitrous | O25: =($N25+$M25)/1000 | Q25: =IF($D10="YES", $C42*$K25*methane/1000,0) | R25: =IF($D10="YES", $E42*$K25*methane/1000,0) | S25: =IF($D10="YES", $C42*$L25*Nitrous/1000,0) | T25: =IF($D10="YES", $E42*$L25*Nitrous/1000,0) | U25: =$C42*$I25*Nitrous/1000 | V25: =$E42*$I25*Nitrous/1000 | W25: =$F25*(IF(D42="Immediate",IF(C42>0,C42*MIN(20,time),0),C42*IF(time>time+20,20,IF(time<20,(time*VLOOKUP(D42, list!$J$48:$K$50,2,))+(time-time),((MIN(20,time)*VLOOKUP(D42, list!$J$48:$K$50,2,))+(time-MIN(20,time))-IF(D42="Exponential",time-20+0.217*time*(EXP(4.606*(20-time)/time)-1),((time-20)^2)*(0.5/time))))))) | X25: =$F25*(IF(F42="Immediate",IF(E42>0,E42*MIN(20,time),0),E42*IF(time>time+20,20,IF(time<20,(time*VLOOKUP(F42, list!$J$48:$K$50,2,))+(time-time),((MIN(20,time)*VLOOKUP(F42, list!$J$48:$K$50,2,))+(time-MIN(20,time))-IF(F42="Exponential",time-20+0.217*time*(EXP(4.606*(20-time)/time)-1),((time-20)^2)*(0.5/time))))))) | Y25: =IF($K25>0, $C42, 0) | Z25: =IF($K25>0, $E42, 0)
C26: =E11 | D26: =F11 | E26: =($K11-$I11)*(-44/12) | F26: =(($O11-$M11)/20)*(-44/12) | G26: =($O11-$M11)/20 | H26: =IF($G26>=0,0,IF($C26="Grassland",((-1)*(($G26*1/IPCC!$B$913)*1000)),((-1)*(($G26*1/IPCC!$B$914)*1000)))) | I26: =IF($E11="Please select", 0, $H26*VLOOKUP(moist_type, IPCC!$B$99:$C$101, 2, FALSE)*N2O_N_conversion) | J26: =IF($D11="YES", $I11*(1/0.4), 0) | K26: =IF('2.LUC'!$G63 = "YES", J26 *VLOOKUP('2.LUC'!$I63, IPCC!$A$1473:$E$1496, 2, FALSE) * VLOOKUP('2.LUC'!$I63, IPCC!$A$1473:$E$1496, 4, FALSE), 0) | L26: =IF('2.LUC'!$G63 = "YES", luc!$I11 * 2.5 *VLOOKUP('2.LUC'!$I63, IPCC!$A$1473:$E$1496, 2, FALSE) * VLOOKUP('2.LUC'!$I63, IPCC!$A$1473:$E$1496, 5, FALSE), 0) | M26: =K26*methane | N26: =($I26+$L26)*Nitrous | O26: =($N26+$M26)/1000 | Q26: =IF($D11="YES", $C43*$K26*methane/1000,0) | R26: =IF($D11="YES", $E43*$K26*methane/1000,0) | S26: =IF($D11="YES", $C43*$L26*Nitrous/1000,0) | T26: =IF($D11="YES", $E43*$L26*Nitrous/1000,0) | U26: =$C43*$I26*Nitrous/1000 | V26: =$E43*$I26*Nitrous/1000 | W26: =$F26*(IF(D43="Immediate",IF(C43>0,C43*MIN(20,time),0),C43*IF(time>time+20,20,IF(time<20,(time*VLOOKUP(D43, list!$J$48:$K$50,2,))+(time-time),((MIN(20,time)*VLOOKUP(D43, list!$J$48:$K$50,2,))+(time-MIN(20,time))-IF(D43="Exponential",time-20+0.217*time*(EXP(4.606*(20-time)/time)-1),((time-20)^2)*(0.5/time))))))) | X26: =$F26*(IF(F43="Immediate",IF(E43>0,E43*MIN(20,time),0),E43*IF(time>time+20,20,IF(time<20,(time*VLOOKUP(F43, list!$J$48:$K$50,2,))+(time-time),((MIN(20,time)*VLOOKUP(F43, list!$J$48:$K$50,2,))+(time-MIN(20,time))-IF(F43="Exponential",time-20+0.217*time*(EXP(4.606*(20-time)/time)-1),((time-20)^2)*(0.5/time))))))) | Y26: =IF($K26>0, $C43, 0) | Z26: =IF($K26>0, $E43, 0)
C27: =E12 | D27: =F12 | E27: =($K12-$I12)*(-44/12) | F27: =(($O12-$M12)/20)*(-44/12) | G27: =($O12-$M12)/20 | H27: =IF($G27>=0,0,IF($C27="Grassland",((-1)*(($G27*1/IPCC!$B$913)*1000)),((-1)*(($G27*1/IPCC!$B$914)*1000)))) | I27: =IF($E12="Please select", 0, $H27*VLOOKUP(moist_type, IPCC!$B$99:$C$101, 2, FALSE)*N2O_N_conversion) | J27: =IF($D12="YES", $I12*(1/0.4), 0) | K27: =IF('2.LUC'!$G64 = "YES", J27 *VLOOKUP('2.LUC'!$I64, IPCC!$A$1473:$E$1496, 2, FALSE) * VLOOKUP('2.LUC'!$I64, IPCC!$A$1473:$E$1496, 4, FALSE), 0) | L27: =IF('2.LUC'!$G64 = "YES", luc!$I12 * 2.5 *VLOOKUP('2.LUC'!$I64, IPCC!$A$1473:$E$1496, 2, FALSE) * VLOOKUP('2.LUC'!$I64, IPCC!$A$1473:$E$1496, 5, FALSE), 0) | M27: =K27*methane | N27: =($I27+$L27)*Nitrous | O27: =($N27+$M27)/1000 | Q27: =IF($D12="YES", $C44*$K27*methane/1000,0) | R27: =IF($D12="YES", $E44*$K27*methane/1000,0) | S27: =IF($D12="YES", $C44*$L27*Nitrous/1000,0) | T27: =IF($D12="YES", $E44*$L27*Nitrous/1000,0) | U27: =$C44*$I27*Nitrous/1000 | V27: =$E44*$I27*Nitrous/1000 | W27: =$F27*(IF(D44="Immediate",IF(C44>0,C44*MIN(20,time),0),C44*IF(time>time+20,20,IF(time<20,(time*VLOOKUP(D44, list!$J$48:$K$50,2,))+(time-time),((MIN(20,time)*VLOOKUP(D44, list!$J$48:$K$50,2,))+(time-MIN(20,time))-IF(D44="Exponential",time-20+0.217*time*(EXP(4.606*(20-time)/time)-1),((time-20)^2)*(0.5/time))))))) | X27: =$F27*(IF(F44="Immediate",IF(E44>0,E44*MIN(20,time),0),E44*IF(time>time+20,20,IF(time<20,(time*VLOOKUP(F44, list!$J$48:$K$50,2,))+(time-time),((MIN(20,time)*VLOOKUP(F44, list!$J$48:$K$50,2,))+(time-MIN(20,time))-IF(F44="Exponential",time-20+0.217*time*(EXP(4.606*(20-time)/time)-1),((time-20)^2)*(0.5/time))))))) | Y27: =IF($K27>0, $C44, 0) | Z27: =IF($K27>0, $E44, 0)
C28: =E13 | D28: =F13 | E28: =($K13-$I13)*(-44/12) | F28: =(($O13-$M13)/20)*(-44/12) | G28: =($O13-$M13)/20 | H28: =IF($G28>=0,0,IF($C28="Grassland",((-1)*(($G28*1/IPCC!$B$913)*1000)),((-1)*(($G28*1/IPCC!$B$914)*1000)))) | I28: =IF($E13="Please select", 0, $H28*VLOOKUP(moist_type, IPCC!$B$99:$C$101, 2, FALSE)*N2O_N_conversion) | J28: =IF($D13="YES", $I13*(1/0.4), 0) | K28: =IF('2.LUC'!$G65 = "YES", J28 *VLOOKUP('2.LUC'!$I65, IPCC!$A$1473:$E$1496, 2, FALSE) * VLOOKUP('2.LUC'!$I65, IPCC!$A$1473:$E$1496, 4, FALSE), 0) | L28: =IF('2.LUC'!$G65 = "YES", luc!$I13 * 2.5 *VLOOKUP('2.LUC'!$I65, IPCC!$A$1473:$E$1496, 2, FALSE) * VLOOKUP('2.LUC'!$I65, IPCC!$A$1473:$E$1496, 5, FALSE), 0) | M28: =K28*methane | N28: =($I28+$L28)*Nitrous | O28: =($N28+$M28)/1000 | Q28: =IF($D13="YES", $C45*$K28*methane/1000,0) | R28: =IF($D13="YES", $E45*$K28*methane/1000,0) | S28: =IF($D13="YES", $C45*$L28*Nitrous/1000,0) | T28: =IF($D13="YES", $E45*$L28*Nitrous/1000,0) | U28: =$C45*$I28*Nitrous/1000 | V28: =$E45*$I28*Nitrous/1000 | W28: =$F28*(IF(D45="Immediate",IF(C45>0,C45*MIN(20,time),0),C45*IF(time>time+20,20,IF(time<20,(time*VLOOKUP(D45, list!$J$48:$K$50,2,))+(time-time),((MIN(20,time)*VLOOKUP(D45, list!$J$48:$K$50,2,))+(time-MIN(20,time))-IF(D45="Exponential",time-20+0.217*time*(EXP(4.606*(20-time)/time)-1),((time-20)^2)*(0.5/time))))))) | X28: =$F28*(IF(F45="Immediate",IF(E45>0,E45*MIN(20,time),0),E45*IF(time>time+20,20,IF(time<20,(time*VLOOKUP(F45, list!$J$48:$K$50,2,))+(time-time),((MIN(20,time)*VLOOKUP(F45, list!$J$48:$K$50,2,))+(time-MIN(20,time))-IF(F45="Exponential",time-20+0.217*time*(EXP(4.606*(20-time)/time)-1),((time-20)^2)*(0.5/time))))))) | Y28: =IF($K28>0, $C45, 0) | Z28: =IF($K28>0, $E45, 0)
C29: =E14 | D29: =F14 | E29: =($K14-$I14)*(-44/12) | F29: =(($O14-$M14)/20)*(-44/12) | G29: =($O14-$M14)/20 | H29: =IF($G29>=0,0,IF($C29="Grassland",((-1)*(($G29*1/IPCC!$B$913)*1000)),((-1)*(($G29*1/IPCC!$B$914)*1000)))) | I29: =IF($E14="Please select", 0, $H29*VLOOKUP(moist_type, IPCC!$B$99:$C$101, 2, FALSE)*N2O_N_conversion) | J29: =IF($D14="YES", $I14*(1/0.4), 0) | K29: =IF('2.LUC'!$G66 = "YES", J29 *VLOOKUP('2.LUC'!$I66, IPCC!$A$1473:$E$1496, 2, FALSE) * VLOOKUP('2.LUC'!$I66, IPCC!$A$1473:$E$1496, 4, FALSE), 0) | L29: =IF('2.LUC'!$G66 = "YES", luc!$I14 * 2.5 *VLOOKUP('2.LUC'!$I66, IPCC!$A$1473:$E$1496, 2, FALSE) * VLOOKUP('2.LUC'!$I66, IPCC!$A$1473:$E$1496, 5, FALSE), 0) | M29: =K29*methane | N29: =($I29+$L29)*Nitrous | O29: =($N29+$M29)/1000 | Q29: =IF($D14="YES", $C46*$K29*methane/1000,0) | R29: =IF($D14="YES", $E46*$K29*methane/1000,0) | S29: =IF($D14="YES", $C46*$L29*Nitrous/1000,0) | T29: =IF($D14="YES", $E46*$L29*Nitrous/1000,0) | U29: =$C46*$I29*Nitrous/1000 | V29: =$E46*$I29*Nitrous/1000 | W29: =$F29*(IF(D46="Immediate",IF(C46>0,C46*MIN(20,time),0),C46*IF(time>time+20,20,IF(time<20,(time*VLOOKUP(D46, list!$J$48:$K$50,2,))+(time-time),((MIN(20,time)*VLOOKUP(D46, list!$J$48:$K$50,2,))+(time-MIN(20,time))-IF(D46="Exponential",time-20+0.217*time*(EXP(4.606*(20-time)/time)-1),((time-20)^2)*(0.5/time))))))) | X29: =$F29*(IF(F46="Immediate",IF(E46>0,E46*MIN(20,time),0),E46*IF(time>time+20,20,IF(time<20,(time*VLOOKUP(F46, list!$J$48:$K$50,2,))+(time-time),((MIN(20,time)*VLOOKUP(F46, list!$J$48:$K$50,2,))+(time-MIN(20,time))-IF(F46="Exponential",time-20+0.217*time*(EXP(4.606*(20-time)/time)-1),((time-20)^2)*(0.5/time))))))) | Y29: =IF($K29>0, $C46, 0) | Z29: =IF($K29>0, $E46, 0)
C30: =E15 | D30: =F15 | E30: =($K15-$I15)*(-44/12) | F30: =(($O15-$M15)/20)*(-44/12) | G30: =($O15-$M15)/20 | H30: =IF($G30>=0,0,IF($C30="Grassland",((-1)*(($G30*1/IPCC!$B$913)*1000)),((-1)*(($G30*1/IPCC!$B$914)*1000)))) | I30: =IF($E15="Please select", 0, $H30*VLOOKUP(moist_type, IPCC!$B$99:$C$101, 2, FALSE)*N2O_N_conversion) | J30: =IF($D15="YES", $I15*(1/0.4), 0) | K30: =IF('2.LUC'!$G67 = "YES", J30 *VLOOKUP('2.LUC'!$I67, IPCC!$A$1473:$E$1496, 2, FALSE) * VLOOKUP('2.LUC'!$I67, IPCC!$A$1473:$E$1496, 4, FALSE), 0) | L30: =IF('2.LUC'!$G67 = "YES", luc!$I15 * 2.5 *VLOOKUP('2.LUC'!$I67, IPCC!$A$1473:$E$1496, 2, FALSE) * VLOOKUP('2.LUC'!$I67, IPCC!$A$1473:$E$1496, 5, FALSE), 0) | M30: =K30*methane | N30: =($I30+$L30)*Nitrous | O30: =($N30+$M30)/1000 | Q30: =IF($D15="YES", $C47*$K30*methane/1000,0) | R30: =IF($D15="YES", $E47*$K30*methane/1000,0) | S30: =IF($D15="YES", $C47*$L30*Nitrous/1000,0) | T30: =IF($D15="YES", $E47*$L30*Nitrous/1000,0) | U30: =$C47*$I30*Nitrous/1000 | V30: =$E47*$I30*Nitrous/1000 | W30: =$F30*(IF(D47="Immediate",IF(C47>0,C47*MIN(20,time),0),C47*IF(time>time+20,20,IF(time<20,(time*VLOOKUP(D47, list!$J$48:$K$50,2,))+(time-time),((MIN(20,time)*VLOOKUP(D47, list!$J$48:$K$50,2,))+(time-MIN(20,time))-IF(D47="Exponential",time-20+0.217*time*(EXP(4.606*(20-time)/time)-1),((time-20)^2)*(0.5/time))))))) | X30: =$F30*(IF(F47="Immediate",IF(E47>0,E47*MIN(20,time),0),E47*IF(time>time+20,20,IF(time<20,(time*VLOOKUP(F47, list!$J$48:$K$50,2,))+(time-time),((MIN(20,time)*VLOOKUP(F47, list!$J$48:$K$50,2,))+(time-MIN(20,time))-IF(F47="Exponential",time-20+0.217*time*(EXP(4.606*(20-time)/time)-1),((time-20)^2)*(0.5/time))))))) | Y30: =IF($K30>0, $C47, 0) | Z30: =IF($K30>0, $E47, 0)
C31: =E16 | D31: =F16 | E31: =($K16-$I16)*(-44/12) | F31: =(($O16-$M16)/20)*(-44/12) | G31: =($O16-$M16)/20 | H31: =IF($G31>=0,0,IF($C31="Grassland",((-1)*(($G31*1/IPCC!$B$913)*1000)),((-1)*(($G31*1/IPCC!$B$914)*1000)))) | I31: =IF($E16="Please select", 0, $H31*VLOOKUP(moist_type, IPCC!$B$99:$C$101, 2, FALSE)*N2O_N_conversion) | J31: =IF($D16="YES", $I16*(1/0.4), 0) | K31: =IF('2.LUC'!$G68 = "YES", J31 *VLOOKUP('2.LUC'!$I68, IPCC!$A$1473:$E$1496, 2, FALSE) * VLOOKUP('2.LUC'!$I68, IPCC!$A$1473:$E$1496, 4, FALSE), 0) | L31: =IF('2.LUC'!$G68 = "YES", luc!$I16 * 2.5 *VLOOKUP('2.LUC'!$I68, IPCC!$A$1473:$E$1496, 2, FALSE) * VLOOKUP('2.LUC'!$I68, IPCC!$A$1473:$E$1496, 5, FALSE), 0) | M31: =K31*methane | N31: =($I31+$L31)*Nitrous | O31: =($N31+$M31)/1000 | Q31: =IF($D16="YES", $C48*$K31*methane/1000,0) | R31: =IF($D16="YES", $E48*$K31*methane/1000,0) | S31: =IF($D16="YES", $C48*$L31*Nitrous/1000,0) | T31: =IF($D16="YES", $E48*$L31*Nitrous/1000,0) | U31: =$C48*$I31*Nitrous/1000 | V31: =$E48*$I31*Nitrous/1000 | W31: =$F31*(IF(D48="Immediate",IF(C48>0,C48*MIN(20,time),0),C48*IF(time>time+20,20,IF(time<20,(time*VLOOKUP(D48, list!$J$48:$K$50,2,))+(time-time),((MIN(20,time)*VLOOKUP(D48, list!$J$48:$K$50,2,))+(time-MIN(20,time))-IF(D48="Exponential",time-20+0.217*time*(EXP(4.606*(20-time)/time)-1),((time-20)^2)*(0.5/time))))))) | X31: =$F31*(IF(F48="Immediate",IF(E48>0,E48*MIN(20,time),0),E48*IF(time>time+20,20,IF(time<20,(time*VLOOKUP(F48, list!$J$48:$K$50,2,))+(time-time),((MIN(20,time)*VLOOKUP(F48, list!$J$48:$K$50,2,))+(time-MIN(20,time))-IF(F48="Exponential",time-20+0.217*time*(EXP(4.606*(20-time)/time)-1),((time-20)^2)*(0.5/time))))))) | Y31: =IF($K31>0, $C48, 0) | Z31: =IF($K31>0, $E48, 0)
C32: =E17 | D32: =F17 | E32: =($K17-$I17)*(-44/12) | F32: =(($O17-$M17)/20)*(-44/12) | G32: =($O17-$M17)/20 | H32: =IF($G32>=0,0,IF($C32="Grassland",((-1)*(($G32*1/IPCC!$B$913)*1000)),((-1)*(($G32*1/IPCC!$B$914)*1000)))) | I32: =IF($E17="Please select", 0, $H32*VLOOKUP(moist_type, IPCC!$B$99:$C$101, 2, FALSE)*N2O_N_conversion) | J32: =IF($D17="YES", $I17*(1/0.4), 0) | K32: =IF('2.LUC'!$G69 = "YES", J32 *VLOOKUP('2.LUC'!$I69, IPCC!$A$1473:$E$1496, 2, FALSE) * VLOOKUP('2.LUC'!$I69, IPCC!$A$1473:$E$1496, 4, FALSE), 0) | L32: =IF('2.LUC'!$G69 = "YES", luc!$I17 * 2.5 *VLOOKUP('2.LUC'!$I69, IPCC!$A$1473:$E$1496, 2, FALSE) * VLOOKUP('2.LUC'!$I69, IPCC!$A$1473:$E$1496, 5, FALSE), 0) | M32: =K32*methane | N32: =($I32+$L32)*Nitrous | O32: =($N32+$M32)/1000 | Q32: =IF($D17="YES", $C49*$K32*methane/1000,0) | R32: =IF($D17="YES", $E49*$K32*methane/1000,0) | S32: =IF($D17="YES", $C49*$L32*Nitrous/1000,0) | T32: =IF($D17="YES", $E49*$L32*Nitrous/1000,0) | U32: =$C49*$I32*Nitrous/1000 | V32: =$E49*$I32*Nitrous/1000 | W32: =$F32*(IF(D49="Immediate",IF(C49>0,C49*MIN(20,time),0),C49*IF(time>time+20,20,IF(time<20,(time*VLOOKUP(D49, list!$J$48:$K$50,2,))+(time-time),((MIN(20,time)*VLOOKUP(D49, list!$J$48:$K$50,2,))+(time-MIN(20,time))-IF(D49="Exponential",time-20+0.217*time*(EXP(4.606*(20-time)/time)-1),((time-20)^2)*(0.5/time))))))) | X32: =$F32*(IF(F49="Immediate",IF(E49>0,E49*MIN(20,time),0),E49*IF(time>time+20,20,IF(time<20,(time*VLOOKUP(F49, list!$J$48:$K$50,2,))+(time-time),((MIN(20,time)*VLOOKUP(F49, list!$J$48:$K$50,2,))+(time-MIN(20,time))-IF(F49="Exponential",time-20+0.217*time*(EXP(4.606*(20-time)/time)-1),((time-20)^2)*(0.5/time))))))) | Y32: =IF($K32>0, $C49, 0) | Z32: =IF($K32>0, $E49, 0)
C33: =E18 | D33: =F18 | E33: =($K18-$I18)*(-44/12) | F33: =(($O18-$M18)/20)*(-44/12) | G33: =($O18-$M18)/20 | H33: =IF($G33>=0,0,IF($C33="Grassland",((-1)*(($G33*1/IPCC!$B$913)*1000)),((-1)*(($G33*1/IPCC!$B$914)*1000)))) | I33: =IF($E18="Please select", 0, $H33*VLOOKUP(moist_type, IPCC!$B$99:$C$101, 2, FALSE)*N2O_N_conversion) | J33: =IF($D18="YES", $I18*(1/0.4), 0) | K33: =IF('2.LUC'!$G70 = "YES", J33 *VLOOKUP('2.LUC'!$I70, IPCC!$A$1473:$E$1496, 2, FALSE) * VLOOKUP('2.LUC'!$I70, IPCC!$A$1473:$E$1496, 4, FALSE), 0) | L33: =IF('2.LUC'!$G70 = "YES", luc!$I18 * 2.5 *VLOOKUP('2.LUC'!$I70, IPCC!$A$1473:$E$1496, 2, FALSE) * VLOOKUP('2.LUC'!$I70, IPCC!$A$1473:$E$1496, 5, FALSE), 0) | M33: =K33*methane | N33: =($I33+$L33)*Nitrous | O33: =($N33+$M33)/1000 | Q33: =IF($D18="YES", $C50*$K33*methane/1000,0) | R33: =IF($D18="YES", $E50*$K33*methane/1000,0) | S33: =IF($D18="YES", $C50*$L33*Nitrous/1000,0) | T33: =IF($D18="YES", $E50*$L33*Nitrous/1000,0) | U33: =$C50*$I33*Nitrous/1000 | V33: =$E50*$I33*Nitrous/1000 | W33: =$F33*(IF(D50="Immediate",IF(C50>0,C50*MIN(20,time),0),C50*IF(time>time+20,20,IF(time<20,(time*VLOOKUP(D50, list!$J$48:$K$50,2,))+(time-time),((MIN(20,time)*VLOOKUP(D50, list!$J$48:$K$50,2,))+(time-MIN(20,time))-IF(D50="Exponential",time-20+0.217*time*(EXP(4.606*(20-time)/time)-1),((time-20)^2)*(0.5/time))))))) | X33: =$F33*(IF(F50="Immediate",IF(E50>0,E50*MIN(20,time),0),E50*IF(time>time+20,20,IF(time<20,(time*VLOOKUP(F50, list!$J$48:$K$50,2,))+(time-time),((MIN(20,time)*VLOOKUP(F50, list!$J$48:$K$50,2,))+(time-MIN(20,time))-IF(F50="Exponential",time-20+0.217*time*(EXP(4.606*(20-time)/time)-1),((time-20)^2)*(0.5/time))))))) | Y33: =IF($K33>0, $C50, 0) | Z33: =IF($K33>0, $E50, 0)
Y34: =SUM(Y24:Y33) | Z34: =SUM(Z24:Z33)
B37: GHG emissions
C38: Area associated with non-forest LU changes | G38: Biomass Change | I38: SOC Change | K38: Emissions from Fire + N mineralised | M38: Total Balance | O38: Balance
C39: Without Project | E39: With Project | G39: Without Project | H39: With Project | I39: Without Project | J39: With Project | K39: Without Project | L39: With Project | M39: Without Project | N39: With Project
B40: SI | C40: Area (ha) | D40: Rate | E40: Area (ha) | F40: Rate | G40: tCO2 | H40: tCO2 | I40: tCO2 | J40: tCO2 | K40: tCO2 | L40: tCO2 | M40: tCO2 | N40: tCO2 | O40: tCO2
B41: 1 | C41: ='2.LUC'!$N61 | D41: =VLOOKUP('2.LUC'!$O61, list!$I$48:$J$50,2,FALSE ) | E41: ='2.LUC'!$P61 | F41: =VLOOKUP('2.LUC'!$Q61, list!$I$48:$J$50,2,FALSE ) | G41: =$C41*$E24 | H41: =$E41*$E24 | I41: =IF(ABS($F24*(IF(D41="Immediate",IF(C41>0,C41*MIN(20,time_tot),0),C41*IF(time_tot>time+20,20,IF(time_tot<20,(time*VLOOKUP(D41, list!$J$48:$K$50,2,))+(time_tot-time),((MIN(20,time)*VLOOKUP(D41, list!$J$48:$K$50,2,))+(time_tot-MIN(20,time))-IF(D41="Exponential",time_tot-20+0.217*time*(EXP(4.606*(20-time_tot)/time)-1),((time_tot-20)^2)*(0.5/time))))))))>=ABS(F24*C41*20),F24*C41*20,$F24*(IF(D41="Immediate",IF(C41>0,C41*MIN(20,time_tot),0),C41*IF(time_tot>time+20,20,IF(time_tot<20,(time*VLOOKUP(D41, list!$J$48:$K$50,2,))+(time_tot-time),((MIN(20,time)*VLOOKUP(D41, list!$J$48:$K$50,2,))+(time_tot-MIN(20,time))-IF(D41="Exponential",time_tot-20+0.217*time*(EXP(4.606*(20-time_tot)/time)-1),((time_tot-20)^2)*(0.5/time)))))))) | J41: =IF(ABS($F24*(IF(F41="Immediate",IF(E41>0,E41*MIN(20,time_tot),0),E41*IF(time_tot>time+20,20,IF(time_tot<20,(time*VLOOKUP(F41, list!$J$48:$K$50,2,))+(time_tot-time),((MIN(20,time)*VLOOKUP(F41, list!$J$48:$K$50,2,))+(time_tot-MIN(20,time))-IF(F41="Exponential",time_tot-20+0.217*time*(EXP(4.606*(20-time_tot)/time)-1),((time_tot-20)^2)*(0.5/time))))))))>=ABS(F24*E41*20),F24*E41*20,$F24*(IF(F41="Immediate",IF(E41>0,E41*MIN(20,time_tot),0),E41*IF(time_tot>time+20,20,IF(time_tot<20,(time*VLOOKUP(F41, list!$J$48:$K$50,2,))+(time_tot-time),((MIN(20,time)*VLOOKUP(F41, list!$J$48:$K$50,2,))+(time_tot-MIN(20,time))-IF(F41="Exponential",time_tot-20+0.217*time*(EXP(4.606*(20-time_tot)/time)-1),((time_tot-20)^2)*(0.5/time)))))))) | K41: =$C41*$O24 | L41: =$E41*$O24 | M41: =$G41+$I41+$K41 | N41: =H41+J41+L41 | O41: =$N41-$M41
B42: 2 | C42: ='2.LUC'!$N62 | D42: =VLOOKUP('2.LUC'!$O62, list!$I$48:$J$50,2,FALSE ) | E42: ='2.LUC'!$P62 | F42: =VLOOKUP('2.LUC'!$Q62, list!$I$48:$J$50,2,FALSE ) | G42: =$C42*$E25 | H42: =$E42*$E25 | I42: =IF(ABS($F25*(IF(D42="Immediate",IF(C42>0,C42*MIN(20,time_tot),0),C42*IF(time_tot>time+20,20,IF(time_tot<20,(time*VLOOKUP(D42, list!$J$48:$K$50,2,))+(time_tot-time),((MIN(20,time)*VLOOKUP(D42, list!$J$48:$K$50,2,))+(time_tot-MIN(20,time))-IF(D42="Exponential",time_tot-20+0.217*time*(EXP(4.606*(20-time_tot)/time)-1),((time_tot-20)^2)*(0.5/time))))))))>=ABS(F25*C42*20),F25*C42*20,$F25*(IF(D42="Immediate",IF(C42>0,C42*MIN(20,time_tot),0),C42*IF(time_tot>time+20,20,IF(time_tot<20,(time*VLOOKUP(D42, list!$J$48:$K$50,2,))+(time_tot-time),((MIN(20,time)*VLOOKUP(D42, list!$J$48:$K$50,2,))+(time_tot-MIN(20,time))-IF(D42="Exponential",time_tot-20+0.217*time*(EXP(4.606*(20-time_tot)/time)-1),((time_tot-20)^2)*(0.5/time)))))))) | J42: =IF(ABS($F25*(IF(F42="Immediate",IF(E42>0,E42*MIN(20,time_tot),0),E42*IF(time_tot>time+20,20,IF(time_tot<20,(time*VLOOKUP(F42, list!$J$48:$K$50,2,))+(time_tot-time),((MIN(20,time)*VLOOKUP(F42, list!$J$48:$K$50,2,))+(time_tot-MIN(20,time))-IF(F42="Exponential",time_tot-20+0.217*time*(EXP(4.606*(20-time_tot)/time)-1),((time_tot-20)^2)*(0.5/time))))))))>=ABS(F25*E42*20),F25*E42*20,$F25*(IF(F42="Immediate",IF(E42>0,E42*MIN(20,time_tot),0),E42*IF(time_tot>time+20,20,IF(time_tot<20,(time*VLOOKUP(F42, list!$J$48:$K$50,2,))+(time_tot-time),((MIN(20,time)*VLOOKUP(F42, list!$J$48:$K$50,2,))+(time_tot-MIN(20,time))-IF(F42="Exponential",time_tot-20+0.217*time*(EXP(4.606*(20-time_tot)/time)-1),((time_tot-20)^2)*(0.5/time)))))))) | K42: =$C42*$O25 | L42: =$E42*$O25 | M42: =$G42+$I42+$K42 | N42: =H42+J42+L42 | O42: =$N42-$M42
B43: 3 | C43: ='2.LUC'!$N63 | D43: =VLOOKUP('2.LUC'!$O63, list!$I$48:$J$50,2,FALSE ) | E43: ='2.LUC'!$P63 | F43: =VLOOKUP('2.LUC'!$Q63, list!$I$48:$J$50,2,FALSE ) | G43: =$C43*$E26 | H43: =$E43*$E26 | I43: =IF(ABS($F26*(IF(D43="Immediate",IF(C43>0,C43*MIN(20,time_tot),0),C43*IF(time_tot>time+20,20,IF(time_tot<20,(time*VLOOKUP(D43, list!$J$48:$K$50,2,))+(time_tot-time),((MIN(20,time)*VLOOKUP(D43, list!$J$48:$K$50,2,))+(time_tot-MIN(20,time))-IF(D43="Exponential",time_tot-20+0.217*time*(EXP(4.606*(20-time_tot)/time)-1),((time_tot-20)^2)*(0.5/time))))))))>=ABS(F26*C43*20),F26*C43*20,$F26*(IF(D43="Immediate",IF(C43>0,C43*MIN(20,time_tot),0),C43*IF(time_tot>time+20,20,IF(time_tot<20,(time*VLOOKUP(D43, list!$J$48:$K$50,2,))+(time_tot-time),((MIN(20,time)*VLOOKUP(D43, list!$J$48:$K$50,2,))+(time_tot-MIN(20,time))-IF(D43="Exponential",time_tot-20+0.217*time*(EXP(4.606*(20-time_tot)/time)-1),((time_tot-20)^2)*(0.5/time)))))))) | J43: =IF(ABS($F26*(IF(F43="Immediate",IF(E43>0,E43*MIN(20,time_tot),0),E43*IF(time_tot>time+20,20,IF(time_tot<20,(time*VLOOKUP(F43, list!$J$48:$K$50,2,))+(time_tot-time),((MIN(20,time)*VLOOKUP(F43, list!$J$48:$K$50,2,))+(time_tot-MIN(20,time))-IF(F43="Exponential",time_tot-20+0.217*time*(EXP(4.606*(20-time_tot)/time)-1),((time_tot-20)^2)*(0.5/time))))))))>=ABS(F26*E43*20),F26*E43*20,$F26*(IF(F43="Immediate",IF(E43>0,E43*MIN(20,time_tot),0),E43*IF(time_tot>time+20,20,IF(time_tot<20,(time*VLOOKUP(F43, list!$J$48:$K$50,2,))+(time_tot-time),((MIN(20,time)*VLOOKUP(F43, list!$J$48:$K$50,2,))+(time_tot-MIN(20,time))-IF(F43="Exponential",time_tot-20+0.217*time*(EXP(4.606*(20-time_tot)/time)-1),((time_tot-20)^2)*(0.5/time)))))))) | K43: =$C43*$O26 | L43: =$E43*$O26 | M43: =$G43+$I43+$K43 | N43: =H43+J43+L43 | O43: =$N43-$M43
B44: 4 | C44: ='2.LUC'!$N64 | D44: =VLOOKUP('2.LUC'!$O64, list!$I$48:$J$50,2,FALSE ) | E44: ='2.LUC'!$P64 | F44: =VLOOKUP('2.LUC'!$Q64, list!$I$48:$J$50,2,FALSE ) | G44: =$C44*$E27 | H44: =$E44*$E27 | I44: =IF(ABS($F27*(IF(D44="Immediate",IF(C44>0,C44*MIN(20,time_tot),0),C44*IF(time_tot>time+20,20,IF(time_tot<20,(time*VLOOKUP(D44, list!$J$48:$K$50,2,))+(time_tot-time),((MIN(20,time)*VLOOKUP(D44, list!$J$48:$K$50,2,))+(time_tot-MIN(20,time))-IF(D44="Exponential",time_tot-20+0.217*time*(EXP(4.606*(20-time_tot)/time)-1),((time_tot-20)^2)*(0.5/time))))))))>=ABS(F27*C44*20),F27*C44*20,$F27*(IF(D44="Immediate",IF(C44>0,C44*MIN(20,time_tot),0),C44*IF(time_tot>time+20,20,IF(time_tot<20,(time*VLOOKUP(D44, list!$J$48:$K$50,2,))+(time_tot-time),((MIN(20,time)*VLOOKUP(D44, list!$J$48:$K$50,2,))+(time_tot-MIN(20,time))-IF(D44="Exponential",time_tot-20+0.217*time*(EXP(4.606*(20-time_tot)/time)-1),((time_tot-20)^2)*(0.5/time)))))))) | J44: =IF(ABS($F27*(IF(F44="Immediate",IF(E44>0,E44*MIN(20,time_tot),0),E44*IF(time_tot>time+20,20,IF(time_tot<20,(time*VLOOKUP(F44, list!$J$48:$K$50,2,))+(time_tot-time),((MIN(20,time)*VLOOKUP(F44, list!$J$48:$K$50,2,))+(time_tot-MIN(20,time))-IF(F44="Exponential",time_tot-20+0.217*time*(EXP(4.606*(20-time_tot)/time)-1),((time_tot-20)^2)*(0.5/time))))))))>=ABS(F27*E44*20),F27*E44*20,$F27*(IF(F44="Immediate",IF(E44>0,E44*MIN(20,time_tot),0),E44*IF(time_tot>time+20,20,IF(time_tot<20,(time*VLOOKUP(F44, list!$J$48:$K$50,2,))+(time_tot-time),((MIN(20,time)*VLOOKUP(F44, list!$J$48:$K$50,2,))+(time_tot-MIN(20,time))-IF(F44="Exponential",time_tot-20+0.217*time*(EXP(4.606*(20-time_tot)/time)-1),((time_tot-20)^2)*(0.5/time)))))))) | K44: =$C44*$O27 | L44: =$E44*$O27 | M44: =$G44+$I44+$K44 | N44: =H44+J44+L44 | O44: =$N44-$M44
B45: 5 | C45: ='2.LUC'!$N65 | D45: =VLOOKUP('2.LUC'!$O65, list!$I$48:$J$50,2,FALSE ) | E45: ='2.LUC'!$P65 | F45: =VLOOKUP('2.LUC'!$Q65, list!$I$48:$J$50,2,FALSE ) | G45: =$C45*$E28 | H45: =$E45*$E28 | I45: =IF(ABS($F28*(IF(D45="Immediate",IF(C45>0,C45*MIN(20,time_tot),0),C45*IF(time_tot>time+20,20,IF(time_tot<20,(time*VLOOKUP(D45, list!$J$48:$K$50,2,))+(time_tot-time),((MIN(20,time)*VLOOKUP(D45, list!$J$48:$K$50,2,))+(time_tot-MIN(20,time))-IF(D45="Exponential",time_tot-20+0.217*time*(EXP(4.606*(20-time_tot)/time)-1),((time_tot-20)^2)*(0.5/time))))))))>=ABS(F28*C45*20),F28*C45*20,$F28*(IF(D45="Immediate",IF(C45>0,C45*MIN(20,time_tot),0),C45*IF(time_tot>time+20,20,IF(time_tot<20,(time*VLOOKUP(D45, list!$J$48:$K$50,2,))+(time_tot-time),((MIN(20,time)*VLOOKUP(D45, list!$J$48:$K$50,2,))+(time_tot-MIN(20,time))-IF(D45="Exponential",time_tot-20+0.217*time*(EXP(4.606*(20-time_tot)/time)-1),((time_tot-20)^2)*(0.5/time)))))))) | J45: =IF(ABS($F28*(IF(F45="Immediate",IF(E45>0,E45*MIN(20,time_tot),0),E45*IF(time_tot>time+20,20,IF(time_tot<20,(time*VLOOKUP(F45, list!$J$48:$K$50,2,))+(time_tot-time),((MIN(20,time)*VLOOKUP(F45, list!$J$48:$K$50,2,))+(time_tot-MIN(20,time))-IF(F45="Exponential",time_tot-20+0.217*time*(EXP(4.606*(20-time_tot)/time)-1),((time_tot-20)^2)*(0.5/time))))))))>=ABS(F28*E45*20),F28*E45*20,$F28*(IF(F45="Immediate",IF(E45>0,E45*MIN(20,time_tot),0),E45*IF(time_tot>time+20,20,IF(time_tot<20,(time*VLOOKUP(F45, list!$J$48:$K$50,2,))+(time_tot-time),((MIN(20,time)*VLOOKUP(F45, list!$J$48:$K$50,2,))+(time_tot-MIN(20,time))-IF(F45="Exponential",time_tot-20+0.217*time*(EXP(4.606*(20-time_tot)/time)-1),((time_tot-20)^2)*(0.5/time)))))))) | K45: =$C45*$O28 | L45: =$E45*$O28 | M45: =$G45+$I45+$K45 | N45: =H45+J45+L45 | O45: =$N45-$M45
B46: 6 | C46: ='2.LUC'!$N66 | D46: =VLOOKUP('2.LUC'!$O66, list!$I$48:$J$50,2,FALSE ) | E46: ='2.LUC'!$P66 | F46: =VLOOKUP('2.LUC'!$Q66, list!$I$48:$J$50,2,FALSE ) | G46: =$C46*$E29 | H46: =$E46*$E29 | I46: =IF(ABS($F29*(IF(D46="Immediate",IF(C46>0,C46*MIN(20,time_tot),0),C46*IF(time_tot>time+20,20,IF(time_tot<20,(time*VLOOKUP(D46, list!$J$48:$K$50,2,))+(time_tot-time),((MIN(20,time)*VLOOKUP(D46, list!$J$48:$K$50,2,))+(time_tot-MIN(20,time))-IF(D46="Exponential",time_tot-20+0.217*time*(EXP(4.606*(20-time_tot)/time)-1),((time_tot-20)^2)*(0.5/time))))))))>=ABS(F29*C46*20),F29*C46*20,$F29*(IF(D46="Immediate",IF(C46>0,C46*MIN(20,time_tot),0),C46*IF(time_tot>time+20,20,IF(time_tot<20,(time*VLOOKUP(D46, list!$J$48:$K$50,2,))+(time_tot-time),((MIN(20,time)*VLOOKUP(D46, list!$J$48:$K$50,2,))+(time_tot-MIN(20,time))-IF(D46="Exponential",time_tot-20+0.217*time*(EXP(4.606*(20-time_tot)/time)-1),((time_tot-20)^2)*(0.5/time)))))))) | J46: =IF(ABS($F29*(IF(F46="Immediate",IF(E46>0,E46*MIN(20,time_tot),0),E46*IF(time_tot>time+20,20,IF(time_tot<20,(time*VLOOKUP(F46, list!$J$48:$K$50,2,))+(time_tot-time),((MIN(20,time)*VLOOKUP(F46, list!$J$48:$K$50,2,))+(time_tot-MIN(20,time))-IF(F46="Exponential",time_tot-20+0.217*time*(EXP(4.606*(20-time_tot)/time)-1),((time_tot-20)^2)*(0.5/time))))))))>=ABS(F29*E46*20),F29*E46*20,$F29*(IF(F46="Immediate",IF(E46>0,E46*MIN(20,time_tot),0),E46*IF(time_tot>time+20,20,IF(time_tot<20,(time*VLOOKUP(F46, list!$J$48:$K$50,2,))+(time_tot-time),((MIN(20,time)*VLOOKUP(F46, list!$J$48:$K$50,2,))+(time_tot-MIN(20,time))-IF(F46="Exponential",time_tot-20+0.217*time*(EXP(4.606*(20-time_tot)/time)-1),((time_tot-20)^2)*(0.5/time)))))))) | K46: =$C46*$O29 | L46: =$E46*$O29 | M46: =$G46+$I46+$K46 | N46: =H46+J46+L46 | O46: =$N46-$M46
